Workbook

Sheet Model
A1: Six Peak Capital - Financial Projections
B2: 46023 | C2: 46054 | D2: 46082 | E2: 46113 | F2: 46143 | G2: 46174 | H2: 46204 | I2: 46235 | J2: 46266 | K2: 46296 | L2: 46327 | M2: 46357 | N2: 46388 | O2: 46419 | P2: 46447 | Q2: 46478 | R2: 46508 | S2: 46539 | T2: 46569 | U2: 46600 | V2: 46631 | W2: 46661 | X2: 46692 | Y2: 46722 | Z2: 46753 | AA2: 46784 | AB2: 46813 | AC2: 46844 | AD2: 46874 | AE2: 46905 | AF2: 46935 | AG2: 46966 | AH2: 46997 | AI2: 47027 | AJ2: 47058 | AK2: 47088 | AL2: 47119 | AM2: 47150 | AN2: 47178 | AO2: 47209 | AP2: 47239 | AQ2: 47270 | AR2: 47300 | AS2: 47331 | AT2: 47362 | AU2: 47392 | AV2: 47423 | AW2: 47453 | AX2: 47484 | AY2: 47515 | AZ2: 47543 | BA2: 47574 | BB2: 47604 | BC2: 47635 | BD2: 47665 | BE2: 47696 | BF2: 47727 | BG2: 47757 | BH2: 47788 | BI2: 47818 | BJ2: 47849 | BK2: 47880 | BL2: 47908 | BM2: 47939 | BN2: 47969 | BO2: 48000 | BP2: 48030 | BQ2: 48061 | BR2: 48092 | BS2: 48122 | BT2: 48153 | BU2: 48183 | BV2: 48214 | BW2: 48245 | BX2: 48274 | BY2: 48305 | BZ2: 48335 | CA2: 48366 | CB2: 48396 | CC2: 48427 | CD2: 48458 | CE2: 48488 | CF2: 48519 | CG2: 48549 | CH2: 48580 | CI2: 48611 | CJ2: 48639 | CK2: 48670 | CL2: 48700 | CM2: 48731 | CN2: 48761 | CO2: 48792 | CP2: 48823 | CQ2: 48853 | CR2: 48884 | CS2: 48914 | CT2: 48945 | CU2: 48976 | CV2: 49004 | CW2: 49035 | CX2: 49065 | CY2: 49096 | CZ2: 49126 | DA2: 49157 | DB2: 49188 | DC2: 49218 | DD2: 49249 | DE2: 49279
A3: Month # | B3: -2 | C3: -1 | D3: 0 | E3: 1 | F3: 2 | G3: 3 | H3: 4 | I3: 5 | J3: 6 | K3: 7 | L3: 8 | M3: 9 | N3: 10 | O3: 11 | P3: 12 | Q3: 13 | R3: 14 | S3: 15 | T3: 16 | U3: 17 | V3: 18 | W3: 19 | X3: 20 | Y3: 21 | Z3: 22 | AA3: 23 | AB3: 24 | AC3: 25 | AD3: 26 | AE3: 27 | AF3: 28 | AG3: 29 | AH3: 30 | AI3: 31 | AJ3: 32 | AK3: 33 | AL3: 34 | AM3: 35 | AN3: 36 | AO3: 37 | AP3: 38 | AQ3: 39 | AR3: 40 | AS3: 41 | AT3: 42 | AU3: 43 | AV3: 44 | AW3: 45 | AX3: 46 | AY3: 47 | AZ3: 48 | BA3: 49 | BB3: 50 | BC3: 51 | BD3: 52 | BE3: 53 | BF3: 54 | BG3: 55 | BH3: 56 | BI3: 57 | BJ3: 58 | BK3: 59 | BL3: 60 | BM3: 61 | BN3: 62 | BO3: 63 | BP3: 64 | BQ3: 65 | BR3: 66 | BS3: 67 | BT3: 68 | BU3: 69 | BV3: 70 | BW3: 71 | BX3: 72 | BY3: 73 | BZ3: 74 | CA3: 75 | CB3: 76 | CC3: 77 | CD3: 78 | CE3: 79 | CF3: 80 | CG3: 81 | CH3: 82 | CI3: 83 | CJ3: 84 | CK3: 85 | CL3: 86 | CM3: 87 | CN3: 88 | CO3: 89 | CP3: 90 | CQ3: 91 | CR3: 92 | CS3: 93 | CT3: 94 | CU3: 95 | CV3: 96 | CW3: 97 | CX3: 98 | CY3: 99 | CZ3: 100 | DA3: 101 | DB3: 102 | DC3: 103 | DD3: 104 | DE3: 105
B4: =IF(ISBLANK(Actuals!C14),"","Actuals") -> Actuals | C4: =IF(ISBLANK(Actuals!D14),"","Actuals") -> Actuals | D4: =IF(ISBLANK(Actuals!E14),"","Actuals") -> Actuals | E4: =IF(ISBLANK(Actuals!F14),"","Actuals") -> Actuals | F4: =IF(ISBLANK(Actuals!G14),"","Actuals") -> Actuals | G4: =IF(ISBLANK(Actuals!H14),"","Actuals") | H4: =IF(ISBLANK(Actuals!I14),"","Actuals") | I4: =IF(ISBLANK(Actuals!J14),"","Actuals") | ... DE4: =IF(ISBLANK(Actuals!DF14),"","Actuals")
A5: YTD Actuals Snapshot:
F6: =IF(LEN(IF(Projects!$G$2="Yes",Projects!$A$2,"")&IF(Projects!$G$3="Yes",", "&Projects!$A$3,"")&IF(Projects!$G$4="Yes",", "&Projects!$A$4,"")&IF(Projects!$G$5="Yes",", "&Projects!$A$5,"")&IF(Projects!$G$6="Yes",", "&Projects!$A$6,""))>0,IF(LEFT(IF(Projects!$G$2="Yes",Projects!$A$2,"")&IF(Projects!$G$3="Yes",", "&Projects!$A$3,"")&IF(Projects!$G$4="Yes",", "&Projects!$A$4,"")&IF(Projects!$G$5="Yes",", "&Projects!$A$5,"")&IF(Projects!$G$6="Yes",", "&Projects!$A$6,""),2)=", ",MID(IF(Projects!$G$2="Yes",Projects!$A$2,"")&IF(Projects!$G$3="Yes",", "&Projects!$A$3,"")&IF(Projects!$G$4="Yes",", "&Projects!$A$4,"")&IF(Projects!$G$5="Yes",", "&Projects!$A$5,"")&IF(Projects!$G$6="Yes",", "&Projects!$A$6,""),3,1000),IF(Projects!$G$2="Yes",Projects!$A$2,"")&IF(Projects!$G$3="Yes",", "&Projects!$A$3,"")&IF(Projects!$G$4="Yes",", "&Projects!$A$4,"")&IF(Projects!$G$5="Yes",", "&Projects!$A$5,"")&IF(Projects!$G$6="Yes",", "&Projects!$A$6,"")),"") -> Crenshaw, Ramsgate, Califa, Whipple, Nelrose | H6: =IF(Projects!$G$7="Yes",Projects!$A$7,"") -> Francis | I6: =IF(Projects!$G$11="Yes",Projects!$A$11,"") -> Klump | J6: =IF(Projects!$G$12="Yes",Projects!$A$12,"") -> Scott | K6: =IF(LEN(IF(Projects!$G$8="Yes",Projects!$A$8,"")&IF(Projects!$G$9="Yes",", "&Projects!$A$9,""))>0,IF(LEFT(IF(Projects!$G$8="Yes",Projects!$A$8,"")&IF(Projects!$G$9="Yes",", "&Projects!$A$9,""),2)=", ",MID(IF(Projects!$G$8="Yes",Projects!$A$8,"")&IF(Projects!$G$9="Yes",", "&Projects!$A$9,""),3,1000),IF(Projects!$G$8="Yes",Projects!$A$8,"")&IF(Projects!$G$9="Yes",", "&Projects!$A$9,"")),"") -> Lexington, Denny | L6: =IF(Projects!$G$10="Yes",Projects!$A$10,"") -> Acama | Q6: =IF(Projects!$G$13="Yes",Projects!$A$13,"") -> Reseda | T6: =IF(Projects!$G$17="Yes",Projects!$A$17,"") | V6: =IF(Projects!$G$18="Yes",Projects!$A$18,"") | Y6: =IF(Projects!$G$19="Yes",Projects!$A$19,"") | AB6: =IF(Projects!$G$20="Yes",Projects!$A$20,"") | AE6: =IF(LEN(IF(Projects!$G$14="Yes",Projects!$A$14,"")&IF(Projects!$G$21="Yes",", "&Projects!$A$21,""))>0,IF(LEFT(IF(Projects!$G$14="Yes",Projects!$A$14,"")&IF(Projects!$G$21="Yes",", "&Projects!$A$21,""),2)=", ",MID(IF(Projects!$G$14="Yes",Projects!$A$14,"")&IF(Projects!$G$21="Yes",", "&Projects!$A$21,""),3,1000),IF(Projects!$G$14="Yes",Projects!$A$14,"")&IF(Projects!$G$21="Yes",", "&Projects!$A$21,"")),"") -> 3rd St | AI6: =IF(Projects!$G$22="Yes",Projects!$A$22,"") | AL6: =IF(Projects!$G$23="Yes",Projects!$A$23,"") | AO6: =IF(Projects!$G$24="Yes",Projects!$A$24,"") | AR6: =IF(Projects!$G$25="Yes",Projects!$A$25,"") | AT6: =IF(Projects!$G$26="Yes",Projects!$A$26,"") | AV6: =IF(Projects!$G$27="Yes",Projects!$A$27,"") | AX6: =IF(Projects!$G$28="Yes",Projects!$A$28,"") | AZ6: =IF(Projects!$G$29="Yes",Projects!$A$29,"") | BB6: =IF(Projects!$G$30="Yes",Projects!$A$30,"") | BD6: =IF(Projects!$G$31="Yes",Projects!$A$31,"") | BF6: =IF(Projects!$G$32="Yes",Projects!$A$32,"") | BH6: =IF(Projects!$G$33="Yes",Projects!$A$33,"") | BJ6: =IF(Projects!$G$34="Yes",Projects!$A$34,"") | BL6: =IF(Projects!$G$35="Yes",Projects!$A$35,"") | BN6: =IF(Projects!$G$36="Yes",Projects!$A$36,"") | BP6: =IF(Projects!$G$37="Yes",Projects!$A$37,"") | BR6: =IF(Projects!$G$38="Yes",Projects!$A$38,"") | BT6: =IF(Projects!$G$39="Yes",Projects!$A$39,"") | BV6: =IF(Projects!$G$40="Yes",Projects!$A$40,"") | BX6: =IF(Projects!$G$41="Yes",Projects!$A$41,"") | BZ6: =IF(Projects!$G$42="Yes",Projects!$A$42,"") | CB6: =IF(Projects!$G$43="Yes",Projects!$A$43,"") | CD6: =IF(Projects!$G$44="Yes",Projects!$A$44,"") | CF6: =IF(Projects!$G$45="Yes",Projects!$A$45,"") | CH6: =IF(Projects!$G$46="Yes",Projects!$A$46,"")
A8: GC Revenue
A10: Other GC Income | B10: =IF(ISBLANK(Actuals!C8),0,Actuals!C8) -> 116367.35 | C10: =IF(ISBLANK(Actuals!D8),0,Actuals!D8) -> 138804.22 | D10: =IF(ISBLANK(Actuals!E8),0,Actuals!E8) -> 219366.88 | E10: =IF(ISBLANK(Actuals!F8),(SUMPRODUCT((Projects!$G$2:$G$14="Yes")*(1>=Projects!$C$2:$C$14)*(1<Projects!$C$2:$C$14+Projects!$D$2:$D$14)*Projects!$B$2:$B$14*Assumptions!$B$10/Projects!$D$2:$D$14*0.95)+SUMPRODUCT((Projects!$G$2:$G$14="Yes")*(1=Projects!$C$2:$C$14+Projects!$D$2:$D$14-1)*Projects!$B$2:$B$14*Assumptions!$B$10*0.05)+SUMPRODUCT((Projects!$G$17:$G$46="Yes")*(1>=Projects!$C$17:$C$46)*(1<Projects!$C$17:$C$46+Projects!$D$17:$D$46)*Projects!$B$17:$B$46*Assumptions!$B$10/Projects!$D$17:$D$46*0.95)+SUMPRODUCT((Projects!$G$17:$G$46="Yes")*(1=Projects!$C$17:$C$46+Projects!$D$17:$D$46-1)*Projects!$B$17:$B$46*Assumptions!$B$10*0.05))+(SUMPRODUCT((Projects!$G$2:$G$14="Yes")*(1>=Projects!$C$2:$C$14)*(1<Projects!$C$2:$C$14+Projects!$D$2:$D$14)*Projects!$B$2:$B$14*Assumptions!$B$12/Projects!$D$2:$D$14*0.95)+SUMPRODUCT((Projects!$G$2:$G$14="Yes")*(1=Projects!$C$2:$C$14+Projects!$D$2:$D$14-1)*Projects!$B$2:$B$14*Assumptions!$B$12*0.05)+SUMPRODUCT((Projects!$G$17:$G$46="Yes")*(1>=Projects!$C$17:$C$46)*(1<Projects!$C$17:$C$46+Projects!$D$17:$D$46)*Projects!$B$17:$B$46*Assumptions!$B$12/Projects!$D$17:$D$46*0.95)+SUMPRODUCT((Projects!$G$17:$G$46="Yes")*(1=Projects!$C$17:$C$46+Projects!$D$17:$D$46-1)*Projects!$B$17:$B$46*Assumptions!$B$12*0.05)),Actuals!F8) -> 212079.14 | F10: =IF(ISBLANK(Actuals!G8),295126.83*Curves!C$6/SUM(Curves!$C$6:$I$6)+1008656.9*Curves!C$7/SUM(Curves!$C$7:$Q$7)+692704.95*Curves!C$8/SUM(Curves!$C$8:$P$8)+790610.91*Curves!C$9/SUM(Curves!$C$9:$P$9)+188945.64*Curves!C$4/SUM(Curves!$C$4:$T$4)+SUMPRODUCT((Projects!$G$7:$G$14="Yes")*(2>=Projects!$C$7:$C$14)*(2<Projects!$C$7:$C$14+Projects!$D$7:$D$14)*Projects!$B$7:$B$14*Assumptions!$B$10/Projects!$D$7:$D$14*0.95)+SUMPRODUCT((Projects!$G$7:$G$14="Yes")*(2=Projects!$C$7:$C$14+Projects!$D$7:$D$14-1)*Projects!$B$7:$B$14*Assumptions!$B$10*0.05)+SUMPRODUCT((Projects!$G$17:$G$46="Yes")*(2>=Projects!$C$17:$C$46)*(2<Projects!$C$17:$C$46+Projects!$D$17:$D$46)*Projects!$B$17:$B$46*Assumptions!$B$10/Projects!$D$17:$D$46*0.95)+SUMPRODUCT((Projects!$G$17:$G$46="Yes")*(2=Projects!$C$17:$C$46+Projects!$D$17:$D$46-1)*Projects!$B$17:$B$46*Assumptions!$B$10*0.05)+SUMPRODUCT((Projects!$G$7:$G$14="Yes")*(2>=Projects!$C$7:$C$14)*(2<Projects!$C$7:$C$14+Projects!$D$7:$D$14)*Projects!$B$7:$B$14*Assumptions!$B$12/Projects!$D$7:$D$14*0.95)+SUMPRODUCT((Projects!$G$7:$G$14="Yes")*(2=Projects!$C$7:$C$14+Projects!$D$7:$D$14-1)*Projects!$B$7:$B$14*Assumptions!$B$12*0.05)+SUMPRODUCT((Projects!$G$17:$G$46="Yes")*(2>=Projects!$C$17:$C$46)*(2<Projects!$C$17:$C$46+Projects!$D$17:$D$46)*Projects!$B$17:$B$46*Assumptions!$B$12/Projects!$D$17:$D$46*0.95)+SUMPRODUCT((Projects!$G$17:$G$46="Yes")*(2=Projects!$C$17:$C$46+Projects!$D$17:$D$46-1)*Projects!$B$17:$B$46*Assumptions!$B$12*0.05),Actuals!G8) -> 267726.14 | G10: =IF(ISBLANK(Actuals!H8),284774.58*Curves!D$6/SUM(Curves!$D$6:$I$6)+945615.84*Curves!D$7/SUM(Curves!$D$7:$Q$7)+646524.62*Curves!D$8/SUM(Curves!$D$8:$P$8)+737903.52*Curves!D$9/SUM(Curves!$D$9:$P$9)+175334.53*Curves!D$4/SUM(Curves!$D$4:$T$4)+SUMPRODUCT((Projects!$G$7:$G$14="Yes")*(3>=Projects!$C$7:$C$14)*(3<Projects!$C$7:$C$14+Projects!$D$7:$D$14)*Projects!$B$7:$B$14*Assumptions!$B$10/Projects!$D$7:$D$14*0.95)+SUMPRODUCT((Projects!$G$7:$G$14="Yes")*(3=Projects!$C$7:$C$14+Projects!$D$7:$D$14-1)*Projects!$B$7:$B$14*Assumptions!$B$10*0.05)+SUMPRODUCT((Projects!$G$17:$G$46="Yes")*(3>=Projects!$C$17:$C$46)*(3<Projects!$C$17:$C$46+Projects!$D$17:$D$46)*Projects!$B$17:$B$46*Assumptions!$B$10/Projects!$D$17:$D$46*0.95)+SUMPRODUCT((Projects!$G$17:$G$46="Yes")*(3=Projects!$C$17:$C$46+Projects!$D$17:$D$46-1)*Projects!$B$17:$B$46*Assumptions!$B$10*0.05)+SUMPRODUCT((Projects!$G$7:$G$14="Yes")*(3>=Projects!$C$7:$C$14)*(3<Projects!$C$7:$C$14+Projects!$D$7:$D$14)*Projects!$B$7:$B$14*Assumptions!$B$12/Projects!$D$7:$D$14*0.95)+SUMPRODUCT((Projects!$G$7:$G$14="Yes")*(3=Projects!$C$7:$C$14+Projects!$D$7:$D$14-1)*Projects!$B$7:$B$14*Assumptions!$B$12*0.05)+SUMPRODUCT((Projects!$G$17:$G$46="Yes")*(3>=Projects!$C$17:$C$46)*(3<Projects!$C$17:$C$46+Projects!$D$17:$D$46)*Projects!$B$17:$B$46*Assumptions!$B$12/Projects!$D$17:$D$46*0.95)+SUMPRODUCT((Projects!$G$17:$G$46="Yes")*(3=Projects!$C$17:$C$46+Projects!$D$17:$D$46-1)*Projects!$B$17:$B$46*Assumptions!$B$12*0.05),Actuals!H8) -> 279422.58 | H10: =IF(ISBLANK(Actuals!I8),284774.58*Curves!E$6/SUM(Curves!$D$6:$I$6)+945615.84*Curves!E$7/SUM(Curves!$D$7:$Q$7)+646524.62*Curves!E$8/SUM(Curves!$D$8:$P$8)+737903.52*Curves!E$9/SUM(Curves!$D$9:$P$9)+175334.53*Curves!E$4/SUM(Curves!$D$4:$T$4)+SUMPRODUCT((Projects!$G$7:$G$14="Yes")*(4>=Projects!$C$7:$C$14)*(4<Projects!$C$7:$C$14+Projects!$D$7:$D$14)*Projects!$B$7:$B$14*Assumptions!$B$10/Projects!$D$7:$D$14*0.95)+SUMPRODUCT((Projects!$G$7:$G$14="Yes")*(4=Projects!$C$7:$C$14+Projects!$D$7:$D$14-1)*Projects!$B$7:$B$14*Assumptions!$B$10*0.05)+SUMPRODUCT((Projects!$G$17:$G$46="Yes")*(4>=Projects!$C$17:$C$46)*(4<Projects!$C$17:$C$46+Projects!$D$17:$D$46)*Projects!$B$17:$B$46*Assumptions!$B$10/Projects!$D$17:$D$46*0.95)+SUMPRODUCT((Projects!$G$17:$G$46="Yes")*(4=Projects!$C$17:$C$46+Projects!$D$17:$D$46-1)*Projects!$B$17:$B$46*Assumptions!$B$10*0.05)+SUMPRODUCT((Projects!$G$7:$G$14="Yes")*(4>=Projects!$C$7:$C$14)*(4<Projects!$C$7:$C$14+Projects!$D$7:$D$14)*Projects!$B$7:$B$14*Assumptions!$B$12/Projects!$D$7:$D$14*0.95)+SUMPRODUCT((Projects!$G$7:$G$14="Yes")*(4=Projects!$C$7:$C$14+Projects!$D$7:$D$14-1)*Projects!$B$7:$B$14*Assumptions!$B$12*0.05)+SUMPRODUCT((Projects!$G$17:$G$46="Yes")*(4>=Projects!$C$17:$C$46)*(4<Projects!$C$17:$C$46+Projects!$D$17:$D$46)*Projects!$B$17:$B$46*Assumptions!$B$12/Projects!$D$17:$D$46*0.95)+SUMPRODUCT((Projects!$G$17:$G$46="Yes")*(4=Projects!$C$17:$C$46+Projects!$D$17:$D$46-1)*Projects!$B$17:$B$46*Assumptions!$B$12*0.05),Actuals!I8) -> 283248.57 | I10: =IF(ISBLANK(Actuals!J8),284774.58*Curves!F$6/SUM(Curves!$D$6:$I$6)+945615.84*Curves!F$7/SUM(Curves!$D$7:$Q$7)+646524.62*Curves!F$8/SUM(Curves!$D$8:$P$8)+737903.52*Curves!F$9/SUM(Curves!$D$9:$P$9)+175334.53*Curves!F$4/SUM(Curves!$D$4:$T$4)+SUMPRODUCT((Projects!$G$7:$G$14="Yes")*(5>=Projects!$C$7:$C$14)*(5<Projects!$C$7:$C$14+Projects!$D$7:$D$14)*Projects!$B$7:$B$14*Assumptions!$B$10/Projects!$D$7:$D$14*0.95)+SUMPRODUCT((Projects!$G$7:$G$14="Yes")*(5=Projects!$C$7:$C$14+Projects!$D$7:$D$14-1)*Projects!$B$7:$B$14*Assumptions!$B$10*0.05)+SUMPRODUCT((Projects!$G$17:$G$46="Yes")*(5>=Projects!$C$17:$C$46)*(5<Projects!$C$17:$C$46+Projects!$D$17:$D$46)*Projects!$B$17:$B$46*Assumptions!$B$10/Projects!$D$17:$D$46*0.95)+SUMPRODUCT((Projects!$G$17:$G$46="Yes")*(5=Projects!$C$17:$C$46+Projects!$D$17:$D$46-1)*Projects!$B$17:$B$46*Assumptions!$B$10*0.05)+SUMPRODUCT((Projects!$G$7:$G$14="Yes")*(5>=Projects!$C$7:$C$14)*(5<Projects!$C$7:$C$14+Projects!$D$7:$D$14)*Projects!$B$7:$B$14*Assumptions!$B$12/Projects!$D$7:$D$14*0.95)+SUMPRODUCT((Projects!$G$7:$G$14="Yes")*(5=Projects!$C$7:$C$14+Projects!$D$7:$D$14-1)*Projects!$B$7:$B$14*Assumptions!$B$12*0.05)+SUMPRODUCT((Projects!$G$17:$G$46="Yes")*(5>=Projects!$C$17:$C$46)*(5<Projects!$C$17:$C$46+Projects!$D$17:$D$46)*Projects!$B$17:$B$46*Assumptions!$B$12/Projects!$D$17:$D$46*0.95)+SUMPRODUCT((Projects!$G$17:$G$46="Yes")*(5=Projects!$C$17:$C$46+Projects!$D$17:$D$46-1)*Projects!$B$17:$B$46*Assumptions!$B$12*0.05),Actuals!J8) -> 282701.4 | J10: =IF(ISBLANK(Actuals!K8),284774.58*Curves!G$6/SUM(Curves!$D$6:$I$6)+945615.84*Curves!G$7/SUM(Curves!$D$7:$Q$7)+646524.62*Curves!G$8/SUM(Curves!$D$8:$P$8)+737903.52*Curves!G$9/SUM(Curves!$D$9:$P$9)+175334.53*Curves!G$4/SUM(Curves!$D$4:$T$4)+SUMPRODUCT((Projects!$G$7:$G$14="Yes")*(6>=Projects!$C$7:$C$14)*(6<Projects!$C$7:$C$14+Projects!$D$7:$D$14)*Projects!$B$7:$B$14*Assumptions!$B$10/Projects!$D$7:$D$14*0.95)+SUMPRODUCT((Projects!$G$7:$G$14="Yes")*(6=Projects!$C$7:$C$14+Projects!$D$7:$D$14-1)*Projects!$B$7:$B$14*Assumptions!$B$10*0.05)+SUMPRODUCT((Projects!$G$17:$G$46="Yes")*(6>=Projects!$C$17:$C$46)*(6<Projects!$C$17:$C$46+Projects!$D$17:$D$46)*Projects!$B$17:$B$46*Assumptions!$B$10/Projects!$D$17:$D$46*0.95)+SUMPRODUCT((Projects!$G$17:$G$46="Yes")*(6=Projects!$C$17:$C$46+Projects!$D$17:$D$46-1)*Projects!$B$17:$B$46*Assumptions!$B$10*0.05)+SUMPRODUCT((Projects!$G$7:$G$14="Yes")*(6>=Projects!$C$7:$C$14)*(6<Projects!$C$7:$C$14+Projects!$D$7:$D$14)*Projects!$B$7:$B$14*Assumptions!$B$12/Projects!$D$7:$D$14*0.95)+SUMPRODUCT((Projects!$G$7:$G$14="Yes")*(6=Projects!$C$7:$C$14+Projects!$D$7:$D$14-1)*Projects!$B$7:$B$14*Assumptions!$B$12*0.05)+SUMPRODUCT((Projects!$G$17:$G$46="Yes")*(6>=Projects!$C$17:$C$46)*(6<Projects!$C$17:$C$46+Projects!$D$17:$D$46)*Projects!$B$17:$B$46*Assumptions!$B$12/Projects!$D$17:$D$46*0.95)+SUMPRODUCT((Projects!$G$17:$G$46="Yes")*(6=Projects!$C$17:$C$46+Projects!$D$17:$D$46-1)*Projects!$B$17:$B$46*Assumptions!$B$12*0.05),Actuals!K8) -> 371166.74 | K10: =IF(ISBLANK(Actuals!L8),284774.58*Curves!H$6/SUM(Curves!$D$6:$I$6)+945615.84*Curves!H$7/SUM(Curves!$D$7:$Q$7)+646524.62*Curves!H$8/SUM(Curves!$D$8:$P$8)+737903.52*Curves!H$9/SUM(Curves!$D$9:$P$9)+175334.53*Curves!H$4/SUM(Curves!$D$4:$T$4)+SUMPRODUCT((Projects!$G$7:$G$14="Yes")*(7>=Projects!$C$7:$C$14)*(7<Projects!$C$7:$C$14+Projects!$D$7:$D$14)*Projects!$B$7:$B$14*Assumptions!$B$10/Projects!$D$7:$D$14*0.95)+SUMPRODUCT((Projects!$G$7:$G$14="Yes")*(7=Projects!$C$7:$C$14+Projects!$D$7:$D$14-1)*Projects!$B$7:$B$14*Assumptions!$B$10*0.05)+SUMPRODUCT((Projects!$G$17:$G$46="Yes")*(7>=Projects!$C$17:$C$46)*(7<Projects!$C$17:$C$46+Projects!$D$17:$D$46)*Projects!$B$17:$B$46*Assumptions!$B$10/Projects!$D$17:$D$46*0.95)+SUMPRODUCT((Projects!$G$17:$G$46="Yes")*(7=Projects!$C$17:$C$46+Projects!$D$17:$D$46-1)*Projects!$B$17:$B$46*Assumptions!$B$10*0.05)+SUMPRODUCT((Projects!$G$7:$G$14="Yes")*(7>=Projects!$C$7:$C$14)*(7<Projects!$C$7:$C$14+Projects!$D$7:$D$14)*Projects!$B$7:$B$14*Assumptions!$B$12/Projects!$D$7:$D$14*0.95)+SUMPRODUCT((Projects!$G$7:$G$14="Yes")*(7=Projects!$C$7:$C$14+Projects!$D$7:$D$14-1)*Projects!$B$7:$B$14*Assumptions!$B$12*0.05)+SUMPRODUCT((Projects!$G$17:$G$46="Yes")*(7>=Projects!$C$17:$C$46)*(7<Projects!$C$17:$C$46+Projects!$D$17:$D$46)*Projects!$B$17:$B$46*Assumptions!$B$12/Projects!$D$17:$D$46*0.95)+SUMPRODUCT((Projects!$G$17:$G$46="Yes")*(7=Projects!$C$17:$C$46+Projects!$D$17:$D$46-1)*Projects!$B$17:$B$46*Assumptions!$B$12*0.05),Actuals!L8) -> 501765.87 | L10: =IF(ISBLANK(Actuals!M8),284774.58*Curves!I$6/SUM(Curves!$D$6:$I$6)+945615.84*Curves!I$7/SUM(Curves!$D$7:$Q$7)+646524.62*Curves!I$8/SUM(Curves!$D$8:$P$8)+737903.52*Curves!I$9/SUM(Curves!$D$9:$P$9)+175334.53*Curves!I$4/SUM(Curves!$D$4:$T$4)+SUMPRODUCT((Projects!$G$7:$G$14="Yes")*(8>=Projects!$C$7:$C$14)*(8<Projects!$C$7:$C$14+Projects!$D$7:$D$14)*Projects!$B$7:$B$14*Assumptions!$B$10/Projects!$D$7:$D$14*0.95)+SUMPRODUCT((Projects!$G$7:$G$14="Yes")*(8=Projects!$C$7:$C$14+Projects!$D$7:$D$14-1)*Projects!$B$7:$B$14*Assumptions!$B$10*0.05)+SUMPRODUCT((Projects!$G$17:$G$46="Yes")*(8>=Projects!$C$17:$C$46)*(8<Projects!$C$17:$C$46+Projects!$D$17:$D$46)*Projects!$B$17:$B$46*Assumptions!$B$10/Projects!$D$17:$D$46*0.95)+SUMPRODUCT((Projects!$G$17:$G$46="Yes")*(8=Projects!$C$17:$C$46+Projects!$D$17:$D$46-1)*Projects!$B$17:$B$46*Assumptions!$B$10*0.05)+SUMPRODUCT((Projects!$G$7:$G$14="Yes")*(8>=Projects!$C$7:$C$14)*(8<Projects!$C$7:$C$14+Projects!$D$7:$D$14)*Projects!$B$7:$B$14*Assumptions!$B$12/Projects!$D$7:$D$14*0.95)+SUMPRODUCT((Projects!$G$7:$G$14="Yes")*(8=Projects!$C$7:$C$14+Projects!$D$7:$D$14-1)*Projects!$B$7:$B$14*Assumptions!$B$12*0.05)+SUMPRODUCT((Projects!$G$17:$G$46="Yes")*(8>=Projects!$C$17:$C$46)*(8<Projects!$C$17:$C$46+Projects!$D$17:$D$46)*Projects!$B$17:$B$46*Assumptions!$B$12/Projects!$D$17:$D$46*0.95)+SUMPRODUCT((Projects!$G$17:$G$46="Yes")*(8=Projects!$C$17:$C$46+Projects!$D$17:$D$46-1)*Projects!$B$17:$B$46*Assumptions!$B$12*0.05),Actuals!M8) -> 545758.03 | M10: =IF(ISBLANK(Actuals!N8),945615.84*Curves!J$7/SUM(Curves!$D$7:$Q$7)+646524.62*Curves!J$8/SUM(Curves!$D$8:$P$8)+737903.52*Curves!J$9/SUM(Curves!$D$9:$P$9)+175334.53*Curves!J$4/SUM(Curves!$D$4:$T$4)+SUMPRODUCT((Projects!$G$7:$G$14="Yes")*(9>=Projects!$C$7:$C$14)*(9<Projects!$C$7:$C$14+Projects!$D$7:$D$14)*Projects!$B$7:$B$14*Assumptions!$B$10/Projects!$D$7:$D$14*0.95)+SUMPRODUCT((Projects!$G$7:$G$14="Yes")*(9=Projects!$C$7:$C$14+Projects!$D$7:$D$14-1)*Projects!$B$7:$B$14*Assumptions!$B$10*0.05)+SUMPRODUCT((Projects!$G$17:$G$46="Yes")*(9>=Projects!$C$17:$C$46)*(9<Projects!$C$17:$C$46+Projects!$D$17:$D$46)*Projects!$B$17:$B$46*Assumptions!$B$10/Projects!$D$17:$D$46*0.95)+SUMPRODUCT((Projects!$G$17:$G$46="Yes")*(9=Projects!$C$17:$C$46+Projects!$D$17:$D$46-1)*Projects!$B$17:$B$46*Assumptions!$B$10*0.05)+SUMPRODUCT((Projects!$G$7:$G$14="Yes")*(9>=Projects!$C$7:$C$14)*(9<Projects!$C$7:$C$14+Projects!$D$7:$D$14)*Projects!$B$7:$B$14*Assumptions!$B$12/Projects!$D$7:$D$14*0.95)+SUMPRODUCT((Projects!$G$7:$G$14="Yes")*(9=Projects!$C$7:$C$14+Projects!$D$7:$D$14-1)*Projects!$B$7:$B$14*Assumptions!$B$12*0.05)+SUMPRODUCT((Projects!$G$17:$G$46="Yes")*(9>=Projects!$C$17:$C$46)*(9<Projects!$C$17:$C$46+Projects!$D$17:$D$46)*Projects!$B$17:$B$46*Assumptions!$B$12/Projects!$D$17:$D$46*0.95)+SUMPRODUCT((Projects!$G$17:$G$46="Yes")*(9=Projects!$C$17:$C$46+Projects!$D$17:$D$46-1)*Projects!$B$17:$B$46*Assumptions!$B$12*0.05),Actuals!N8) -> 501958.06 | N10: =IF(ISBLANK(Actuals!O8),945615.84*Curves!K$7/SUM(Curves!$D$7:$Q$7)+646524.62*Curves!K$8/SUM(Curves!$D$8:$P$8)+737903.52*Curves!K$9/SUM(Curves!$D$9:$P$9)+175334.53*Curves!K$4/SUM(Curves!$D$4:$T$4)+SUMPRODUCT((Projects!$G$7:$G$14="Yes")*(10>=Projects!$C$7:$C$14)*(10<Projects!$C$7:$C$14+Projects!$D$7:$D$14)*Projects!$B$7:$B$14*Assumptions!$B$10/Projects!$D$7:$D$14*0.95)+SUMPRODUCT((Projects!$G$7:$G$14="Yes")*(10=Projects!$C$7:$C$14+Projects!$D$7:$D$14-1)*Projects!$B$7:$B$14*Assumptions!$B$10*0.05)+SUMPRODUCT((Projects!$G$17:$G$46="Yes")*(10>=Projects!$C$17:$C$46)*(10<Projects!$C$17:$C$46+Projects!$D$17:$D$46)*Projects!$B$17:$B$46*Assumptions!$B$10/Projects!$D$17:$D$46*0.95)+SUMPRODUCT((Projects!$G$17:$G$46="Yes")*(10=Projects!$C$17:$C$46+Projects!$D$17:$D$46-1)*Projects!$B$17:$B$46*Assumptions!$B$10*0.05)+SUMPRODUCT((Projects!$G$7:$G$14="Yes")*(10>=Projects!$C$7:$C$14)*(10<Projects!$C$7:$C$14+Projects!$D$7:$D$14)*Projects!$B$7:$B$14*Assumptions!$B$12/Projects!$D$7:$D$14*0.95)+SUMPRODUCT((Projects!$G$7:$G$14="Yes")*(10=Projects!$C$7:$C$14+Projects!$D$7:$D$14-1)*Projects!$B$7:$B$14*Assumptions!$B$12*0.05)+SUMPRODUCT((Projects!$G$17:$G$46="Yes")*(10>=Projects!$C$17:$C$46)*(10<Projects!$C$17:$C$46+Projects!$D$17:$D$46)*Projects!$B$17:$B$46*Assumptions!$B$12/Projects!$D$17:$D$46*0.95)+SUMPRODUCT((Projects!$G$17:$G$46="Yes")*(10=Projects!$C$17:$C$46+Projects!$D$17:$D$46-1)*Projects!$B$17:$B$46*Assumptions!$B$12*0.05),Actuals!O8) -> 486345.86 | O10: =IF(ISBLANK(Actuals!P8),945615.84*Curves!L$7/SUM(Curves!$D$7:$Q$7)+646524.62*Curves!L$8/SUM(Curves!$D$8:$P$8)+737903.52*Curves!L$9/SUM(Curves!$D$9:$P$9)+175334.53*Curves!L$4/SUM(Curves!$D$4:$T$4)+SUMPRODUCT((Projects!$G$7:$G$14="Yes")*(11>=Projects!$C$7:$C$14)*(11<Projects!$C$7:$C$14+Projects!$D$7:$D$14)*Projects!$B$7:$B$14*Assumptions!$B$10/Projects!$D$7:$D$14*0.95)+SUMPRODUCT((Projects!$G$7:$G$14="Yes")*(11=Projects!$C$7:$C$14+Projects!$D$7:$D$14-1)*Projects!$B$7:$B$14*Assumptions!$B$10*0.05)+SUMPRODUCT((Projects!$G$17:$G$46="Yes")*(11>=Projects!$C$17:$C$46)*(11<Projects!$C$17:$C$46+Projects!$D$17:$D$46)*Projects!$B$17:$B$46*Assumptions!$B$10/Projects!$D$17:$D$46*0.95)+SUMPRODUCT((Projects!$G$17:$G$46="Yes")*(11=Projects!$C$17:$C$46+Projects!$D$17:$D$46-1)*Projects!$B$17:$B$46*Assumptions!$B$10*0.05)+SUMPRODUCT((Projects!$G$7:$G$14="Yes")*(11>=Projects!$C$7:$C$14)*(11<Projects!$C$7:$C$14+Projects!$D$7:$D$14)*Projects!$B$7:$B$14*Assumptions!$B$12/Projects!$D$7:$D$14*0.95)+SUMPRODUCT((Projects!$G$7:$G$14="Yes")*(11=Projects!$C$7:$C$14+Projects!$D$7:$D$14-1)*Projects!$B$7:$B$14*Assumptions!$B$12*0.05)+SUMPRODUCT((Projects!$G$17:$G$46="Yes")*(11>=Projects!$C$17:$C$46)*(11<Projects!$C$17:$C$46+Projects!$D$17:$D$46)*Projects!$B$17:$B$46*Assumptions!$B$12/Projects!$D$17:$D$46*0.95)+SUMPRODUCT((Projects!$G$17:$G$46="Yes")*(11=Projects!$C$17:$C$46+Projects!$D$17:$D$46-1)*Projects!$B$17:$B$46*Assumptions!$B$12*0.05),Actuals!P8) -> 468164.35 | P10: =IF(ISBLANK(Actuals!Q8),945615.84*Curves!M$7/SUM(Curves!$D$7:$Q$7)+646524.62*Curves!M$8/SUM(Curves!$D$8:$P$8)+737903.52*Curves!M$9/SUM(Curves!$D$9:$P$9)+175334.53*Curves!M$4/SUM(Curves!$D$4:$T$4)+SUMPRODUCT((Projects!$G$7:$G$14="Yes")*(12>=Projects!$C$7:$C$14)*(12<Projects!$C$7:$C$14+Projects!$D$7:$D$14)*Projects!$B$7:$B$14*Assumptions!$B$10/Projects!$D$7:$D$14*0.95)+SUMPRODUCT((Projects!$G$7:$G$14="Yes")*(12=Projects!$C$7:$C$14+Projects!$D$7:$D$14-1)*Projects!$B$7:$B$14*Assumptions!$B$10*0.05)+SUMPRODUCT((Projects!$G$17:$G$46="Yes")*(12>=Projects!$C$17:$C$46)*(12<Projects!$C$17:$C$46+Projects!$D$17:$D$46)*Projects!$B$17:$B$46*Assumptions!$B$10/Projects!$D$17:$D$46*0.95)+SUMPRODUCT((Projects!$G$17:$G$46="Yes")*(12=Projects!$C$17:$C$46+Projects!$D$17:$D$46-1)*Projects!$B$17:$B$46*Assumptions!$B$10*0.05)+SUMPRODUCT((Projects!$G$7:$G$14="Yes")*(12>=Projects!$C$7:$C$14)*(12<Projects!$C$7:$C$14+Projects!$D$7:$D$14)*Projects!$B$7:$B$14*Assumptions!$B$12/Projects!$D$7:$D$14*0.95)+SUMPRODUCT((Projects!$G$7:$G$14="Yes")*(12=Projects!$C$7:$C$14+Projects!$D$7:$D$14-1)*Projects!$B$7:$B$14*Assumptions!$B$12*0.05)+SUMPRODUCT((Projects!$G$17:$G$46="Yes")*(12>=Projects!$C$17:$C$46)*(12<Projects!$C$17:$C$46+Projects!$D$17:$D$46)*Projects!$B$17:$B$46*Assumptions!$B$12/Projects!$D$17:$D$46*0.95)+SUMPRODUCT((Projects!$G$17:$G$46="Yes")*(12=Projects!$C$17:$C$46+Projects!$D$17:$D$46-1)*Projects!$B$17:$B$46*Assumptions!$B$12*0.05),Actuals!Q8) -> 448383.47 | Q10: =IF(ISBLANK(Actuals!R8),945615.84*Curves!N$7/SUM(Curves!$D$7:$Q$7)+646524.62*Curves!N$8/SUM(Curves!$D$8:$P$8)+737903.52*Curves!N$9/SUM(Curves!$D$9:$P$9)+175334.53*Curves!N$4/SUM(Curves!$D$4:$T$4)+SUMPRODUCT((Projects!$G$7:$G$14="Yes")*(13>=Projects!$C$7:$C$14)*(13<Projects!$C$7:$C$14+Projects!$D$7:$D$14)*Projects!$B$7:$B$14*Assumptions!$B$10/Projects!$D$7:$D$14*0.95)+SUMPRODUCT((Projects!$G$7:$G$14="Yes")*(13=Projects!$C$7:$C$14+Projects!$D$7:$D$14-1)*Projects!$B$7:$B$14*Assumptions!$B$10*0.05)+SUMPRODUCT((Projects!$G$17:$G$46="Yes")*(13>=Projects!$C$17:$C$46)*(13<Projects!$C$17:$C$46+Projects!$D$17:$D$46)*Projects!$B$17:$B$46*Assumptions!$B$10/Projects!$D$17:$D$46*0.95)+SUMPRODUCT((Projects!$G$17:$G$46="Yes")*(13=Projects!$C$17:$C$46+Projects!$D$17:$D$46-1)*Projects!$B$17:$B$46*Assumptions!$B$10*0.05)+SUMPRODUCT((Projects!$G$7:$G$14="Yes")*(13>=Projects!$C$7:$C$14)*(13<Projects!$C$7:$C$14+Projects!$D$7:$D$14)*Projects!$B$7:$B$14*Assumptions!$B$12/Projects!$D$7:$D$14*0.95)+SUMPRODUCT((Projects!$G$7:$G$14="Yes")*(13=Projects!$C$7:$C$14+Projects!$D$7:$D$14-1)*Projects!$B$7:$B$14*Assumptions!$B$12*0.05)+SUMPRODUCT((Projects!$G$17:$G$46="Yes")*(13>=Projects!$C$17:$C$46)*(13<Projects!$C$17:$C$46+Projects!$D$17:$D$46)*Projects!$B$17:$B$46*Assumptions!$B$12/Projects!$D$17:$D$46*0.95)+SUMPRODUCT((Projects!$G$17:$G$46="Yes")*(13=Projects!$C$17:$C$46+Projects!$D$17:$D$46-1)*Projects!$B$17:$B$46*Assumptions!$B$12*0.05),Actuals!R8) -> 526589.1 | R10: =IF(ISBLANK(Actuals!S8),945615.84*Curves!O$7/SUM(Curves!$D$7:$Q$7)+646524.62*Curves!O$8/SUM(Curves!$D$8:$P$8)+737903.52*Curves!O$9/SUM(Curves!$D$9:$P$9)+175334.53*Curves!O$4/SUM(Curves!$D$4:$T$4)+SUMPRODUCT((Projects!$G$7:$G$14="Yes")*(14>=Projects!$C$7:$C$14)*(14<Projects!$C$7:$C$14+Projects!$D$7:$D$14)*Projects!$B$7:$B$14*Assumptions!$B$10/Projects!$D$7:$D$14*0.95)+SUMPRODUCT((Projects!$G$7:$G$14="Yes")*(14=Projects!$C$7:$C$14+Projects!$D$7:$D$14-1)*Projects!$B$7:$B$14*Assumptions!$B$10*0.05)+SUMPRODUCT((Projects!$G$17:$G$46="Yes")*(14>=Projects!$C$17:$C$46)*(14<Projects!$C$17:$C$46+Projects!$D$17:$D$46)*Projects!$B$17:$B$46*Assumptions!$B$10/Projects!$D$17:$D$46*0.95)+SUMPRODUCT((Projects!$G$17:$G$46="Yes")*(14=Projects!$C$17:$C$46+Projects!$D$17:$D$46-1)*Projects!$B$17:$B$46*Assumptions!$B$10*0.05)+SUMPRODUCT((Projects!$G$7:$G$14="Yes")*(14>=Projects!$C$7:$C$14)*(14<Projects!$C$7:$C$14+Projects!$D$7:$D$14)*Projects!$B$7:$B$14*Assumptions!$B$12/Projects!$D$7:$D$14*0.95)+SUMPRODUCT((Projects!$G$7:$G$14="Yes")*(14=Projects!$C$7:$C$14+Projects!$D$7:$D$14-1)*Projects!$B$7:$B$14*Assumptions!$B$12*0.05)+SUMPRODUCT((Projects!$G$17:$G$46="Yes")*(14>=Projects!$C$17:$C$46)*(14<Projects!$C$17:$C$46+Projects!$D$17:$D$46)*Projects!$B$17:$B$46*Assumptions!$B$12/Projects!$D$17:$D$46*0.95)+SUMPRODUCT((Projects!$G$17:$G$46="Yes")*(14=Projects!$C$17:$C$46+Projects!$D$17:$D$46-1)*Projects!$B$17:$B$46*Assumptions!$B$12*0.05),Actuals!S8) -> 506433.48 | S10: =IF(ISBLANK(Actuals!T8),945615.84*Curves!P$7/SUM(Curves!$D$7:$Q$7)+646524.62*Curves!P$8/SUM(Curves!$D$8:$P$8)+737903.52*Curves!P$9/SUM(Curves!$D$9:$P$9)+175334.53*Curves!P$4/SUM(Curves!$D$4:$T$4)+SUMPRODUCT((Projects!$G$7:$G$14="Yes")*(15>=Projects!$C$7:$C$14)*(15<Projects!$C$7:$C$14+Projects!$D$7:$D$14)*Projects!$B$7:$B$14*Assumptions!$B$10/Projects!$D$7:$D$14*0.95)+SUMPRODUCT((Projects!$G$7:$G$14="Yes")*(15=Projects!$C$7:$C$14+Projects!$D$7:$D$14-1)*Projects!$B$7:$B$14*Assumptions!$B$10*0.05)+SUMPRODUCT((Projects!$G$17:$G$46="Yes")*(15>=Projects!$C$17:$C$46)*(15<Projects!$C$17:$C$46+Projects!$D$17:$D$46)*Projects!$B$17:$B$46*Assumptions!$B$10/Projects!$D$17:$D$46*0.95)+SUMPRODUCT((Projects!$G$17:$G$46="Yes")*(15=Projects!$C$17:$C$46+Projects!$D$17:$D$46-1)*Projects!$B$17:$B$46*Assumptions!$B$10*0.05)+SUMPRODUCT((Projects!$G$7:$G$14="Yes")*(15>=Projects!$C$7:$C$14)*(15<Projects!$C$7:$C$14+Projects!$D$7:$D$14)*Projects!$B$7:$B$14*Assumptions!$B$12/Projects!$D$7:$D$14*0.95)+SUMPRODUCT((Projects!$G$7:$G$14="Yes")*(15=Projects!$C$7:$C$14+Projects!$D$7:$D$14-1)*Projects!$B$7:$B$14*Assumptions!$B$12*0.05)+SUMPRODUCT((Projects!$G$17:$G$46="Yes")*(15>=Projects!$C$17:$C$46)*(15<Projects!$C$17:$C$46+Projects!$D$17:$D$46)*Projects!$B$17:$B$46*Assumptions!$B$12/Projects!$D$17:$D$46*0.95)+SUMPRODUCT((Projects!$G$17:$G$46="Yes")*(15=Projects!$C$17:$C$46+Projects!$D$17:$D$46-1)*Projects!$B$17:$B$46*Assumptions!$B$12*0.05),Actuals!T8) -> 487280.85 | T10: =IF(ISBLANK(Actuals!U8),945615.84*Curves!Q$7/SUM(Curves!$D$7:$Q$7)+175334.53*Curves!Q$4/SUM(Curves!$D$4:$T$4)+SUMPRODUCT((Projects!$G$7:$G$14="Yes")*(16>=Projects!$C$7:$C$14)*(16<Projects!$C$7:$C$14+Projects!$D$7:$D$14)*Projects!$B$7:$B$14*Assumptions!$B$10/Projects!$D$7:$D$14*0.95)+SUMPRODUCT((Projects!$G$7:$G$14="Yes")*(16=Projects!$C$7:$C$14+Projects!$D$7:$D$14-1)*Projects!$B$7:$B$14*Assumptions!$B$10*0.05)+SUMPRODUCT((Projects!$G$17:$G$46="Yes")*(16>=Projects!$C$17:$C$46)*(16<Projects!$C$17:$C$46+Projects!$D$17:$D$46)*Projects!$B$17:$B$46*Assumptions!$B$10/Projects!$D$17:$D$46*0.95)+SUMPRODUCT((Projects!$G$17:$G$46="Yes")*(16=Projects!$C$17:$C$46+Projects!$D$17:$D$46-1)*Projects!$B$17:$B$46*Assumptions!$B$10*0.05)+SUMPRODUCT((Projects!$G$7:$G$14="Yes")*(16>=Projects!$C$7:$C$14)*(16<Projects!$C$7:$C$14+Projects!$D$7:$D$14)*Projects!$B$7:$B$14*Assumptions!$B$12/Projects!$D$7:$D$14*0.95)+SUMPRODUCT((Projects!$G$7:$G$14="Yes")*(16=Projects!$C$7:$C$14+Projects!$D$7:$D$14-1)*Projects!$B$7:$B$14*Assumptions!$B$12*0.05)+SUMPRODUCT((Projects!$G$17:$G$46="Yes")*(16>=Projects!$C$17:$C$46)*(16<Projects!$C$17:$C$46+Projects!$D$17:$D$46)*Projects!$B$17:$B$46*Assumptions!$B$12/Projects!$D$17:$D$46*0.95)+SUMPRODUCT((Projects!$G$17:$G$46="Yes")*(16=Projects!$C$17:$C$46+Projects!$D$17:$D$46-1)*Projects!$B$17:$B$46*Assumptions!$B$12*0.05),Actuals!U8) -> 430629.52 | U10: =IF(ISBLANK(Actuals!V8),175334.53*Curves!R$4/SUM(Curves!$D$4:$T$4)+SUMPRODUCT((Projects!$G$7:$G$14="Yes")*(17>=Projects!$C$7:$C$14)*(17<Projects!$C$7:$C$14+Projects!$D$7:$D$14)*Projects!$B$7:$B$14*Assumptions!$B$10/Projects!$D$7:$D$14*0.95)+SUMPRODUCT((Projects!$G$7:$G$14="Yes")*(17=Projects!$C$7:$C$14+Projects!$D$7:$D$14-1)*Projects!$B$7:$B$14*Assumptions!$B$10*0.05)+SUMPRODUCT((Projects!$G$17:$G$46="Yes")*(17>=Projects!$C$17:$C$46)*(17<Projects!$C$17:$C$46+Projects!$D$17:$D$46)*Projects!$B$17:$B$46*Assumptions!$B$10/Projects!$D$17:$D$46*0.95)+SUMPRODUCT((Projects!$G$17:$G$46="Yes")*(17=Projects!$C$17:$C$46+Projects!$D$17:$D$46-1)*Projects!$B$17:$B$46*Assumptions!$B$10*0.05)+SUMPRODUCT((Projects!$G$7:$G$14="Yes")*(17>=Projects!$C$7:$C$14)*(17<Projects!$C$7:$C$14+Projects!$D$7:$D$14)*Projects!$B$7:$B$14*Assumptions!$B$12/Projects!$D$7:$D$14*0.95)+SUMPRODUCT((Projects!$G$7:$G$14="Yes")*(17=Projects!$C$7:$C$14+Projects!$D$7:$D$14-1)*Projects!$B$7:$B$14*Assumptions!$B$12*0.05)+SUMPRODUCT((Projects!$G$17:$G$46="Yes")*(17>=Projects!$C$17:$C$46)*(17<Projects!$C$17:$C$46+Projects!$D$17:$D$46)*Projects!$B$17:$B$46*Assumptions!$B$12/Projects!$D$17:$D$46*0.95)+SUMPRODUCT((Projects!$G$17:$G$46="Yes")*(17=Projects!$C$17:$C$46+Projects!$D$17:$D$46-1)*Projects!$B$17:$B$46*Assumptions!$B$12*0.05),Actuals!V8) -> 397766.99 | V10: =IF(ISBLANK(Actuals!W8),175334.53*Curves!S$4/SUM(Curves!$D$4:$T$4)+SUMPRODUCT((Projects!$G$7:$G$14="Yes")*(18>=Projects!$C$7:$C$14)*(18<Projects!$C$7:$C$14+Projects!$D$7:$D$14)*Projects!$B$7:$B$14*Assumptions!$B$10/Projects!$D$7:$D$14*0.95)+SUMPRODUCT((Projects!$G$7:$G$14="Yes")*(18=Projects!$C$7:$C$14+Projects!$D$7:$D$14-1)*Projects!$B$7:$B$14*Assumptions!$B$10*0.05)+SUMPRODUCT((Projects!$G$17:$G$46="Yes")*(18>=Projects!$C$17:$C$46)*(18<Projects!$C$17:$C$46+Projects!$D$17:$D$46)*Projects!$B$17:$B$46*Assumptions!$B$10/Projects!$D$17:$D$46*0.95)+SUMPRODUCT((Projects!$G$17:$G$46="Yes")*(18=Projects!$C$17:$C$46+Projects!$D$17:$D$46-1)*Projects!$B$17:$B$46*Assumptions!$B$10*0.05)+SUMPRODUCT((Projects!$G$7:$G$14="Yes")*(18>=Projects!$C$7:$C$14)*(18<Projects!$C$7:$C$14+Projects!$D$7:$D$14)*Projects!$B$7:$B$14*Assumptions!$B$12/Projects!$D$7:$D$14*0.95)+SUMPRODUCT((Projects!$G$7:$G$14="Yes")*(18=Projects!$C$7:$C$14+Projects!$D$7:$D$14-1)*Projects!$B$7:$B$14*Assumptions!$B$12*0.05)+SUMPRODUCT((Projects!$G$17:$G$46="Yes")*(18>=Projects!$C$17:$C$46)*(18<Projects!$C$17:$C$46+Projects!$D$17:$D$46)*Projects!$B$17:$B$46*Assumptions!$B$12/Projects!$D$17:$D$46*0.95)+SUMPRODUCT((Projects!$G$17:$G$46="Yes")*(18=Projects!$C$17:$C$46+Projects!$D$17:$D$46-1)*Projects!$B$17:$B$46*Assumptions!$B$12*0.05),Actuals!W8) -> 396514.31 | W10: =IF(ISBLANK(Actuals!X8),175334.53*Curves!T$4/SUM(Curves!$D$4:$T$4)+SUMPRODUCT((Projects!$G$7:$G$14="Yes")*(19>=Projects!$C$7:$C$14)*(19<Projects!$C$7:$C$14+Projects!$D$7:$D$14)*Projects!$B$7:$B$14*Assumptions!$B$10/Projects!$D$7:$D$14*0.95)+SUMPRODUCT((Projects!$G$7:$G$14="Yes")*(19=Projects!$C$7:$C$14+Projects!$D$7:$D$14-1)*Projects!$B$7:$B$14*Assumptions!$B$10*0.05)+SUMPRODUCT((Projects!$G$17:$G$46="Yes")*(19>=Projects!$C$17:$C$46)*(19<Projects!$C$17:$C$46+Projects!$D$17:$D$46)*Projects!$B$17:$B$46*Assumptions!$B$10/Projects!$D$17:$D$46*0.95)+SUMPRODUCT((Projects!$G$17:$G$46="Yes")*(19=Projects!$C$17:$C$46+Projects!$D$17:$D$46-1)*Projects!$B$17:$B$46*Assumptions!$B$10*0.05)+SUMPRODUCT((Projects!$G$7:$G$14="Yes")*(19>=Projects!$C$7:$C$14)*(19<Projects!$C$7:$C$14+Projects!$D$7:$D$14)*Projects!$B$7:$B$14*Assumptions!$B$12/Projects!$D$7:$D$14*0.95)+SUMPRODUCT((Projects!$G$7:$G$14="Yes")*(19=Projects!$C$7:$C$14+Projects!$D$7:$D$14-1)*Projects!$B$7:$B$14*Assumptions!$B$12*0.05)+SUMPRODUCT((Projects!$G$17:$G$46="Yes")*(19>=Projects!$C$17:$C$46)*(19<Projects!$C$17:$C$46+Projects!$D$17:$D$46)*Projects!$B$17:$B$46*Assumptions!$B$12/Projects!$D$17:$D$46*0.95)+SUMPRODUCT((Projects!$G$17:$G$46="Yes")*(19=Projects!$C$17:$C$46+Projects!$D$17:$D$46-1)*Projects!$B$17:$B$46*Assumptions!$B$12*0.05),Actuals!X8) -> 395350.54 | X10: =IF(ISBLANK(Actuals!Y8),0+SUMPRODUCT((Projects!$G$7:$G$14="Yes")*(20>=Projects!$C$7:$C$14)*(20<Projects!$C$7:$C$14+Projects!$D$7:$D$14)*Projects!$B$7:$B$14*Assumptions!$B$10/Projects!$D$7:$D$14*0.95)+SUMPRODUCT((Projects!$G$7:$G$14="Yes")*(20=Projects!$C$7:$C$14+Projects!$D$7:$D$14-1)*Projects!$B$7:$B$14*Assumptions!$B$10*0.05)+SUMPRODUCT((Projects!$G$17:$G$46="Yes")*(20>=Projects!$C$17:$C$46)*(20<Projects!$C$17:$C$46+Projects!$D$17:$D$46)*Projects!$B$17:$B$46*Assumptions!$B$10/Projects!$D$17:$D$46*0.95)+SUMPRODUCT((Projects!$G$17:$G$46="Yes")*(20=Projects!$C$17:$C$46+Projects!$D$17:$D$46-1)*Projects!$B$17:$B$46*Assumptions!$B$10*0.05)+SUMPRODUCT((Projects!$G$7:$G$14="Yes")*(20>=Projects!$C$7:$C$14)*(20<Projects!$C$7:$C$14+Projects!$D$7:$D$14)*Projects!$B$7:$B$14*Assumptions!$B$12/Projects!$D$7:$D$14*0.95)+SUMPRODUCT((Projects!$G$7:$G$14="Yes")*(20=Projects!$C$7:$C$14+Projects!$D$7:$D$14-1)*Projects!$B$7:$B$14*Assumptions!$B$12*0.05)+SUMPRODUCT((Projects!$G$17:$G$46="Yes")*(20>=Projects!$C$17:$C$46)*(20<Projects!$C$17:$C$46+Projects!$D$17:$D$46)*Projects!$B$17:$B$46*Assumptions!$B$12/Projects!$D$17:$D$46*0.95)+SUMPRODUCT((Projects!$G$17:$G$46="Yes")*(20=Projects!$C$17:$C$46+Projects!$D$17:$D$46-1)*Projects!$B$17:$B$46*Assumptions!$B$12*0.05),Actuals!Y8) -> 390408.22 | Y10: =IF(ISBLANK(Actuals!Z8),0+SUMPRODUCT((Projects!$G$7:$G$14="Yes")*(21>=Projects!$C$7:$C$14)*(21<Projects!$C$7:$C$14+Projects!$D$7:$D$14)*Projects!$B$7:$B$14*Assumptions!$B$10/Projects!$D$7:$D$14*0.95)+SUMPRODUCT((Projects!$G$7:$G$14="Yes")*(21=Projects!$C$7:$C$14+Projects!$D$7:$D$14-1)*Projects!$B$7:$B$14*Assumptions!$B$10*0.05)+SUMPRODUCT((Projects!$G$17:$G$46="Yes")*(21>=Projects!$C$17:$C$46)*(21<Projects!$C$17:$C$46+Projects!$D$17:$D$46)*Projects!$B$17:$B$46*Assumptions!$B$10/Projects!$D$17:$D$46*0.95)+SUMPRODUCT((Projects!$G$17:$G$46="Yes")*(21=Projects!$C$17:$C$46+Projects!$D$17:$D$46-1)*Projects!$B$17:$B$46*Assumptions!$B$10*0.05)+SUMPRODUCT((Projects!$G$7:$G$14="Yes")*(21>=Projects!$C$7:$C$14)*(21<Projects!$C$7:$C$14+Projects!$D$7:$D$14)*Projects!$B$7:$B$14*Assumptions!$B$12/Projects!$D$7:$D$14*0.95)+SUMPRODUCT((Projects!$G$7:$G$14="Yes")*(21=Projects!$C$7:$C$14+Projects!$D$7:$D$14-1)*Projects!$B$7:$B$14*Assumptions!$B$12*0.05)+SUMPRODUCT((Projects!$G$17:$G$46="Yes")*(21>=Projects!$C$17:$C$46)*(21<Projects!$C$17:$C$46+Projects!$D$17:$D$46)*Projects!$B$17:$B$46*Assumptions!$B$12/Projects!$D$17:$D$46*0.95)+SUMPRODUCT((Projects!$G$17:$G$46="Yes")*(21=Projects!$C$17:$C$46+Projects!$D$17:$D$46-1)*Projects!$B$17:$B$46*Assumptions!$B$12*0.05),Actuals!Z8) -> 390408.22 | Z10: =IF(ISBLANK(Actuals!AA8),0+SUMPRODUCT((Projects!$G$7:$G$14="Yes")*(22>=Projects!$C$7:$C$14)*(22<Projects!$C$7:$C$14+Projects!$D$7:$D$14)*Projects!$B$7:$B$14*Assumptions!$B$10/Projects!$D$7:$D$14*0.95)+SUMPRODUCT((Projects!$G$7:$G$14="Yes")*(22=Projects!$C$7:$C$14+Projects!$D$7:$D$14-1)*Projects!$B$7:$B$14*Assumptions!$B$10*0.05)+SUMPRODUCT((Projects!$G$17:$G$46="Yes")*(22>=Projects!$C$17:$C$46)*(22<Projects!$C$17:$C$46+Projects!$D$17:$D$46)*Projects!$B$17:$B$46*Assumptions!$B$10/Projects!$D$17:$D$46*0.95)+SUMPRODUCT((Projects!$G$17:$G$46="Yes")*(22=Projects!$C$17:$C$46+Projects!$D$17:$D$46-1)*Projects!$B$17:$B$46*Assumptions!$B$10*0.05)+SUMPRODUCT((Projects!$G$7:$G$14="Yes")*(22>=Projects!$C$7:$C$14)*(22<Projects!$C$7:$C$14+Projects!$D$7:$D$14)*Projects!$B$7:$B$14*Assumptions!$B$12/Projects!$D$7:$D$14*0.95)+SUMPRODUCT((Projects!$G$7:$G$14="Yes")*(22=Projects!$C$7:$C$14+Projects!$D$7:$D$14-1)*Projects!$B$7:$B$14*Assumptions!$B$12*0.05)+SUMPRODUCT((Projects!$G$17:$G$46="Yes")*(22>=Projects!$C$17:$C$46)*(22<Projects!$C$17:$C$46+Projects!$D$17:$D$46)*Projects!$B$17:$B$46*Assumptions!$B$12/Projects!$D$17:$D$46*0.95)+SUMPRODUCT((Projects!$G$17:$G$46="Yes")*(22=Projects!$C$17:$C$46+Projects!$D$17:$D$46-1)*Projects!$B$17:$B$46*Assumptions!$B$12*0.05),Actuals!AA8) -> 390408.22 | AA10: =IF(ISBLANK(Actuals!AB8),0+SUMPRODUCT((Projects!$G$7:$G$14="Yes")*(23>=Projects!$C$7:$C$14)*(23<Projects!$C$7:$C$14+Projects!$D$7:$D$14)*Projects!$B$7:$B$14*Assumptions!$B$10/Projects!$D$7:$D$14*0.95)+SUMPRODUCT((Projects!$G$7:$G$14="Yes")*(23=Projects!$C$7:$C$14+Projects!$D$7:$D$14-1)*Projects!$B$7:$B$14*Assumptions!$B$10*0.05)+SUMPRODUCT((Projects!$G$17:$G$46="Yes")*(23>=Projects!$C$17:$C$46)*(23<Projects!$C$17:$C$46+Projects!$D$17:$D$46)*Projects!$B$17:$B$46*Assumptions!$B$10/Projects!$D$17:$D$46*0.95)+SUMPRODUCT((Projects!$G$17:$G$46="Yes")*(23=Projects!$C$17:$C$46+Projects!$D$17:$D$46-1)*Projects!$B$17:$B$46*Assumptions!$B$10*0.05)+SUMPRODUCT((Projects!$G$7:$G$14="Yes")*(23>=Projects!$C$7:$C$14)*(23<Projects!$C$7:$C$14+Projects!$D$7:$D$14)*Projects!$B$7:$B$14*Assumptions!$B$12/Projects!$D$7:$D$14*0.95)+SUMPRODUCT((Projects!$G$7:$G$14="Yes")*(23=Projects!$C$7:$C$14+Projects!$D$7:$D$14-1)*Projects!$B$7:$B$14*Assumptions!$B$12*0.05)+SUMPRODUCT((Projects!$G$17:$G$46="Yes")*(23>=Projects!$C$17:$C$46)*(23<Projects!$C$17:$C$46+Projects!$D$17:$D$46)*Projects!$B$17:$B$46*Assumptions!$B$12/Projects!$D$17:$D$46*0.95)+SUMPRODUCT((Projects!$G$17:$G$46="Yes")*(23=Projects!$C$17:$C$46+Projects!$D$17:$D$46-1)*Projects!$B$17:$B$46*Assumptions!$B$12*0.05),Actuals!AB8) -> 390408.22 | AB10: =IF(ISBLANK(Actuals!AC8),0+SUMPRODUCT((Projects!$G$7:$G$14="Yes")*(24>=Projects!$C$7:$C$14)*(24<Projects!$C$7:$C$14+Projects!$D$7:$D$14)*Projects!$B$7:$B$14*Assumptions!$B$10/Projects!$D$7:$D$14*0.95)+SUMPRODUCT((Projects!$G$7:$G$14="Yes")*(24=Projects!$C$7:$C$14+Projects!$D$7:$D$14-1)*Projects!$B$7:$B$14*Assumptions!$B$10*0.05)+SUMPRODUCT((Projects!$G$17:$G$46="Yes")*(24>=Projects!$C$17:$C$46)*(24<Projects!$C$17:$C$46+Projects!$D$17:$D$46)*Projects!$B$17:$B$46*Assumptions!$B$10/Projects!$D$17:$D$46*0.95)+SUMPRODUCT((Projects!$G$17:$G$46="Yes")*(24=Projects!$C$17:$C$46+Projects!$D$17:$D$46-1)*Projects!$B$17:$B$46*Assumptions!$B$10*0.05)+SUMPRODUCT((Projects!$G$7:$G$14="Yes")*(24>=Projects!$C$7:$C$14)*(24<Projects!$C$7:$C$14+Projects!$D$7:$D$14)*Projects!$B$7:$B$14*Assumptions!$B$12/Projects!$D$7:$D$14*0.95)+SUMPRODUCT((Projects!$G$7:$G$14="Yes")*(24=Projects!$C$7:$C$14+Projects!$D$7:$D$14-1)*Projects!$B$7:$B$14*Assumptions!$B$12*0.05)+SUMPRODUCT((Projects!$G$17:$G$46="Yes")*(24>=Projects!$C$17:$C$46)*(24<Projects!$C$17:$C$46+Projects!$D$17:$D$46)*Projects!$B$17:$B$46*Assumptions!$B$12/Projects!$D$17:$D$46*0.95)+SUMPRODUCT((Projects!$G$17:$G$46="Yes")*(24=Projects!$C$17:$C$46+Projects!$D$17:$D$46-1)*Projects!$B$17:$B$46*Assumptions!$B$12*0.05),Actuals!AC8) -> 390408.22 | AC10: =IF(ISBLANK(Actuals!AD8),0+SUMPRODUCT((Projects!$G$7:$G$14="Yes")*(25>=Projects!$C$7:$C$14)*(25<Projects!$C$7:$C$14+Projects!$D$7:$D$14)*Projects!$B$7:$B$14*Assumptions!$B$10/Projects!$D$7:$D$14*0.95)+SUMPRODUCT((Projects!$G$7:$G$14="Yes")*(25=Projects!$C$7:$C$14+Projects!$D$7:$D$14-1)*Projects!$B$7:$B$14*Assumptions!$B$10*0.05)+SUMPRODUCT((Projects!$G$17:$G$46="Yes")*(25>=Projects!$C$17:$C$46)*(25<Projects!$C$17:$C$46+Projects!$D$17:$D$46)*Projects!$B$17:$B$46*Assumptions!$B$10/Projects!$D$17:$D$46*0.95)+SUMPRODUCT((Projects!$G$17:$G$46="Yes")*(25=Projects!$C$17:$C$46+Projects!$D$17:$D$46-1)*Projects!$B$17:$B$46*Assumptions!$B$10*0.05)+SUMPRODUCT((Projects!$G$7:$G$14="Yes")*(25>=Projects!$C$7:$C$14)*(25<Projects!$C$7:$C$14+Projects!$D$7:$D$14)*Projects!$B$7:$B$14*Assumptions!$B$12/Projects!$D$7:$D$14*0.95)+SUMPRODUCT((Projects!$G$7:$G$14="Yes")*(25=Projects!$C$7:$C$14+Projects!$D$7:$D$14-1)*Projects!$B$7:$B$14*Assumptions!$B$12*0.05)+SUMPRODUCT((Projects!$G$17:$G$46="Yes")*(25>=Projects!$C$17:$C$46)*(25<Projects!$C$17:$C$46+Projects!$D$17:$D$46)*Projects!$B$17:$B$46*Assumptions!$B$12/Projects!$D$17:$D$46*0.95)+SUMPRODUCT((Projects!$G$17:$G$46="Yes")*(25=Projects!$C$17:$C$46+Projects!$D$17:$D$46-1)*Projects!$B$17:$B$46*Assumptions!$B$12*0.05),Actuals!AD8) -> 496173.94 | AD10: =IF(ISBLANK(Actuals!AE8),0+SUMPRODUCT((Projects!$G$7:$G$14="Yes")*(26>=Projects!$C$7:$C$14)*(26<Projects!$C$7:$C$14+Projects!$D$7:$D$14)*Projects!$B$7:$B$14*Assumptions!$B$10/Projects!$D$7:$D$14*0.95)+SUMPRODUCT((Projects!$G$7:$G$14="Yes")*(26=Projects!$C$7:$C$14+Projects!$D$7:$D$14-1)*Projects!$B$7:$B$14*Assumptions!$B$10*0.05)+SUMPRODUCT((Projects!$G$17:$G$46="Yes")*(26>=Projects!$C$17:$C$46)*(26<Projects!$C$17:$C$46+Projects!$D$17:$D$46)*Projects!$B$17:$B$46*Assumptions!$B$10/Projects!$D$17:$D$46*0.95)+SUMPRODUCT((Projects!$G$17:$G$46="Yes")*(26=Projects!$C$17:$C$46+Projects!$D$17:$D$46-1)*Projects!$B$17:$B$46*Assumptions!$B$10*0.05)+SUMPRODUCT((Projects!$G$7:$G$14="Yes")*(26>=Projects!$C$7:$C$14)*(26<Projects!$C$7:$C$14+Projects!$D$7:$D$14)*Projects!$B$7:$B$14*Assumptions!$B$12/Projects!$D$7:$D$14*0.95)+SUMPRODUCT((Projects!$G$7:$G$14="Yes")*(26=Projects!$C$7:$C$14+Projects!$D$7:$D$14-1)*Projects!$B$7:$B$14*Assumptions!$B$12*0.05)+SUMPRODUCT((Projects!$G$17:$G$46="Yes")*(26>=Projects!$C$17:$C$46)*(26<Projects!$C$17:$C$46+Projects!$D$17:$D$46)*Projects!$B$17:$B$46*Assumptions!$B$12/Projects!$D$17:$D$46*0.95)+SUMPRODUCT((Projects!$G$17:$G$46="Yes")*(26=Projects!$C$17:$C$46+Projects!$D$17:$D$46-1)*Projects!$B$17:$B$46*Assumptions!$B$12*0.05),Actuals!AE8) -> 284642.5 | AE10: =IF(ISBLANK(Actuals!AF8),0+SUMPRODUCT((Projects!$G$7:$G$14="Yes")*(27>=Projects!$C$7:$C$14)*(27<Projects!$C$7:$C$14+Projects!$D$7:$D$14)*Projects!$B$7:$B$14*Assumptions!$B$10/Projects!$D$7:$D$14*0.95)+SUMPRODUCT((Projects!$G$7:$G$14="Yes")*(27=Projects!$C$7:$C$14+Projects!$D$7:$D$14-1)*Projects!$B$7:$B$14*Assumptions!$B$10*0.05)+SUMPRODUCT((Projects!$G$17:$G$46="Yes")*(27>=Projects!$C$17:$C$46)*(27<Projects!$C$17:$C$46+Projects!$D$17:$D$46)*Projects!$B$17:$B$46*Assumptions!$B$10/Projects!$D$17:$D$46*0.95)+SUMPRODUCT((Projects!$G$17:$G$46="Yes")*(27=Projects!$C$17:$C$46+Projects!$D$17:$D$46-1)*Projects!$B$17:$B$46*Assumptions!$B$10*0.05)+SUMPRODUCT((Projects!$G$7:$G$14="Yes")*(27>=Projects!$C$7:$C$14)*(27<Projects!$C$7:$C$14+Projects!$D$7:$D$14)*Projects!$B$7:$B$14*Assumptions!$B$12/Projects!$D$7:$D$14*0.95)+SUMPRODUCT((Projects!$G$7:$G$14="Yes")*(27=Projects!$C$7:$C$14+Projects!$D$7:$D$14-1)*Projects!$B$7:$B$14*Assumptions!$B$12*0.05)+SUMPRODUCT((Projects!$G$17:$G$46="Yes")*(27>=Projects!$C$17:$C$46)*(27<Projects!$C$17:$C$46+Projects!$D$17:$D$46)*Projects!$B$17:$B$46*Assumptions!$B$12/Projects!$D$17:$D$46*0.95)+SUMPRODUCT((Projects!$G$17:$G$46="Yes")*(27=Projects!$C$17:$C$46+Projects!$D$17:$D$46-1)*Projects!$B$17:$B$46*Assumptions!$B$12*0.05),Actuals!AF8) -> 374733.91 | AF10: =IF(ISBLANK(Actuals!AG8),0+SUMPRODUCT((Projects!$G$7:$G$14="Yes")*(28>=Projects!$C$7:$C$14)*(28<Projects!$C$7:$C$14+Projects!$D$7:$D$14)*Projects!$B$7:$B$14*Assumptions!$B$10/Projects!$D$7:$D$14*0.95)+SUMPRODUCT((Projects!$G$7:$G$14="Yes")*(28=Projects!$C$7:$C$14+Projects!$D$7:$D$14-1)*Projects!$B$7:$B$14*Assumptions!$B$10*0.05)+SUMPRODUCT((Projects!$G$17:$G$46="Yes")*(28>=Projects!$C$17:$C$46)*(28<Projects!$C$17:$C$46+Projects!$D$17:$D$46)*Projects!$B$17:$B$46*Assumptions!$B$10/Projects!$D$17:$D$46*0.95)+SUMPRODUCT((Projects!$G$17:$G$46="Yes")*(28=Projects!$C$17:$C$46+Projects!$D$17:$D$46-1)*Projects!$B$17:$B$46*Assumptions!$B$10*0.05)+SUMPRODUCT((Projects!$G$7:$G$14="Yes")*(28>=Projects!$C$7:$C$14)*(28<Projects!$C$7:$C$14+Projects!$D$7:$D$14)*Projects!$B$7:$B$14*Assumptions!$B$12/Projects!$D$7:$D$14*0.95)+SUMPRODUCT((Projects!$G$7:$G$14="Yes")*(28=Projects!$C$7:$C$14+Projects!$D$7:$D$14-1)*Projects!$B$7:$B$14*Assumptions!$B$12*0.05)+SUMPRODUCT((Projects!$G$17:$G$46="Yes")*(28>=Projects!$C$17:$C$46)*(28<Projects!$C$17:$C$46+Projects!$D$17:$D$46)*Projects!$B$17:$B$46*Assumptions!$B$12/Projects!$D$17:$D$46*0.95)+SUMPRODUCT((Projects!$G$17:$G$46="Yes")*(28=Projects!$C$17:$C$46+Projects!$D$17:$D$46-1)*Projects!$B$17:$B$46*Assumptions!$B$12*0.05),Actuals!AG8) -> 374733.91 | AG10: =IF(ISBLANK(Actuals!AH8),0+SUMPRODUCT((Projects!$G$7:$G$14="Yes")*(29>=Projects!$C$7:$C$14)*(29<Projects!$C$7:$C$14+Projects!$D$7:$D$14)*Projects!$B$7:$B$14*Assumptions!$B$10/Projects!$D$7:$D$14*0.95)+SUMPRODUCT((Projects!$G$7:$G$14="Yes")*(29=Projects!$C$7:$C$14+Projects!$D$7:$D$14-1)*Projects!$B$7:$B$14*Assumptions!$B$10*0.05)+SUMPRODUCT((Projects!$G$17:$G$46="Yes")*(29>=Projects!$C$17:$C$46)*(29<Projects!$C$17:$C$46+Projects!$D$17:$D$46)*Projects!$B$17:$B$46*Assumptions!$B$10/Projects!$D$17:$D$46*0.95)+SUMPRODUCT((Projects!$G$17:$G$46="Yes")*(29=Projects!$C$17:$C$46+Projects!$D$17:$D$46-1)*Projects!$B$17:$B$46*Assumptions!$B$10*0.05)+SUMPRODUCT((Projects!$G$7:$G$14="Yes")*(29>=Projects!$C$7:$C$14)*(29<Projects!$C$7:$C$14+Projects!$D$7:$D$14)*Projects!$B$7:$B$14*Assumptions!$B$12/Projects!$D$7:$D$14*0.95)+SUMPRODUCT((Projects!$G$7:$G$14="Yes")*(29=Projects!$C$7:$C$14+Projects!$D$7:$D$14-1)*Projects!$B$7:$B$14*Assumptions!$B$12*0.05)+SUMPRODUCT((Projects!$G$17:$G$46="Yes")*(29>=Projects!$C$17:$C$46)*(29<Projects!$C$17:$C$46+Projects!$D$17:$D$46)*Projects!$B$17:$B$46*Assumptions!$B$12/Projects!$D$17:$D$46*0.95)+SUMPRODUCT((Projects!$G$17:$G$46="Yes")*(29=Projects!$C$17:$C$46+Projects!$D$17:$D$46-1)*Projects!$B$17:$B$46*Assumptions!$B$12*0.05),Actuals!AH8) -> 374733.91 | AH10: =IF(ISBLANK(Actuals!AI8),0+SUMPRODUCT((Projects!$G$7:$G$14="Yes")*(30>=Projects!$C$7:$C$14)*(30<Projects!$C$7:$C$14+Projects!$D$7:$D$14)*Projects!$B$7:$B$14*Assumptions!$B$10/Projects!$D$7:$D$14*0.95)+SUMPRODUCT((Projects!$G$7:$G$14="Yes")*(30=Projects!$C$7:$C$14+Projects!$D$7:$D$14-1)*Projects!$B$7:$B$14*Assumptions!$B$10*0.05)+SUMPRODUCT((Projects!$G$17:$G$46="Yes")*(30>=Projects!$C$17:$C$46)*(30<Projects!$C$17:$C$46+Projects!$D$17:$D$46)*Projects!$B$17:$B$46*Assumptions!$B$10/Projects!$D$17:$D$46*0.95)+SUMPRODUCT((Projects!$G$17:$G$46="Yes")*(30=Projects!$C$17:$C$46+Projects!$D$17:$D$46-1)*Projects!$B$17:$B$46*Assumptions!$B$10*0.05)+SUMPRODUCT((Projects!$G$7:$G$14="Yes")*(30>=Projects!$C$7:$C$14)*(30<Projects!$C$7:$C$14+Projects!$D$7:$D$14)*Projects!$B$7:$B$14*Assumptions!$B$12/Projects!$D$7:$D$14*0.95)+SUMPRODUCT((Projects!$G$7:$G$14="Yes")*(30=Projects!$C$7:$C$14+Projects!$D$7:$D$14-1)*Projects!$B$7:$B$14*Assumptions!$B$12*0.05)+SUMPRODUCT((Projects!$G$17:$G$46="Yes")*(30>=Projects!$C$17:$C$46)*(30<Projects!$C$17:$C$46+Projects!$D$17:$D$46)*Projects!$B$17:$B$46*Assumptions!$B$12/Projects!$D$17:$D$46*0.95)+SUMPRODUCT((Projects!$G$17:$G$46="Yes")*(30=Projects!$C$17:$C$46+Projects!$D$17:$D$46-1)*Projects!$B$17:$B$46*Assumptions!$B$12*0.05),Actuals!AI8) -> 374733.91 | AI10: =IF(ISBLANK(Actuals!AJ8),0+SUMPRODUCT((Projects!$G$7:$G$14="Yes")*(31>=Projects!$C$7:$C$14)*(31<Projects!$C$7:$C$14+Projects!$D$7:$D$14)*Projects!$B$7:$B$14*Assumptions!$B$10/Projects!$D$7:$D$14*0.95)+SUMPRODUCT((Projects!$G$7:$G$14="Yes")*(31=Projects!$C$7:$C$14+Projects!$D$7:$D$14-1)*Projects!$B$7:$B$14*Assumptions!$B$10*0.05)+SUMPRODUCT((Projects!$G$17:$G$46="Yes")*(31>=Projects!$C$17:$C$46)*(31<Projects!$C$17:$C$46+Projects!$D$17:$D$46)*Projects!$B$17:$B$46*Assumptions!$B$10/Projects!$D$17:$D$46*0.95)+SUMPRODUCT((Projects!$G$17:$G$46="Yes")*(31=Projects!$C$17:$C$46+Projects!$D$17:$D$46-1)*Projects!$B$17:$B$46*Assumptions!$B$10*0.05)+SUMPRODUCT((Projects!$G$7:$G$14="Yes")*(31>=Projects!$C$7:$C$14)*(31<Projects!$C$7:$C$14+Projects!$D$7:$D$14)*Projects!$B$7:$B$14*Assumptions!$B$12/Projects!$D$7:$D$14*0.95)+SUMPRODUCT((Projects!$G$7:$G$14="Yes")*(31=Projects!$C$7:$C$14+Projects!$D$7:$D$14-1)*Projects!$B$7:$B$14*Assumptions!$B$12*0.05)+SUMPRODUCT((Projects!$G$17:$G$46="Yes")*(31>=Projects!$C$17:$C$46)*(31<Projects!$C$17:$C$46+Projects!$D$17:$D$46)*Projects!$B$17:$B$46*Assumptions!$B$12/Projects!$D$17:$D$46*0.95)+SUMPRODUCT((Projects!$G$17:$G$46="Yes")*(31=Projects!$C$17:$C$46+Projects!$D$17:$D$46-1)*Projects!$B$17:$B$46*Assumptions!$B$12*0.05),Actuals!AJ8) -> 447874.71 | AJ10: =IF(ISBLANK(Actuals!AK8),0+SUMPRODUCT((Projects!$G$7:$G$14="Yes")*(32>=Projects!$C$7:$C$14)*(32<Projects!$C$7:$C$14+Projects!$D$7:$D$14)*Projects!$B$7:$B$14*Assumptions!$B$10/Projects!$D$7:$D$14*0.95)+SUMPRODUCT((Projects!$G$7:$G$14="Yes")*(32=Projects!$C$7:$C$14+Projects!$D$7:$D$14-1)*Projects!$B$7:$B$14*Assumptions!$B$10*0.05)+SUMPRODUCT((Projects!$G$17:$G$46="Yes")*(32>=Projects!$C$17:$C$46)*(32<Projects!$C$17:$C$46+Projects!$D$17:$D$46)*Projects!$B$17:$B$46*Assumptions!$B$10/Projects!$D$17:$D$46*0.95)+SUMPRODUCT((Projects!$G$17:$G$46="Yes")*(32=Projects!$C$17:$C$46+Projects!$D$17:$D$46-1)*Projects!$B$17:$B$46*Assumptions!$B$10*0.05)+SUMPRODUCT((Projects!$G$7:$G$14="Yes")*(32>=Projects!$C$7:$C$14)*(32<Projects!$C$7:$C$14+Projects!$D$7:$D$14)*Projects!$B$7:$B$14*Assumptions!$B$12/Projects!$D$7:$D$14*0.95)+SUMPRODUCT((Projects!$G$7:$G$14="Yes")*(32=Projects!$C$7:$C$14+Projects!$D$7:$D$14-1)*Projects!$B$7:$B$14*Assumptions!$B$12*0.05)+SUMPRODUCT((Projects!$G$17:$G$46="Yes")*(32>=Projects!$C$17:$C$46)*(32<Projects!$C$17:$C$46+Projects!$D$17:$D$46)*Projects!$B$17:$B$46*Assumptions!$B$12/Projects!$D$17:$D$46*0.95)+SUMPRODUCT((Projects!$G$17:$G$46="Yes")*(32=Projects!$C$17:$C$46+Projects!$D$17:$D$46-1)*Projects!$B$17:$B$46*Assumptions!$B$12*0.05),Actuals!AK8) -> 316830.78 | AK10: =IF(ISBLANK(Actuals!AL8),0+SUMPRODUCT((Projects!$G$7:$G$14="Yes")*(33>=Projects!$C$7:$C$14)*(33<Projects!$C$7:$C$14+Projects!$D$7:$D$14)*Projects!$B$7:$B$14*Assumptions!$B$10/Projects!$D$7:$D$14*0.95)+SUMPRODUCT((Projects!$G$7:$G$14="Yes")*(33=Projects!$C$7:$C$14+Projects!$D$7:$D$14-1)*Projects!$B$7:$B$14*Assumptions!$B$10*0.05)+SUMPRODUCT((Projects!$G$17:$G$46="Yes")*(33>=Projects!$C$17:$C$46)*(33<Projects!$C$17:$C$46+Projects!$D$17:$D$46)*Projects!$B$17:$B$46*Assumptions!$B$10/Projects!$D$17:$D$46*0.95)+SUMPRODUCT((Projects!$G$17:$G$46="Yes")*(33=Projects!$C$17:$C$46+Projects!$D$17:$D$46-1)*Projects!$B$17:$B$46*Assumptions!$B$10*0.05)+SUMPRODUCT((Projects!$G$7:$G$14="Yes")*(33>=Projects!$C$7:$C$14)*(33<Projects!$C$7:$C$14+Projects!$D$7:$D$14)*Projects!$B$7:$B$14*Assumptions!$B$12/Projects!$D$7:$D$14*0.95)+SUMPRODUCT((Projects!$G$7:$G$14="Yes")*(33=Projects!$C$7:$C$14+Projects!$D$7:$D$14-1)*Projects!$B$7:$B$14*Assumptions!$B$12*0.05)+SUMPRODUCT((Projects!$G$17:$G$46="Yes")*(33>=Projects!$C$17:$C$46)*(33<Projects!$C$17:$C$46+Projects!$D$17:$D$46)*Projects!$B$17:$B$46*Assumptions!$B$12/Projects!$D$17:$D$46*0.95)+SUMPRODUCT((Projects!$G$17:$G$46="Yes")*(33=Projects!$C$17:$C$46+Projects!$D$17:$D$46-1)*Projects!$B$17:$B$46*Assumptions!$B$12*0.05),Actuals!AL8) -> 316830.78 | AL10: =IF(ISBLANK(Actuals!AM8),0+SUMPRODUCT((Projects!$G$7:$G$14="Yes")*(34>=Projects!$C$7:$C$14)*(34<Projects!$C$7:$C$14+Projects!$D$7:$D$14)*Projects!$B$7:$B$14*Assumptions!$B$10/Projects!$D$7:$D$14*0.95)+SUMPRODUCT((Projects!$G$7:$G$14="Yes")*(34=Projects!$C$7:$C$14+Projects!$D$7:$D$14-1)*Projects!$B$7:$B$14*Assumptions!$B$10*0.05)+SUMPRODUCT((Projects!$G$17:$G$46="Yes")*(34>=Projects!$C$17:$C$46)*(34<Projects!$C$17:$C$46+Projects!$D$17:$D$46)*Projects!$B$17:$B$46*Assumptions!$B$10/Projects!$D$17:$D$46*0.95)+SUMPRODUCT((Projects!$G$17:$G$46="Yes")*(34=Projects!$C$17:$C$46+Projects!$D$17:$D$46-1)*Projects!$B$17:$B$46*Assumptions!$B$10*0.05)+SUMPRODUCT((Projects!$G$7:$G$14="Yes")*(34>=Projects!$C$7:$C$14)*(34<Projects!$C$7:$C$14+Projects!$D$7:$D$14)*Projects!$B$7:$B$14*Assumptions!$B$12/Projects!$D$7:$D$14*0.95)+SUMPRODUCT((Projects!$G$7:$G$14="Yes")*(34=Projects!$C$7:$C$14+Projects!$D$7:$D$14-1)*Projects!$B$7:$B$14*Assumptions!$B$12*0.05)+SUMPRODUCT((Projects!$G$17:$G$46="Yes")*(34>=Projects!$C$17:$C$46)*(34<Projects!$C$17:$C$46+Projects!$D$17:$D$46)*Projects!$B$17:$B$46*Assumptions!$B$12/Projects!$D$17:$D$46*0.95)+SUMPRODUCT((Projects!$G$17:$G$46="Yes")*(34=Projects!$C$17:$C$46+Projects!$D$17:$D$46-1)*Projects!$B$17:$B$46*Assumptions!$B$12*0.05),Actuals!AM8) -> 316830.78 | AM10: =IF(ISBLANK(Actuals!AN8),0+SUMPRODUCT((Projects!$G$7:$G$14="Yes")*(35>=Projects!$C$7:$C$14)*(35<Projects!$C$7:$C$14+Projects!$D$7:$D$14)*Projects!$B$7:$B$14*Assumptions!$B$10/Projects!$D$7:$D$14*0.95)+SUMPRODUCT((Projects!$G$7:$G$14="Yes")*(35=Projects!$C$7:$C$14+Projects!$D$7:$D$14-1)*Projects!$B$7:$B$14*Assumptions!$B$10*0.05)+SUMPRODUCT((Projects!$G$17:$G$46="Yes")*(35>=Projects!$C$17:$C$46)*(35<Projects!$C$17:$C$46+Projects!$D$17:$D$46)*Projects!$B$17:$B$46*Assumptions!$B$10/Projects!$D$17:$D$46*0.95)+SUMPRODUCT((Projects!$G$17:$G$46="Yes")*(35=Projects!$C$17:$C$46+Projects!$D$17:$D$46-1)*Projects!$B$17:$B$46*Assumptions!$B$10*0.05)+SUMPRODUCT((Projects!$G$7:$G$14="Yes")*(35>=Projects!$C$7:$C$14)*(35<Projects!$C$7:$C$14+Projects!$D$7:$D$14)*Projects!$B$7:$B$14*Assumptions!$B$12/Projects!$D$7:$D$14*0.95)+SUMPRODUCT((Projects!$G$7:$G$14="Yes")*(35=Projects!$C$7:$C$14+Projects!$D$7:$D$14-1)*Projects!$B$7:$B$14*Assumptions!$B$12*0.05)+SUMPRODUCT((Projects!$G$17:$G$46="Yes")*(35>=Projects!$C$17:$C$46)*(35<Projects!$C$17:$C$46+Projects!$D$17:$D$46)*Projects!$B$17:$B$46*Assumptions!$B$12/Projects!$D$17:$D$46*0.95)+SUMPRODUCT((Projects!$G$17:$G$46="Yes")*(35=Projects!$C$17:$C$46+Projects!$D$17:$D$46-1)*Projects!$B$17:$B$46*Assumptions!$B$12*0.05),Actuals!AN8) -> 464631.5 | AN10: =IF(ISBLANK(Actuals!AO8),0+SUMPRODUCT((Projects!$G$7:$G$14="Yes")*(36>=Projects!$C$7:$C$14)*(36<Projects!$C$7:$C$14+Projects!$D$7:$D$14)*Projects!$B$7:$B$14*Assumptions!$B$10/Projects!$D$7:$D$14*0.95)+SUMPRODUCT((Projects!$G$7:$G$14="Yes")*(36=Projects!$C$7:$C$14+Projects!$D$7:$D$14-1)*Projects!$B$7:$B$14*Assumptions!$B$10*0.05)+SUMPRODUCT((Projects!$G$17:$G$46="Yes")*(36>=Projects!$C$17:$C$46)*(36<Projects!$C$17:$C$46+Projects!$D$17:$D$46)*Projects!$B$17:$B$46*Assumptions!$B$10/Projects!$D$17:$D$46*0.95)+SUMPRODUCT((Projects!$G$17:$G$46="Yes")*(36=Projects!$C$17:$C$46+Projects!$D$17:$D$46-1)*Projects!$B$17:$B$46*Assumptions!$B$10*0.05)+SUMPRODUCT((Projects!$G$7:$G$14="Yes")*(36>=Projects!$C$7:$C$14)*(36<Projects!$C$7:$C$14+Projects!$D$7:$D$14)*Projects!$B$7:$B$14*Assumptions!$B$12/Projects!$D$7:$D$14*0.95)+SUMPRODUCT((Projects!$G$7:$G$14="Yes")*(36=Projects!$C$7:$C$14+Projects!$D$7:$D$14-1)*Projects!$B$7:$B$14*Assumptions!$B$12*0.05)+SUMPRODUCT((Projects!$G$17:$G$46="Yes")*(36>=Projects!$C$17:$C$46)*(36<Projects!$C$17:$C$46+Projects!$D$17:$D$46)*Projects!$B$17:$B$46*Assumptions!$B$12/Projects!$D$17:$D$46*0.95)+SUMPRODUCT((Projects!$G$17:$G$46="Yes")*(36=Projects!$C$17:$C$46+Projects!$D$17:$D$46-1)*Projects!$B$17:$B$46*Assumptions!$B$12*0.05),Actuals!AO8) -> 277726.09 | AO10: =IF(ISBLANK(Actuals!AP8),0+SUMPRODUCT((Projects!$G$7:$G$14="Yes")*(37>=Projects!$C$7:$C$14)*(37<Projects!$C$7:$C$14+Projects!$D$7:$D$14)*Projects!$B$7:$B$14*Assumptions!$B$10/Projects!$D$7:$D$14*0.95)+SUMPRODUCT((Projects!$G$7:$G$14="Yes")*(37=Projects!$C$7:$C$14+Projects!$D$7:$D$14-1)*Projects!$B$7:$B$14*Assumptions!$B$10*0.05)+SUMPRODUCT((Projects!$G$17:$G$46="Yes")*(37>=Projects!$C$17:$C$46)*(37<Projects!$C$17:$C$46+Projects!$D$17:$D$46)*Projects!$B$17:$B$46*Assumptions!$B$10/Projects!$D$17:$D$46*0.95)+SUMPRODUCT((Projects!$G$17:$G$46="Yes")*(37=Projects!$C$17:$C$46+Projects!$D$17:$D$46-1)*Projects!$B$17:$B$46*Assumptions!$B$10*0.05)+SUMPRODUCT((Projects!$G$7:$G$14="Yes")*(37>=Projects!$C$7:$C$14)*(37<Projects!$C$7:$C$14+Projects!$D$7:$D$14)*Projects!$B$7:$B$14*Assumptions!$B$12/Projects!$D$7:$D$14*0.95)+SUMPRODUCT((Projects!$G$7:$G$14="Yes")*(37=Projects!$C$7:$C$14+Projects!$D$7:$D$14-1)*Projects!$B$7:$B$14*Assumptions!$B$12*0.05)+SUMPRODUCT((Projects!$G$17:$G$46="Yes")*(37>=Projects!$C$17:$C$46)*(37<Projects!$C$17:$C$46+Projects!$D$17:$D$46)*Projects!$B$17:$B$46*Assumptions!$B$12/Projects!$D$17:$D$46*0.95)+SUMPRODUCT((Projects!$G$17:$G$46="Yes")*(37=Projects!$C$17:$C$46+Projects!$D$17:$D$46-1)*Projects!$B$17:$B$46*Assumptions!$B$12*0.05),Actuals!AP8) -> 188705.45 | AP10: =IF(ISBLANK(Actuals!AQ8),0+SUMPRODUCT((Projects!$G$7:$G$14="Yes")*(38>=Projects!$C$7:$C$14)*(38<Projects!$C$7:$C$14+Projects!$D$7:$D$14)*Projects!$B$7:$B$14*Assumptions!$B$10/Projects!$D$7:$D$14*0.95)+SUMPRODUCT((Projects!$G$7:$G$14="Yes")*(38=Projects!$C$7:$C$14+Projects!$D$7:$D$14-1)*Projects!$B$7:$B$14*Assumptions!$B$10*0.05)+SUMPRODUCT((Projects!$G$17:$G$46="Yes")*(38>=Projects!$C$17:$C$46)*(38<Projects!$C$17:$C$46+Projects!$D$17:$D$46)*Projects!$B$17:$B$46*Assumptions!$B$10/Projects!$D$17:$D$46*0.95)+SUMPRODUCT((Projects!$G$17:$G$46="Yes")*(38=Projects!$C$17:$C$46+Projects!$D$17:$D$46-1)*Projects!$B$17:$B$46*Assumptions!$B$10*0.05)+SUMPRODUCT((Projects!$G$7:$G$14="Yes")*(38>=Projects!$C$7:$C$14)*(38<Projects!$C$7:$C$14+Projects!$D$7:$D$14)*Projects!$B$7:$B$14*Assumptions!$B$12/Projects!$D$7:$D$14*0.95)+SUMPRODUCT((Projects!$G$7:$G$14="Yes")*(38=Projects!$C$7:$C$14+Projects!$D$7:$D$14-1)*Projects!$B$7:$B$14*Assumptions!$B$12*0.05)+SUMPRODUCT((Projects!$G$17:$G$46="Yes")*(38>=Projects!$C$17:$C$46)*(38<Projects!$C$17:$C$46+Projects!$D$17:$D$46)*Projects!$B$17:$B$46*Assumptions!$B$12/Projects!$D$17:$D$46*0.95)+SUMPRODUCT((Projects!$G$17:$G$46="Yes")*(38=Projects!$C$17:$C$46+Projects!$D$17:$D$46-1)*Projects!$B$17:$B$46*Assumptions!$B$12*0.05),Actuals!AQ8) -> 188705.45 | AQ10: =IF(ISBLANK(Actuals!AR8),0+SUMPRODUCT((Projects!$G$7:$G$14="Yes")*(39>=Projects!$C$7:$C$14)*(39<Projects!$C$7:$C$14+Projects!$D$7:$D$14)*Projects!$B$7:$B$14*Assumptions!$B$10/Projects!$D$7:$D$14*0.95)+SUMPRODUCT((Projects!$G$7:$G$14="Yes")*(39=Projects!$C$7:$C$14+Projects!$D$7:$D$14-1)*Projects!$B$7:$B$14*Assumptions!$B$10*0.05)+SUMPRODUCT((Projects!$G$17:$G$46="Yes")*(39>=Projects!$C$17:$C$46)*(39<Projects!$C$17:$C$46+Projects!$D$17:$D$46)*Projects!$B$17:$B$46*Assumptions!$B$10/Projects!$D$17:$D$46*0.95)+SUMPRODUCT((Projects!$G$17:$G$46="Yes")*(39=Projects!$C$17:$C$46+Projects!$D$17:$D$46-1)*Projects!$B$17:$B$46*Assumptions!$B$10*0.05)+SUMPRODUCT((Projects!$G$7:$G$14="Yes")*(39>=Projects!$C$7:$C$14)*(39<Projects!$C$7:$C$14+Projects!$D$7:$D$14)*Projects!$B$7:$B$14*Assumptions!$B$12/Projects!$D$7:$D$14*0.95)+SUMPRODUCT((Projects!$G$7:$G$14="Yes")*(39=Projects!$C$7:$C$14+Projects!$D$7:$D$14-1)*Projects!$B$7:$B$14*Assumptions!$B$12*0.05)+SUMPRODUCT((Projects!$G$17:$G$46="Yes")*(39>=Projects!$C$17:$C$46)*(39<Projects!$C$17:$C$46+Projects!$D$17:$D$46)*Projects!$B$17:$B$46*Assumptions!$B$12/Projects!$D$17:$D$46*0.95)+SUMPRODUCT((Projects!$G$17:$G$46="Yes")*(39=Projects!$C$17:$C$46+Projects!$D$17:$D$46-1)*Projects!$B$17:$B$46*Assumptions!$B$12*0.05),Actuals!AR8) -> 188705.45 | AR10: =IF(ISBLANK(Actuals!AS8),0+SUMPRODUCT((Projects!$G$7:$G$14="Yes")*(40>=Projects!$C$7:$C$14)*(40<Projects!$C$7:$C$14+Projects!$D$7:$D$14)*Projects!$B$7:$B$14*Assumptions!$B$10/Projects!$D$7:$D$14*0.95)+SUMPRODUCT((Projects!$G$7:$G$14="Yes")*(40=Projects!$C$7:$C$14+Projects!$D$7:$D$14-1)*Projects!$B$7:$B$14*Assumptions!$B$10*0.05)+SUMPRODUCT((Projects!$G$17:$G$46="Yes")*(40>=Projects!$C$17:$C$46)*(40<Projects!$C$17:$C$46+Projects!$D$17:$D$46)*Projects!$B$17:$B$46*Assumptions!$B$10/Projects!$D$17:$D$46*0.95)+SUMPRODUCT((Projects!$G$17:$G$46="Yes")*(40=Projects!$C$17:$C$46+Projects!$D$17:$D$46-1)*Projects!$B$17:$B$46*Assumptions!$B$10*0.05)+SUMPRODUCT((Projects!$G$7:$G$14="Yes")*(40>=Projects!$C$7:$C$14)*(40<Projects!$C$7:$C$14+Projects!$D$7:$D$14)*Projects!$B$7:$B$14*Assumptions!$B$12/Projects!$D$7:$D$14*0.95)+SUMPRODUCT((Projects!$G$7:$G$14="Yes")*(40=Projects!$C$7:$C$14+Projects!$D$7:$D$14-1)*Projects!$B$7:$B$14*Assumptions!$B$12*0.05)+SUMPRODUCT((Projects!$G$17:$G$46="Yes")*(40>=Projects!$C$17:$C$46)*(40<Projects!$C$17:$C$46+Projects!$D$17:$D$46)*Projects!$B$17:$B$46*Assumptions!$B$12/Projects!$D$17:$D$46*0.95)+SUMPRODUCT((Projects!$G$17:$G$46="Yes")*(40=Projects!$C$17:$C$46+Projects!$D$17:$D$46-1)*Projects!$B$17:$B$46*Assumptions!$B$12*0.05),Actuals!AS8) -> 188705.45 | AS10: =IF(ISBLANK(Actuals!AT8),0+SUMPRODUCT((Projects!$G$7:$G$14="Yes")*(41>=Projects!$C$7:$C$14)*(41<Projects!$C$7:$C$14+Projects!$D$7:$D$14)*Projects!$B$7:$B$14*Assumptions!$B$10/Projects!$D$7:$D$14*0.95)+SUMPRODUCT((Projects!$G$7:$G$14="Yes")*(41=Projects!$C$7:$C$14+Projects!$D$7:$D$14-1)*Projects!$B$7:$B$14*Assumptions!$B$10*0.05)+SUMPRODUCT((Projects!$G$17:$G$46="Yes")*(41>=Projects!$C$17:$C$46)*(41<Projects!$C$17:$C$46+Projects!$D$17:$D$46)*Projects!$B$17:$B$46*Assumptions!$B$10/Projects!$D$17:$D$46*0.95)+SUMPRODUCT((Projects!$G$17:$G$46="Yes")*(41=Projects!$C$17:$C$46+Projects!$D$17:$D$46-1)*Projects!$B$17:$B$46*Assumptions!$B$10*0.05)+SUMPRODUCT((Projects!$G$7:$G$14="Yes")*(41>=Projects!$C$7:$C$14)*(41<Projects!$C$7:$C$14+Projects!$D$7:$D$14)*Projects!$B$7:$B$14*Assumptions!$B$12/Projects!$D$7:$D$14*0.95)+SUMPRODUCT((Projects!$G$7:$G$14="Yes")*(41=Projects!$C$7:$C$14+Projects!$D$7:$D$14-1)*Projects!$B$7:$B$14*Assumptions!$B$12*0.05)+SUMPRODUCT((Projects!$G$17:$G$46="Yes")*(41>=Projects!$C$17:$C$46)*(41<Projects!$C$17:$C$46+Projects!$D$17:$D$46)*Projects!$B$17:$B$46*Assumptions!$B$12/Projects!$D$17:$D$46*0.95)+SUMPRODUCT((Projects!$G$17:$G$46="Yes")*(41=Projects!$C$17:$C$46+Projects!$D$17:$D$46-1)*Projects!$B$17:$B$46*Assumptions!$B$12*0.05),Actuals!AT8) -> 188705.45 | AT10: =IF(ISBLANK(Actuals!AU8),0+SUMPRODUCT((Projects!$G$7:$G$14="Yes")*(42>=Projects!$C$7:$C$14)*(42<Projects!$C$7:$C$14+Projects!$D$7:$D$14)*Projects!$B$7:$B$14*Assumptions!$B$10/Projects!$D$7:$D$14*0.95)+SUMPRODUCT((Projects!$G$7:$G$14="Yes")*(42=Projects!$C$7:$C$14+Projects!$D$7:$D$14-1)*Projects!$B$7:$B$14*Assumptions!$B$10*0.05)+SUMPRODUCT((Projects!$G$17:$G$46="Yes")*(42>=Projects!$C$17:$C$46)*(42<Projects!$C$17:$C$46+Projects!$D$17:$D$46)*Projects!$B$17:$B$46*Assumptions!$B$10/Projects!$D$17:$D$46*0.95)+SUMPRODUCT((Projects!$G$17:$G$46="Yes")*(42=Projects!$C$17:$C$46+Projects!$D$17:$D$46-1)*Projects!$B$17:$B$46*Assumptions!$B$10*0.05)+SUMPRODUCT((Projects!$G$7:$G$14="Yes")*(42>=Projects!$C$7:$C$14)*(42<Projects!$C$7:$C$14+Projects!$D$7:$D$14)*Projects!$B$7:$B$14*Assumptions!$B$12/Projects!$D$7:$D$14*0.95)+SUMPRODUCT((Projects!$G$7:$G$14="Yes")*(42=Projects!$C$7:$C$14+Projects!$D$7:$D$14-1)*Projects!$B$7:$B$14*Assumptions!$B$12*0.05)+SUMPRODUCT((Projects!$G$17:$G$46="Yes")*(42>=Projects!$C$17:$C$46)*(42<Projects!$C$17:$C$46+Projects!$D$17:$D$46)*Projects!$B$17:$B$46*Assumptions!$B$12/Projects!$D$17:$D$46*0.95)+SUMPRODUCT((Projects!$G$17:$G$46="Yes")*(42=Projects!$C$17:$C$46+Projects!$D$17:$D$46-1)*Projects!$B$17:$B$46*Assumptions!$B$12*0.05),Actuals!AU8) -> 344411.82 | AU10: =IF(ISBLANK(Actuals!AV8),0+SUMPRODUCT((Projects!$G$7:$G$14="Yes")*(43>=Projects!$C$7:$C$14)*(43<Projects!$C$7:$C$14+Projects!$D$7:$D$14)*Projects!$B$7:$B$14*Assumptions!$B$10/Projects!$D$7:$D$14*0.95)+SUMPRODUCT((Projects!$G$7:$G$14="Yes")*(43=Projects!$C$7:$C$14+Projects!$D$7:$D$14-1)*Projects!$B$7:$B$14*Assumptions!$B$10*0.05)+SUMPRODUCT((Projects!$G$17:$G$46="Yes")*(43>=Projects!$C$17:$C$46)*(43<Projects!$C$17:$C$46+Projects!$D$17:$D$46)*Projects!$B$17:$B$46*Assumptions!$B$10/Projects!$D$17:$D$46*0.95)+SUMPRODUCT((Projects!$G$17:$G$46="Yes")*(43=Projects!$C$17:$C$46+Projects!$D$17:$D$46-1)*Projects!$B$17:$B$46*Assumptions!$B$10*0.05)+SUMPRODUCT((Projects!$G$7:$G$14="Yes")*(43>=Projects!$C$7:$C$14)*(43<Projects!$C$7:$C$14+Projects!$D$7:$D$14)*Projects!$B$7:$B$14*Assumptions!$B$12/Projects!$D$7:$D$14*0.95)+SUMPRODUCT((Projects!$G$7:$G$14="Yes")*(43=Projects!$C$7:$C$14+Projects!$D$7:$D$14-1)*Projects!$B$7:$B$14*Assumptions!$B$12*0.05)+SUMPRODUCT((Projects!$G$17:$G$46="Yes")*(43>=Projects!$C$17:$C$46)*(43<Projects!$C$17:$C$46+Projects!$D$17:$D$46)*Projects!$B$17:$B$46*Assumptions!$B$12/Projects!$D$17:$D$46*0.95)+SUMPRODUCT((Projects!$G$17:$G$46="Yes")*(43=Projects!$C$17:$C$46+Projects!$D$17:$D$46-1)*Projects!$B$17:$B$46*Assumptions!$B$12*0.05),Actuals!AV8) -> 90091.41 | AV10: =IF(ISBLANK(Actuals!AW8),0+SUMPRODUCT((Projects!$G$7:$G$14="Yes")*(44>=Projects!$C$7:$C$14)*(44<Projects!$C$7:$C$14+Projects!$D$7:$D$14)*Projects!$B$7:$B$14*Assumptions!$B$10/Projects!$D$7:$D$14*0.95)+SUMPRODUCT((Projects!$G$7:$G$14="Yes")*(44=Projects!$C$7:$C$14+Projects!$D$7:$D$14-1)*Projects!$B$7:$B$14*Assumptions!$B$10*0.05)+SUMPRODUCT((Projects!$G$17:$G$46="Yes")*(44>=Projects!$C$17:$C$46)*(44<Projects!$C$17:$C$46+Projects!$D$17:$D$46)*Projects!$B$17:$B$46*Assumptions!$B$10/Projects!$D$17:$D$46*0.95)+SUMPRODUCT((Projects!$G$17:$G$46="Yes")*(44=Projects!$C$17:$C$46+Projects!$D$17:$D$46-1)*Projects!$B$17:$B$46*Assumptions!$B$10*0.05)+SUMPRODUCT((Projects!$G$7:$G$14="Yes")*(44>=Projects!$C$7:$C$14)*(44<Projects!$C$7:$C$14+Projects!$D$7:$D$14)*Projects!$B$7:$B$14*Assumptions!$B$12/Projects!$D$7:$D$14*0.95)+SUMPRODUCT((Projects!$G$7:$G$14="Yes")*(44=Projects!$C$7:$C$14+Projects!$D$7:$D$14-1)*Projects!$B$7:$B$14*Assumptions!$B$12*0.05)+SUMPRODUCT((Projects!$G$17:$G$46="Yes")*(44>=Projects!$C$17:$C$46)*(44<Projects!$C$17:$C$46+Projects!$D$17:$D$46)*Projects!$B$17:$B$46*Assumptions!$B$12/Projects!$D$17:$D$46*0.95)+SUMPRODUCT((Projects!$G$17:$G$46="Yes")*(44=Projects!$C$17:$C$46+Projects!$D$17:$D$46-1)*Projects!$B$17:$B$46*Assumptions!$B$12*0.05),Actuals!AW8) -> 90091.41 | AW10: =IF(ISBLANK(Actuals!AX8),0+SUMPRODUCT((Projects!$G$7:$G$14="Yes")*(45>=Projects!$C$7:$C$14)*(45<Projects!$C$7:$C$14+Projects!$D$7:$D$14)*Projects!$B$7:$B$14*Assumptions!$B$10/Projects!$D$7:$D$14*0.95)+SUMPRODUCT((Projects!$G$7:$G$14="Yes")*(45=Projects!$C$7:$C$14+Projects!$D$7:$D$14-1)*Projects!$B$7:$B$14*Assumptions!$B$10*0.05)+SUMPRODUCT((Projects!$G$17:$G$46="Yes")*(45>=Projects!$C$17:$C$46)*(45<Projects!$C$17:$C$46+Projects!$D$17:$D$46)*Projects!$B$17:$B$46*Assumptions!$B$10/Projects!$D$17:$D$46*0.95)+SUMPRODUCT((Projects!$G$17:$G$46="Yes")*(45=Projects!$C$17:$C$46+Projects!$D$17:$D$46-1)*Projects!$B$17:$B$46*Assumptions!$B$10*0.05)+SUMPRODUCT((Projects!$G$7:$G$14="Yes")*(45>=Projects!$C$7:$C$14)*(45<Projects!$C$7:$C$14+Projects!$D$7:$D$14)*Projects!$B$7:$B$14*Assumptions!$B$12/Projects!$D$7:$D$14*0.95)+SUMPRODUCT((Projects!$G$7:$G$14="Yes")*(45=Projects!$C$7:$C$14+Projects!$D$7:$D$14-1)*Projects!$B$7:$B$14*Assumptions!$B$12*0.05)+SUMPRODUCT((Projects!$G$17:$G$46="Yes")*(45>=Projects!$C$17:$C$46)*(45<Projects!$C$17:$C$46+Projects!$D$17:$D$46)*Projects!$B$17:$B$46*Assumptions!$B$12/Projects!$D$17:$D$46*0.95)+SUMPRODUCT((Projects!$G$17:$G$46="Yes")*(45=Projects!$C$17:$C$46+Projects!$D$17:$D$46-1)*Projects!$B$17:$B$46*Assumptions!$B$12*0.05),Actuals!AX8) -> 90091.41 | AX10: =IF(ISBLANK(Actuals!AY8),0+SUMPRODUCT((Projects!$G$7:$G$14="Yes")*(46>=Projects!$C$7:$C$14)*(46<Projects!$C$7:$C$14+Projects!$D$7:$D$14)*Projects!$B$7:$B$14*Assumptions!$B$10/Projects!$D$7:$D$14*0.95)+SUMPRODUCT((Projects!$G$7:$G$14="Yes")*(46=Projects!$C$7:$C$14+Projects!$D$7:$D$14-1)*Projects!$B$7:$B$14*Assumptions!$B$10*0.05)+SUMPRODUCT((Projects!$G$17:$G$46="Yes")*(46>=Projects!$C$17:$C$46)*(46<Projects!$C$17:$C$46+Projects!$D$17:$D$46)*Projects!$B$17:$B$46*Assumptions!$B$10/Projects!$D$17:$D$46*0.95)+SUMPRODUCT((Projects!$G$17:$G$46="Yes")*(46=Projects!$C$17:$C$46+Projects!$D$17:$D$46-1)*Projects!$B$17:$B$46*Assumptions!$B$10*0.05)+SUMPRODUCT((Projects!$G$7:$G$14="Yes")*(46>=Projects!$C$7:$C$14)*(46<Projects!$C$7:$C$14+Projects!$D$7:$D$14)*Projects!$B$7:$B$14*Assumptions!$B$12/Projects!$D$7:$D$14*0.95)+SUMPRODUCT((Projects!$G$7:$G$14="Yes")*(46=Projects!$C$7:$C$14+Projects!$D$7:$D$14-1)*Projects!$B$7:$B$14*Assumptions!$B$12*0.05)+SUMPRODUCT((Projects!$G$17:$G$46="Yes")*(46>=Projects!$C$17:$C$46)*(46<Projects!$C$17:$C$46+Projects!$D$17:$D$46)*Projects!$B$17:$B$46*Assumptions!$B$12/Projects!$D$17:$D$46*0.95)+SUMPRODUCT((Projects!$G$17:$G$46="Yes")*(46=Projects!$C$17:$C$46+Projects!$D$17:$D$46-1)*Projects!$B$17:$B$46*Assumptions!$B$12*0.05),Actuals!AY8) -> 90091.41 | AY10: =IF(ISBLANK(Actuals!AZ8),0+SUMPRODUCT((Projects!$G$7:$G$14="Yes")*(47>=Projects!$C$7:$C$14)*(47<Projects!$C$7:$C$14+Projects!$D$7:$D$14)*Projects!$B$7:$B$14*Assumptions!$B$10/Projects!$D$7:$D$14*0.95)+SUMPRODUCT((Projects!$G$7:$G$14="Yes")*(47=Projects!$C$7:$C$14+Projects!$D$7:$D$14-1)*Projects!$B$7:$B$14*Assumptions!$B$10*0.05)+SUMPRODUCT((Projects!$G$17:$G$46="Yes")*(47>=Projects!$C$17:$C$46)*(47<Projects!$C$17:$C$46+Projects!$D$17:$D$46)*Projects!$B$17:$B$46*Assumptions!$B$10/Projects!$D$17:$D$46*0.95)+SUMPRODUCT((Projects!$G$17:$G$46="Yes")*(47=Projects!$C$17:$C$46+Projects!$D$17:$D$46-1)*Projects!$B$17:$B$46*Assumptions!$B$10*0.05)+SUMPRODUCT((Projects!$G$7:$G$14="Yes")*(47>=Projects!$C$7:$C$14)*(47<Projects!$C$7:$C$14+Projects!$D$7:$D$14)*Projects!$B$7:$B$14*Assumptions!$B$12/Projects!$D$7:$D$14*0.95)+SUMPRODUCT((Projects!$G$7:$G$14="Yes")*(47=Projects!$C$7:$C$14+Projects!$D$7:$D$14-1)*Projects!$B$7:$B$14*Assumptions!$B$12*0.05)+SUMPRODUCT((Projects!$G$17:$G$46="Yes")*(47>=Projects!$C$17:$C$46)*(47<Projects!$C$17:$C$46+Projects!$D$17:$D$46)*Projects!$B$17:$B$46*Assumptions!$B$12/Projects!$D$17:$D$46*0.95)+SUMPRODUCT((Projects!$G$17:$G$46="Yes")*(47=Projects!$C$17:$C$46+Projects!$D$17:$D$46-1)*Projects!$B$17:$B$46*Assumptions!$B$12*0.05),Actuals!AZ8) -> 90091.41 | AZ10: =IF(ISBLANK(Actuals!BA8),0+SUMPRODUCT((Projects!$G$7:$G$14="Yes")*(48>=Projects!$C$7:$C$14)*(48<Projects!$C$7:$C$14+Projects!$D$7:$D$14)*Projects!$B$7:$B$14*Assumptions!$B$10/Projects!$D$7:$D$14*0.95)+SUMPRODUCT((Projects!$G$7:$G$14="Yes")*(48=Projects!$C$7:$C$14+Projects!$D$7:$D$14-1)*Projects!$B$7:$B$14*Assumptions!$B$10*0.05)+SUMPRODUCT((Projects!$G$17:$G$46="Yes")*(48>=Projects!$C$17:$C$46)*(48<Projects!$C$17:$C$46+Projects!$D$17:$D$46)*Projects!$B$17:$B$46*Assumptions!$B$10/Projects!$D$17:$D$46*0.95)+SUMPRODUCT((Projects!$G$17:$G$46="Yes")*(48=Projects!$C$17:$C$46+Projects!$D$17:$D$46-1)*Projects!$B$17:$B$46*Assumptions!$B$10*0.05)+SUMPRODUCT((Projects!$G$7:$G$14="Yes")*(48>=Projects!$C$7:$C$14)*(48<Projects!$C$7:$C$14+Projects!$D$7:$D$14)*Projects!$B$7:$B$14*Assumptions!$B$12/Projects!$D$7:$D$14*0.95)+SUMPRODUCT((Projects!$G$7:$G$14="Yes")*(48=Projects!$C$7:$C$14+Projects!$D$7:$D$14-1)*Projects!$B$7:$B$14*Assumptions!$B$12*0.05)+SUMPRODUCT((Projects!$G$17:$G$46="Yes")*(48>=Projects!$C$17:$C$46)*(48<Projects!$C$17:$C$46+Projects!$D$17:$D$46)*Projects!$B$17:$B$46*Assumptions!$B$12/Projects!$D$17:$D$46*0.95)+SUMPRODUCT((Projects!$G$17:$G$46="Yes")*(48=Projects!$C$17:$C$46+Projects!$D$17:$D$46-1)*Projects!$B$17:$B$46*Assumptions!$B$12*0.05),Actuals!BA8) -> 90091.41 | BA10: =IF(ISBLANK(Actuals!BB8),0+SUMPRODUCT((Projects!$G$7:$G$14="Yes")*(49>=Projects!$C$7:$C$14)*(49<Projects!$C$7:$C$14+Projects!$D$7:$D$14)*Projects!$B$7:$B$14*Assumptions!$B$10/Projects!$D$7:$D$14*0.95)+SUMPRODUCT((Projects!$G$7:$G$14="Yes")*(49=Projects!$C$7:$C$14+Projects!$D$7:$D$14-1)*Projects!$B$7:$B$14*Assumptions!$B$10*0.05)+SUMPRODUCT((Projects!$G$17:$G$46="Yes")*(49>=Projects!$C$17:$C$46)*(49<Projects!$C$17:$C$46+Projects!$D$17:$D$46)*Projects!$B$17:$B$46*Assumptions!$B$10/Projects!$D$17:$D$46*0.95)+SUMPRODUCT((Projects!$G$17:$G$46="Yes")*(49=Projects!$C$17:$C$46+Projects!$D$17:$D$46-1)*Projects!$B$17:$B$46*Assumptions!$B$10*0.05)+SUMPRODUCT((Projects!$G$7:$G$14="Yes")*(49>=Projects!$C$7:$C$14)*(49<Projects!$C$7:$C$14+Projects!$D$7:$D$14)*Projects!$B$7:$B$14*Assumptions!$B$12/Projects!$D$7:$D$14*0.95)+SUMPRODUCT((Projects!$G$7:$G$14="Yes")*(49=Projects!$C$7:$C$14+Projects!$D$7:$D$14-1)*Projects!$B$7:$B$14*Assumptions!$B$12*0.05)+SUMPRODUCT((Projects!$G$17:$G$46="Yes")*(49>=Projects!$C$17:$C$46)*(49<Projects!$C$17:$C$46+Projects!$D$17:$D$46)*Projects!$B$17:$B$46*Assumptions!$B$12/Projects!$D$17:$D$46*0.95)+SUMPRODUCT((Projects!$G$17:$G$46="Yes")*(49=Projects!$C$17:$C$46+Projects!$D$17:$D$46-1)*Projects!$B$17:$B$46*Assumptions!$B$12*0.05),Actuals!BB8) -> 90091.41 | BB10: =IF(ISBLANK(Actuals!BC8),0+SUMPRODUCT((Projects!$G$7:$G$14="Yes")*(50>=Projects!$C$7:$C$14)*(50<Projects!$C$7:$C$14+Projects!$D$7:$D$14)*Projects!$B$7:$B$14*Assumptions!$B$10/Projects!$D$7:$D$14*0.95)+SUMPRODUCT((Projects!$G$7:$G$14="Yes")*(50=Projects!$C$7:$C$14+Projects!$D$7:$D$14-1)*Projects!$B$7:$B$14*Assumptions!$B$10*0.05)+SUMPRODUCT((Projects!$G$17:$G$46="Yes")*(50>=Projects!$C$17:$C$46)*(50<Projects!$C$17:$C$46+Projects!$D$17:$D$46)*Projects!$B$17:$B$46*Assumptions!$B$10/Projects!$D$17:$D$46*0.95)+SUMPRODUCT((Projects!$G$17:$G$46="Yes")*(50=Projects!$C$17:$C$46+Projects!$D$17:$D$46-1)*Projects!$B$17:$B$46*Assumptions!$B$10*0.05)+SUMPRODUCT((Projects!$G$7:$G$14="Yes")*(50>=Projects!$C$7:$C$14)*(50<Projects!$C$7:$C$14+Projects!$D$7:$D$14)*Projects!$B$7:$B$14*Assumptions!$B$12/Projects!$D$7:$D$14*0.95)+SUMPRODUCT((Projects!$G$7:$G$14="Yes")*(50=Projects!$C$7:$C$14+Projects!$D$7:$D$14-1)*Projects!$B$7:$B$14*Assumptions!$B$12*0.05)+SUMPRODUCT((Projects!$G$17:$G$46="Yes")*(50>=Projects!$C$17:$C$46)*(50<Projects!$C$17:$C$46+Projects!$D$17:$D$46)*Projects!$B$17:$B$46*Assumptions!$B$12/Projects!$D$17:$D$46*0.95)+SUMPRODUCT((Projects!$G$17:$G$46="Yes")*(50=Projects!$C$17:$C$46+Projects!$D$17:$D$46-1)*Projects!$B$17:$B$46*Assumptions!$B$12*0.05),Actuals!BC8) -> 90091.41 | BC10: =IF(ISBLANK(Actuals!BD8),0+SUMPRODUCT((Projects!$G$7:$G$14="Yes")*(51>=Projects!$C$7:$C$14)*(51<Projects!$C$7:$C$14+Projects!$D$7:$D$14)*Projects!$B$7:$B$14*Assumptions!$B$10/Projects!$D$7:$D$14*0.95)+SUMPRODUCT((Projects!$G$7:$G$14="Yes")*(51=Projects!$C$7:$C$14+Projects!$D$7:$D$14-1)*Projects!$B$7:$B$14*Assumptions!$B$10*0.05)+SUMPRODUCT((Projects!$G$17:$G$46="Yes")*(51>=Projects!$C$17:$C$46)*(51<Projects!$C$17:$C$46+Projects!$D$17:$D$46)*Projects!$B$17:$B$46*Assumptions!$B$10/Projects!$D$17:$D$46*0.95)+SUMPRODUCT((Projects!$G$17:$G$46="Yes")*(51=Projects!$C$17:$C$46+Projects!$D$17:$D$46-1)*Projects!$B$17:$B$46*Assumptions!$B$10*0.05)+SUMPRODUCT((Projects!$G$7:$G$14="Yes")*(51>=Projects!$C$7:$C$14)*(51<Projects!$C$7:$C$14+Projects!$D$7:$D$14)*Projects!$B$7:$B$14*Assumptions!$B$12/Projects!$D$7:$D$14*0.95)+SUMPRODUCT((Projects!$G$7:$G$14="Yes")*(51=Projects!$C$7:$C$14+Projects!$D$7:$D$14-1)*Projects!$B$7:$B$14*Assumptions!$B$12*0.05)+SUMPRODUCT((Projects!$G$17:$G$46="Yes")*(51>=Projects!$C$17:$C$46)*(51<Projects!$C$17:$C$46+Projects!$D$17:$D$46)*Projects!$B$17:$B$46*Assumptions!$B$12/Projects!$D$17:$D$46*0.95)+SUMPRODUCT((Projects!$G$17:$G$46="Yes")*(51=Projects!$C$17:$C$46+Projects!$D$17:$D$46-1)*Projects!$B$17:$B$46*Assumptions!$B$12*0.05),Actuals!BD8) -> 90091.41 | BD10: =IF(ISBLANK(Actuals!BE8),0+SUMPRODUCT((Projects!$G$7:$G$14="Yes")*(52>=Projects!$C$7:$C$14)*(52<Projects!$C$7:$C$14+Projects!$D$7:$D$14)*Projects!$B$7:$B$14*Assumptions!$B$10/Projects!$D$7:$D$14*0.95)+SUMPRODUCT((Projects!$G$7:$G$14="Yes")*(52=Projects!$C$7:$C$14+Projects!$D$7:$D$14-1)*Projects!$B$7:$B$14*Assumptions!$B$10*0.05)+SUMPRODUCT((Projects!$G$17:$G$46="Yes")*(52>=Projects!$C$17:$C$46)*(52<Projects!$C$17:$C$46+Projects!$D$17:$D$46)*Projects!$B$17:$B$46*Assumptions!$B$10/Projects!$D$17:$D$46*0.95)+SUMPRODUCT((Projects!$G$17:$G$46="Yes")*(52=Projects!$C$17:$C$46+Projects!$D$17:$D$46-1)*Projects!$B$17:$B$46*Assumptions!$B$10*0.05)+SUMPRODUCT((Projects!$G$7:$G$14="Yes")*(52>=Projects!$C$7:$C$14)*(52<Projects!$C$7:$C$14+Projects!$D$7:$D$14)*Projects!$B$7:$B$14*Assumptions!$B$12/Projects!$D$7:$D$14*0.95)+SUMPRODUCT((Projects!$G$7:$G$14="Yes")*(52=Projects!$C$7:$C$14+Projects!$D$7:$D$14-1)*Projects!$B$7:$B$14*Assumptions!$B$12*0.05)+SUMPRODUCT((Projects!$G$17:$G$46="Yes")*(52>=Projects!$C$17:$C$46)*(52<Projects!$C$17:$C$46+Projects!$D$17:$D$46)*Projects!$B$17:$B$46*Assumptions!$B$12/Projects!$D$17:$D$46*0.95)+SUMPRODUCT((Projects!$G$17:$G$46="Yes")*(52=Projects!$C$17:$C$46+Projects!$D$17:$D$46-1)*Projects!$B$17:$B$46*Assumptions!$B$12*0.05),Actuals!BE8) -> 90091.41 | BE10: =IF(ISBLANK(Actuals!BF8),0+SUMPRODUCT((Projects!$G$7:$G$14="Yes")*(53>=Projects!$C$7:$C$14)*(53<Projects!$C$7:$C$14+Projects!$D$7:$D$14)*Projects!$B$7:$B$14*Assumptions!$B$10/Projects!$D$7:$D$14*0.95)+SUMPRODUCT((Projects!$G$7:$G$14="Yes")*(53=Projects!$C$7:$C$14+Projects!$D$7:$D$14-1)*Projects!$B$7:$B$14*Assumptions!$B$10*0.05)+SUMPRODUCT((Projects!$G$17:$G$46="Yes")*(53>=Projects!$C$17:$C$46)*(53<Projects!$C$17:$C$46+Projects!$D$17:$D$46)*Projects!$B$17:$B$46*Assumptions!$B$10/Projects!$D$17:$D$46*0.95)+SUMPRODUCT((Projects!$G$17:$G$46="Yes")*(53=Projects!$C$17:$C$46+Projects!$D$17:$D$46-1)*Projects!$B$17:$B$46*Assumptions!$B$10*0.05)+SUMPRODUCT((Projects!$G$7:$G$14="Yes")*(53>=Projects!$C$7:$C$14)*(53<Projects!$C$7:$C$14+Projects!$D$7:$D$14)*Projects!$B$7:$B$14*Assumptions!$B$12/Projects!$D$7:$D$14*0.95)+SUMPRODUCT((Projects!$G$7:$G$14="Yes")*(53=Projects!$C$7:$C$14+Projects!$D$7:$D$14-1)*Projects!$B$7:$B$14*Assumptions!$B$12*0.05)+SUMPRODUCT((Projects!$G$17:$G$46="Yes")*(53>=Projects!$C$17:$C$46)*(53<Projects!$C$17:$C$46+Projects!$D$17:$D$46)*Projects!$B$17:$B$46*Assumptions!$B$12/Projects!$D$17:$D$46*0.95)+SUMPRODUCT((Projects!$G$17:$G$46="Yes")*(53=Projects!$C$17:$C$46+Projects!$D$17:$D$46-1)*Projects!$B$17:$B$46*Assumptions!$B$12*0.05),Actuals!BF8) -> 90091.41 | BF10: =IF(ISBLANK(Actuals!BG8),0+SUMPRODUCT((Projects!$G$7:$G$14="Yes")*(54>=Projects!$C$7:$C$14)*(54<Projects!$C$7:$C$14+Projects!$D$7:$D$14)*Projects!$B$7:$B$14*Assumptions!$B$10/Projects!$D$7:$D$14*0.95)+SUMPRODUCT((Projects!$G$7:$G$14="Yes")*(54=Projects!$C$7:$C$14+Projects!$D$7:$D$14-1)*Projects!$B$7:$B$14*Assumptions!$B$10*0.05)+SUMPRODUCT((Projects!$G$17:$G$46="Yes")*(54>=Projects!$C$17:$C$46)*(54<Projects!$C$17:$C$46+Projects!$D$17:$D$46)*Projects!$B$17:$B$46*Assumptions!$B$10/Projects!$D$17:$D$46*0.95)+SUMPRODUCT((Projects!$G$17:$G$46="Yes")*(54=Projects!$C$17:$C$46+Projects!$D$17:$D$46-1)*Projects!$B$17:$B$46*Assumptions!$B$10*0.05)+SUMPRODUCT((Projects!$G$7:$G$14="Yes")*(54>=Projects!$C$7:$C$14)*(54<Projects!$C$7:$C$14+Projects!$D$7:$D$14)*Projects!$B$7:$B$14*Assumptions!$B$12/Projects!$D$7:$D$14*0.95)+SUMPRODUCT((Projects!$G$7:$G$14="Yes")*(54=Projects!$C$7:$C$14+Projects!$D$7:$D$14-1)*Projects!$B$7:$B$14*Assumptions!$B$12*0.05)+SUMPRODUCT((Projects!$G$17:$G$46="Yes")*(54>=Projects!$C$17:$C$46)*(54<Projects!$C$17:$C$46+Projects!$D$17:$D$46)*Projects!$B$17:$B$46*Assumptions!$B$12/Projects!$D$17:$D$46*0.95)+SUMPRODUCT((Projects!$G$17:$G$46="Yes")*(54=Projects!$C$17:$C$46+Projects!$D$17:$D$46-1)*Projects!$B$17:$B$46*Assumptions!$B$12*0.05),Actuals!BG8) -> 90091.41 | BG10: =IF(ISBLANK(Actuals!BH8),0+SUMPRODUCT((Projects!$G$7:$G$14="Yes")*(55>=Projects!$C$7:$C$14)*(55<Projects!$C$7:$C$14+Projects!$D$7:$D$14)*Projects!$B$7:$B$14*Assumptions!$B$10/Projects!$D$7:$D$14*0.95)+SUMPRODUCT((Projects!$G$7:$G$14="Yes")*(55=Projects!$C$7:$C$14+Projects!$D$7:$D$14-1)*Projects!$B$7:$B$14*Assumptions!$B$10*0.05)+SUMPRODUCT((Projects!$G$17:$G$46="Yes")*(55>=Projects!$C$17:$C$46)*(55<Projects!$C$17:$C$46+Projects!$D$17:$D$46)*Projects!$B$17:$B$46*Assumptions!$B$10/Projects!$D$17:$D$46*0.95)+SUMPRODUCT((Projects!$G$17:$G$46="Yes")*(55=Projects!$C$17:$C$46+Projects!$D$17:$D$46-1)*Projects!$B$17:$B$46*Assumptions!$B$10*0.05)+SUMPRODUCT((Projects!$G$7:$G$14="Yes")*(55>=Projects!$C$7:$C$14)*(55<Projects!$C$7:$C$14+Projects!$D$7:$D$14)*Projects!$B$7:$B$14*Assumptions!$B$12/Projects!$D$7:$D$14*0.95)+SUMPRODUCT((Projects!$G$7:$G$14="Yes")*(55=Projects!$C$7:$C$14+Projects!$D$7:$D$14-1)*Projects!$B$7:$B$14*Assumptions!$B$12*0.05)+SUMPRODUCT((Projects!$G$17:$G$46="Yes")*(55>=Projects!$C$17:$C$46)*(55<Projects!$C$17:$C$46+Projects!$D$17:$D$46)*Projects!$B$17:$B$46*Assumptions!$B$12/Projects!$D$17:$D$46*0.95)+SUMPRODUCT((Projects!$G$17:$G$46="Yes")*(55=Projects!$C$17:$C$46+Projects!$D$17:$D$46-1)*Projects!$B$17:$B$46*Assumptions!$B$12*0.05),Actuals!BH8) -> 90091.41 | BH10: =IF(ISBLANK(Actuals!BI8),0+SUMPRODUCT((Projects!$G$7:$G$14="Yes")*(56>=Projects!$C$7:$C$14)*(56<Projects!$C$7:$C$14+Projects!$D$7:$D$14)*Projects!$B$7:$B$14*Assumptions!$B$10/Projects!$D$7:$D$14*0.95)+SUMPRODUCT((Projects!$G$7:$G$14="Yes")*(56=Projects!$C$7:$C$14+Projects!$D$7:$D$14-1)*Projects!$B$7:$B$14*Assumptions!$B$10*0.05)+SUMPRODUCT((Projects!$G$17:$G$46="Yes")*(56>=Projects!$C$17:$C$46)*(56<Projects!$C$17:$C$46+Projects!$D$17:$D$46)*Projects!$B$17:$B$46*Assumptions!$B$10/Projects!$D$17:$D$46*0.95)+SUMPRODUCT((Projects!$G$17:$G$46="Yes")*(56=Projects!$C$17:$C$46+Projects!$D$17:$D$46-1)*Projects!$B$17:$B$46*Assumptions!$B$10*0.05)+SUMPRODUCT((Projects!$G$7:$G$14="Yes")*(56>=Projects!$C$7:$C$14)*(56<Projects!$C$7:$C$14+Projects!$D$7:$D$14)*Projects!$B$7:$B$14*Assumptions!$B$12/Projects!$D$7:$D$14*0.95)+SUMPRODUCT((Projects!$G$7:$G$14="Yes")*(56=Projects!$C$7:$C$14+Projects!$D$7:$D$14-1)*Projects!$B$7:$B$14*Assumptions!$B$12*0.05)+SUMPRODUCT((Projects!$G$17:$G$46="Yes")*(56>=Projects!$C$17:$C$46)*(56<Projects!$C$17:$C$46+Projects!$D$17:$D$46)*Projects!$B$17:$B$46*Assumptions!$B$12/Projects!$D$17:$D$46*0.95)+SUMPRODUCT((Projects!$G$17:$G$46="Yes")*(56=Projects!$C$17:$C$46+Projects!$D$17:$D$46-1)*Projects!$B$17:$B$46*Assumptions!$B$12*0.05),Actuals!BI8) -> 232341.01 | BI10: =IF(ISBLANK(Actuals!BJ8),0+SUMPRODUCT((Projects!$G$7:$G$14="Yes")*(57>=Projects!$C$7:$C$14)*(57<Projects!$C$7:$C$14+Projects!$D$7:$D$14)*Projects!$B$7:$B$14*Assumptions!$B$10/Projects!$D$7:$D$14*0.95)+SUMPRODUCT((Projects!$G$7:$G$14="Yes")*(57=Projects!$C$7:$C$14+Projects!$D$7:$D$14-1)*Projects!$B$7:$B$14*Assumptions!$B$10*0.05)+SUMPRODUCT((Projects!$G$17:$G$46="Yes")*(57>=Projects!$C$17:$C$46)*(57<Projects!$C$17:$C$46+Projects!$D$17:$D$46)*Projects!$B$17:$B$46*Assumptions!$B$10/Projects!$D$17:$D$46*0.95)+SUMPRODUCT((Projects!$G$17:$G$46="Yes")*(57=Projects!$C$17:$C$46+Projects!$D$17:$D$46-1)*Projects!$B$17:$B$46*Assumptions!$B$10*0.05)+SUMPRODUCT((Projects!$G$7:$G$14="Yes")*(57>=Projects!$C$7:$C$14)*(57<Projects!$C$7:$C$14+Projects!$D$7:$D$14)*Projects!$B$7:$B$14*Assumptions!$B$12/Projects!$D$7:$D$14*0.95)+SUMPRODUCT((Projects!$G$7:$G$14="Yes")*(57=Projects!$C$7:$C$14+Projects!$D$7:$D$14-1)*Projects!$B$7:$B$14*Assumptions!$B$12*0.05)+SUMPRODUCT((Projects!$G$17:$G$46="Yes")*(57>=Projects!$C$17:$C$46)*(57<Projects!$C$17:$C$46+Projects!$D$17:$D$46)*Projects!$B$17:$B$46*Assumptions!$B$12/Projects!$D$17:$D$46*0.95)+SUMPRODUCT((Projects!$G$17:$G$46="Yes")*(57=Projects!$C$17:$C$46+Projects!$D$17:$D$46-1)*Projects!$B$17:$B$46*Assumptions!$B$12*0.05),Actuals!BJ8) -> 0 | BJ10: =IF(ISBLANK(Actuals!BK8),0+SUMPRODUCT((Projects!$G$7:$G$14="Yes")*(58>=Projects!$C$7:$C$14)*(58<Projects!$C$7:$C$14+Projects!$D$7:$D$14)*Projects!$B$7:$B$14*Assumptions!$B$10/Projects!$D$7:$D$14*0.95)+SUMPRODUCT((Projects!$G$7:$G$14="Yes")*(58=Projects!$C$7:$C$14+Projects!$D$7:$D$14-1)*Projects!$B$7:$B$14*Assumptions!$B$10*0.05)+SUMPRODUCT((Projects!$G$17:$G$46="Yes")*(58>=Projects!$C$17:$C$46)*(58<Projects!$C$17:$C$46+Projects!$D$17:$D$46)*Projects!$B$17:$B$46*Assumptions!$B$10/Projects!$D$17:$D$46*0.95)+SUMPRODUCT((Projects!$G$17:$G$46="Yes")*(58=Projects!$C$17:$C$46+Projects!$D$17:$D$46-1)*Projects!$B$17:$B$46*Assumptions!$B$10*0.05)+SUMPRODUCT((Projects!$G$7:$G$14="Yes")*(58>=Projects!$C$7:$C$14)*(58<Projects!$C$7:$C$14+Projects!$D$7:$D$14)*Projects!$B$7:$B$14*Assumptions!$B$12/Projects!$D$7:$D$14*0.95)+SUMPRODUCT((Projects!$G$7:$G$14="Yes")*(58=Projects!$C$7:$C$14+Projects!$D$7:$D$14-1)*Projects!$B$7:$B$14*Assumptions!$B$12*0.05)+SUMPRODUCT((Projects!$G$17:$G$46="Yes")*(58>=Projects!$C$17:$C$46)*(58<Projects!$C$17:$C$46+Projects!$D$17:$D$46)*Projects!$B$17:$B$46*Assumptions!$B$12/Projects!$D$17:$D$46*0.95)+SUMPRODUCT((Projects!$G$17:$G$46="Yes")*(58=Projects!$C$17:$C$46+Projects!$D$17:$D$46-1)*Projects!$B$17:$B$46*Assumptions!$B$12*0.05),Actuals!BK8) -> 0 | BK10: =IF(ISBLANK(Actuals!BL8),0+SUMPRODUCT((Projects!$G$7:$G$14="Yes")*(59>=Projects!$C$7:$C$14)*(59<Projects!$C$7:$C$14+Projects!$D$7:$D$14)*Projects!$B$7:$B$14*Assumptions!$B$10/Projects!$D$7:$D$14*0.95)+SUMPRODUCT((Projects!$G$7:$G$14="Yes")*(59=Projects!$C$7:$C$14+Projects!$D$7:$D$14-1)*Projects!$B$7:$B$14*Assumptions!$B$10*0.05)+SUMPRODUCT((Projects!$G$17:$G$46="Yes")*(59>=Projects!$C$17:$C$46)*(59<Projects!$C$17:$C$46+Projects!$D$17:$D$46)*Projects!$B$17:$B$46*Assumptions!$B$10/Projects!$D$17:$D$46*0.95)+SUMPRODUCT((Projects!$G$17:$G$46="Yes")*(59=Projects!$C$17:$C$46+Projects!$D$17:$D$46-1)*Projects!$B$17:$B$46*Assumptions!$B$10*0.05)+SUMPRODUCT((Projects!$G$7:$G$14="Yes")*(59>=Projects!$C$7:$C$14)*(59<Projects!$C$7:$C$14+Projects!$D$7:$D$14)*Projects!$B$7:$B$14*Assumptions!$B$12/Projects!$D$7:$D$14*0.95)+SUMPRODUCT((Projects!$G$7:$G$14="Yes")*(59=Projects!$C$7:$C$14+Projects!$D$7:$D$14-1)*Projects!$B$7:$B$14*Assumptions!$B$12*0.05)+SUMPRODUCT((Projects!$G$17:$G$46="Yes")*(59>=Projects!$C$17:$C$46)*(59<Projects!$C$17:$C$46+Projects!$D$17:$D$46)*Projects!$B$17:$B$46*Assumptions!$B$12/Projects!$D$17:$D$46*0.95)+SUMPRODUCT((Projects!$G$17:$G$46="Yes")*(59=Projects!$C$17:$C$46+Projects!$D$17:$D$46-1)*Projects!$B$17:$B$46*Assumptions!$B$12*0.05),Actuals!BL8) -> 0 | BL10: =IF(ISBLANK(Actuals!BM8),0+SUMPRODUCT((Projects!$G$7:$G$14="Yes")*(60>=Projects!$C$7:$C$14)*(60<Projects!$C$7:$C$14+Projects!$D$7:$D$14)*Projects!$B$7:$B$14*Assumptions!$B$10/Projects!$D$7:$D$14*0.95)+SUMPRODUCT((Projects!$G$7:$G$14="Yes")*(60=Projects!$C$7:$C$14+Projects!$D$7:$D$14-1)*Projects!$B$7:$B$14*Assumptions!$B$10*0.05)+SUMPRODUCT((Projects!$G$17:$G$46="Yes")*(60>=Projects!$C$17:$C$46)*(60<Projects!$C$17:$C$46+Projects!$D$17:$D$46)*Projects!$B$17:$B$46*Assumptions!$B$10/Projects!$D$17:$D$46*0.95)+SUMPRODUCT((Projects!$G$17:$G$46="Yes")*(60=Projects!$C$17:$C$46+Projects!$D$17:$D$46-1)*Projects!$B$17:$B$46*Assumptions!$B$10*0.05)+SUMPRODUCT((Projects!$G$7:$G$14="Yes")*(60>=Projects!$C$7:$C$14)*(60<Projects!$C$7:$C$14+Projects!$D$7:$D$14)*Projects!$B$7:$B$14*Assumptions!$B$12/Projects!$D$7:$D$14*0.95)+SUMPRODUCT((Projects!$G$7:$G$14="Yes")*(60=Projects!$C$7:$C$14+Projects!$D$7:$D$14-1)*Projects!$B$7:$B$14*Assumptions!$B$12*0.05)+SUMPRODUCT((Projects!$G$17:$G$46="Yes")*(60>=Projects!$C$17:$C$46)*(60<Projects!$C$17:$C$46+Projects!$D$17:$D$46)*Projects!$B$17:$B$46*Assumptions!$B$12/Projects!$D$17:$D$46*0.95)+SUMPRODUCT((Projects!$G$17:$G$46="Yes")*(60=Projects!$C$17:$C$46+Projects!$D$17:$D$46-1)*Projects!$B$17:$B$46*Assumptions!$B$12*0.05),Actuals!BM8) -> 0 | BM10: =IF(ISBLANK(Actuals!BN8),0+SUMPRODUCT((Projects!$G$7:$G$14="Yes")*(61>=Projects!$C$7:$C$14)*(61<Projects!$C$7:$C$14+Projects!$D$7:$D$14)*Projects!$B$7:$B$14*Assumptions!$B$10/Projects!$D$7:$D$14*0.95)+SUMPRODUCT((Projects!$G$7:$G$14="Yes")*(61=Projects!$C$7:$C$14+Projects!$D$7:$D$14-1)*Projects!$B$7:$B$14*Assumptions!$B$10*0.05)+SUMPRODUCT((Projects!$G$17:$G$46="Yes")*(61>=Projects!$C$17:$C$46)*(61<Projects!$C$17:$C$46+Projects!$D$17:$D$46)*Projects!$B$17:$B$46*Assumptions!$B$10/Projects!$D$17:$D$46*0.95)+SUMPRODUCT((Projects!$G$17:$G$46="Yes")*(61=Projects!$C$17:$C$46+Projects!$D$17:$D$46-1)*Projects!$B$17:$B$46*Assumptions!$B$10*0.05)+SUMPRODUCT((Projects!$G$7:$G$14="Yes")*(61>=Projects!$C$7:$C$14)*(61<Projects!$C$7:$C$14+Projects!$D$7:$D$14)*Projects!$B$7:$B$14*Assumptions!$B$12/Projects!$D$7:$D$14*0.95)+SUMPRODUCT((Projects!$G$7:$G$14="Yes")*(61=Projects!$C$7:$C$14+Projects!$D$7:$D$14-1)*Projects!$B$7:$B$14*Assumptions!$B$12*0.05)+SUMPRODUCT((Projects!$G$17:$G$46="Yes")*(61>=Projects!$C$17:$C$46)*(61<Projects!$C$17:$C$46+Projects!$D$17:$D$46)*Projects!$B$17:$B$46*Assumptions!$B$12/Projects!$D$17:$D$46*0.95)+SUMPRODUCT((Projects!$G$17:$G$46="Yes")*(61=Projects!$C$17:$C$46+Projects!$D$17:$D$46-1)*Projects!$B$17:$B$46*Assumptions!$B$12*0.05),Actuals!BN8) -> 0 | BN10: =IF(ISBLANK(Actuals!BO8),0+SUMPRODUCT((Projects!$G$7:$G$14="Yes")*(62>=Projects!$C$7:$C$14)*(62<Projects!$C$7:$C$14+Projects!$D$7:$D$14)*Projects!$B$7:$B$14*Assumptions!$B$10/Projects!$D$7:$D$14*0.95)+SUMPRODUCT((Projects!$G$7:$G$14="Yes")*(62=Projects!$C$7:$C$14+Projects!$D$7:$D$14-1)*Projects!$B$7:$B$14*Assumptions!$B$10*0.05)+SUMPRODUCT((Projects!$G$17:$G$46="Yes")*(62>=Projects!$C$17:$C$46)*(62<Projects!$C$17:$C$46+Projects!$D$17:$D$46)*Projects!$B$17:$B$46*Assumptions!$B$10/Projects!$D$17:$D$46*0.95)+SUMPRODUCT((Projects!$G$17:$G$46="Yes")*(62=Projects!$C$17:$C$46+Projects!$D$17:$D$46-1)*Projects!$B$17:$B$46*Assumptions!$B$10*0.05)+SUMPRODUCT((Projects!$G$7:$G$14="Yes")*(62>=Projects!$C$7:$C$14)*(62<Projects!$C$7:$C$14+Projects!$D$7:$D$14)*Projects!$B$7:$B$14*Assumptions!$B$12/Projects!$D$7:$D$14*0.95)+SUMPRODUCT((Projects!$G$7:$G$14="Yes")*(62=Projects!$C$7:$C$14+Projects!$D$7:$D$14-1)*Projects!$B$7:$B$14*Assumptions!$B$12*0.05)+SUMPRODUCT((Projects!$G$17:$G$46="Yes")*(62>=Projects!$C$17:$C$46)*(62<Projects!$C$17:$C$46+Projects!$D$17:$D$46)*Projects!$B$17:$B$46*Assumptions!$B$12/Projects!$D$17:$D$46*0.95)+SUMPRODUCT((Projects!$G$17:$G$46="Yes")*(62=Projects!$C$17:$C$46+Projects!$D$17:$D$46-1)*Projects!$B$17:$B$46*Assumptions!$B$12*0.05),Actuals!BO8) -> 0 | BO10: =IF(ISBLANK(Actuals!BP8),0+SUMPRODUCT((Projects!$G$7:$G$14="Yes")*(63>=Projects!$C$7:$C$14)*(63<Projects!$C$7:$C$14+Projects!$D$7:$D$14)*Projects!$B$7:$B$14*Assumptions!$B$10/Projects!$D$7:$D$14*0.95)+SUMPRODUCT((Projects!$G$7:$G$14="Yes")*(63=Projects!$C$7:$C$14+Projects!$D$7:$D$14-1)*Projects!$B$7:$B$14*Assumptions!$B$10*0.05)+SUMPRODUCT((Projects!$G$17:$G$46="Yes")*(63>=Projects!$C$17:$C$46)*(63<Projects!$C$17:$C$46+Projects!$D$17:$D$46)*Projects!$B$17:$B$46*Assumptions!$B$10/Projects!$D$17:$D$46*0.95)+SUMPRODUCT((Projects!$G$17:$G$46="Yes")*(63=Projects!$C$17:$C$46+Projects!$D$17:$D$46-1)*Projects!$B$17:$B$46*Assumptions!$B$10*0.05)+SUMPRODUCT((Projects!$G$7:$G$14="Yes")*(63>=Projects!$C$7:$C$14)*(63<Projects!$C$7:$C$14+Projects!$D$7:$D$14)*Projects!$B$7:$B$14*Assumptions!$B$12/Projects!$D$7:$D$14*0.95)+SUMPRODUCT((Projects!$G$7:$G$14="Yes")*(63=Projects!$C$7:$C$14+Projects!$D$7:$D$14-1)*Projects!$B$7:$B$14*Assumptions!$B$12*0.05)+SUMPRODUCT((Projects!$G$17:$G$46="Yes")*(63>=Projects!$C$17:$C$46)*(63<Projects!$C$17:$C$46+Projects!$D$17:$D$46)*Projects!$B$17:$B$46*Assumptions!$B$12/Projects!$D$17:$D$46*0.95)+SUMPRODUCT((Projects!$G$17:$G$46="Yes")*(63=Projects!$C$17:$C$46+Projects!$D$17:$D$46-1)*Projects!$B$17:$B$46*Assumptions!$B$12*0.05),Actuals!BP8) -> 0 | BP10: =IF(ISBLANK(Actuals!BQ8),0+SUMPRODUCT((Projects!$G$7:$G$14="Yes")*(64>=Projects!$C$7:$C$14)*(64<Projects!$C$7:$C$14+Projects!$D$7:$D$14)*Projects!$B$7:$B$14*Assumptions!$B$10/Projects!$D$7:$D$14*0.95)+SUMPRODUCT((Projects!$G$7:$G$14="Yes")*(64=Projects!$C$7:$C$14+Projects!$D$7:$D$14-1)*Projects!$B$7:$B$14*Assumptions!$B$10*0.05)+SUMPRODUCT((Projects!$G$17:$G$46="Yes")*(64>=Projects!$C$17:$C$46)*(64<Projects!$C$17:$C$46+Projects!$D$17:$D$46)*Projects!$B$17:$B$46*Assumptions!$B$10/Projects!$D$17:$D$46*0.95)+SUMPRODUCT((Projects!$G$17:$G$46="Yes")*(64=Projects!$C$17:$C$46+Projects!$D$17:$D$46-1)*Projects!$B$17:$B$46*Assumptions!$B$10*0.05)+SUMPRODUCT((Projects!$G$7:$G$14="Yes")*(64>=Projects!$C$7:$C$14)*(64<Projects!$C$7:$C$14+Projects!$D$7:$D$14)*Projects!$B$7:$B$14*Assumptions!$B$12/Projects!$D$7:$D$14*0.95)+SUMPRODUCT((Projects!$G$7:$G$14="Yes")*(64=Projects!$C$7:$C$14+Projects!$D$7:$D$14-1)*Projects!$B$7:$B$14*Assumptions!$B$12*0.05)+SUMPRODUCT((Projects!$G$17:$G$46="Yes")*(64>=Projects!$C$17:$C$46)*(64<Projects!$C$17:$C$46+Projects!$D$17:$D$46)*Projects!$B$17:$B$46*Assumptions!$B$12/Projects!$D$17:$D$46*0.95)+SUMPRODUCT((Projects!$G$17:$G$46="Yes")*(64=Projects!$C$17:$C$46+Projects!$D$17:$D$46-1)*Projects!$B$17:$B$46*Assumptions!$B$12*0.05),Actuals!BQ8) -> 0 | BQ10: =IF(ISBLANK(Actuals!BR8),0+SUMPRODUCT((Projects!$G$7:$G$14="Yes")*(65>=Projects!$C$7:$C$14)*(65<Projects!$C$7:$C$14+Projects!$D$7:$D$14)*Projects!$B$7:$B$14*Assumptions!$B$10/Projects!$D$7:$D$14*0.95)+SUMPRODUCT((Projects!$G$7:$G$14="Yes")*(65=Projects!$C$7:$C$14+Projects!$D$7:$D$14-1)*Projects!$B$7:$B$14*Assumptions!$B$10*0.05)+SUMPRODUCT((Projects!$G$17:$G$46="Yes")*(65>=Projects!$C$17:$C$46)*(65<Projects!$C$17:$C$46+Projects!$D$17:$D$46)*Projects!$B$17:$B$46*Assumptions!$B$10/Projects!$D$17:$D$46*0.95)+SUMPRODUCT((Projects!$G$17:$G$46="Yes")*(65=Projects!$C$17:$C$46+Projects!$D$17:$D$46-1)*Projects!$B$17:$B$46*Assumptions!$B$10*0.05)+SUMPRODUCT((Projects!$G$7:$G$14="Yes")*(65>=Projects!$C$7:$C$14)*(65<Projects!$C$7:$C$14+Projects!$D$7:$D$14)*Projects!$B$7:$B$14*Assumptions!$B$12/Projects!$D$7:$D$14*0.95)+SUMPRODUCT((Projects!$G$7:$G$14="Yes")*(65=Projects!$C$7:$C$14+Projects!$D$7:$D$14-1)*Projects!$B$7:$B$14*Assumptions!$B$12*0.05)+SUMPRODUCT((Projects!$G$17:$G$46="Yes")*(65>=Projects!$C$17:$C$46)*(65<Projects!$C$17:$C$46+Projects!$D$17:$D$46)*Projects!$B$17:$B$46*Assumptions!$B$12/Projects!$D$17:$D$46*0.95)+SUMPRODUCT((Projects!$G$17:$G$46="Yes")*(65=Projects!$C$17:$C$46+Projects!$D$17:$D$46-1)*Projects!$B$17:$B$46*Assumptions!$B$12*0.05),Actuals!BR8) -> 0 | BR10: =IF(ISBLANK(Actuals!BS8),0+SUMPRODUCT((Projects!$G$7:$G$14="Yes")*(66>=Projects!$C$7:$C$14)*(66<Projects!$C$7:$C$14+Projects!$D$7:$D$14)*Projects!$B$7:$B$14*Assumptions!$B$10/Projects!$D$7:$D$14*0.95)+SUMPRODUCT((Projects!$G$7:$G$14="Yes")*(66=Projects!$C$7:$C$14+Projects!$D$7:$D$14-1)*Projects!$B$7:$B$14*Assumptions!$B$10*0.05)+SUMPRODUCT((Projects!$G$17:$G$46="Yes")*(66>=Projects!$C$17:$C$46)*(66<Projects!$C$17:$C$46+Projects!$D$17:$D$46)*Projects!$B$17:$B$46*Assumptions!$B$10/Projects!$D$17:$D$46*0.95)+SUMPRODUCT((Projects!$G$17:$G$46="Yes")*(66=Projects!$C$17:$C$46+Projects!$D$17:$D$46-1)*Projects!$B$17:$B$46*Assumptions!$B$10*0.05)+SUMPRODUCT((Projects!$G$7:$G$14="Yes")*(66>=Projects!$C$7:$C$14)*(66<Projects!$C$7:$C$14+Projects!$D$7:$D$14)*Projects!$B$7:$B$14*Assumptions!$B$12/Projects!$D$7:$D$14*0.95)+SUMPRODUCT((Projects!$G$7:$G$14="Yes")*(66=Projects!$C$7:$C$14+Projects!$D$7:$D$14-1)*Projects!$B$7:$B$14*Assumptions!$B$12*0.05)+SUMPRODUCT((Projects!$G$17:$G$46="Yes")*(66>=Projects!$C$17:$C$46)*(66<Projects!$C$17:$C$46+Projects!$D$17:$D$46)*Projects!$B$17:$B$46*Assumptions!$B$12/Projects!$D$17:$D$46*0.95)+SUMPRODUCT((Projects!$G$17:$G$46="Yes")*(66=Projects!$C$17:$C$46+Projects!$D$17:$D$46-1)*Projects!$B$17:$B$46*Assumptions!$B$12*0.05),Actuals!BS8) -> 0 | BS10: =IF(ISBLANK(Actuals!BT8),0+SUMPRODUCT((Projects!$G$7:$G$14="Yes")*(67>=Projects!$C$7:$C$14)*(67<Projects!$C$7:$C$14+Projects!$D$7:$D$14)*Projects!$B$7:$B$14*Assumptions!$B$10/Projects!$D$7:$D$14*0.95)+SUMPRODUCT((Projects!$G$7:$G$14="Yes")*(67=Projects!$C$7:$C$14+Projects!$D$7:$D$14-1)*Projects!$B$7:$B$14*Assumptions!$B$10*0.05)+SUMPRODUCT((Projects!$G$17:$G$46="Yes")*(67>=Projects!$C$17:$C$46)*(67<Projects!$C$17:$C$46+Projects!$D$17:$D$46)*Projects!$B$17:$B$46*Assumptions!$B$10/Projects!$D$17:$D$46*0.95)+SUMPRODUCT((Projects!$G$17:$G$46="Yes")*(67=Projects!$C$17:$C$46+Projects!$D$17:$D$46-1)*Projects!$B$17:$B$46*Assumptions!$B$10*0.05)+SUMPRODUCT((Projects!$G$7:$G$14="Yes")*(67>=Projects!$C$7:$C$14)*(67<Projects!$C$7:$C$14+Projects!$D$7:$D$14)*Projects!$B$7:$B$14*Assumptions!$B$12/Projects!$D$7:$D$14*0.95)+SUMPRODUCT((Projects!$G$7:$G$14="Yes")*(67=Projects!$C$7:$C$14+Projects!$D$7:$D$14-1)*Projects!$B$7:$B$14*Assumptions!$B$12*0.05)+SUMPRODUCT((Projects!$G$17:$G$46="Yes")*(67>=Projects!$C$17:$C$46)*(67<Projects!$C$17:$C$46+Projects!$D$17:$D$46)*Projects!$B$17:$B$46*Assumptions!$B$12/Projects!$D$17:$D$46*0.95)+SUMPRODUCT((Projects!$G$17:$G$46="Yes")*(67=Projects!$C$17:$C$46+Projects!$D$17:$D$46-1)*Projects!$B$17:$B$46*Assumptions!$B$12*0.05),Actuals!BT8) -> 0 | BT10: =IF(ISBLANK(Actuals!BU8),0+SUMPRODUCT((Projects!$G$7:$G$14="Yes")*(68>=Projects!$C$7:$C$14)*(68<Projects!$C$7:$C$14+Projects!$D$7:$D$14)*Projects!$B$7:$B$14*Assumptions!$B$10/Projects!$D$7:$D$14*0.95)+SUMPRODUCT((Projects!$G$7:$G$14="Yes")*(68=Projects!$C$7:$C$14+Projects!$D$7:$D$14-1)*Projects!$B$7:$B$14*Assumptions!$B$10*0.05)+SUMPRODUCT((Projects!$G$17:$G$46="Yes")*(68>=Projects!$C$17:$C$46)*(68<Projects!$C$17:$C$46+Projects!$D$17:$D$46)*Projects!$B$17:$B$46*Assumptions!$B$10/Projects!$D$17:$D$46*0.95)+SUMPRODUCT((Projects!$G$17:$G$46="Yes")*(68=Projects!$C$17:$C$46+Projects!$D$17:$D$46-1)*Projects!$B$17:$B$46*Assumptions!$B$10*0.05)+SUMPRODUCT((Projects!$G$7:$G$14="Yes")*(68>=Projects!$C$7:$C$14)*(68<Projects!$C$7:$C$14+Projects!$D$7:$D$14)*Projects!$B$7:$B$14*Assumptions!$B$12/Projects!$D$7:$D$14*0.95)+SUMPRODUCT((Projects!$G$7:$G$14="Yes")*(68=Projects!$C$7:$C$14+Projects!$D$7:$D$14-1)*Projects!$B$7:$B$14*Assumptions!$B$12*0.05)+SUMPRODUCT((Projects!$G$17:$G$46="Yes")*(68>=Projects!$C$17:$C$46)*(68<Projects!$C$17:$C$46+Projects!$D$17:$D$46)*Projects!$B$17:$B$46*Assumptions!$B$12/Projects!$D$17:$D$46*0.95)+SUMPRODUCT((Projects!$G$17:$G$46="Yes")*(68=Projects!$C$17:$C$46+Projects!$D$17:$D$46-1)*Projects!$B$17:$B$46*Assumptions!$B$12*0.05),Actuals!BU8) -> 0 | BU10: =IF(ISBLANK(Actuals!BV8),0+SUMPRODUCT((Projects!$G$7:$G$14="Yes")*(69>=Projects!$C$7:$C$14)*(69<Projects!$C$7:$C$14+Projects!$D$7:$D$14)*Projects!$B$7:$B$14*Assumptions!$B$10/Projects!$D$7:$D$14*0.95)+SUMPRODUCT((Projects!$G$7:$G$14="Yes")*(69=Projects!$C$7:$C$14+Projects!$D$7:$D$14-1)*Projects!$B$7:$B$14*Assumptions!$B$10*0.05)+SUMPRODUCT((Projects!$G$17:$G$46="Yes")*(69>=Projects!$C$17:$C$46)*(69<Projects!$C$17:$C$46+Projects!$D$17:$D$46)*Projects!$B$17:$B$46*Assumptions!$B$10/Projects!$D$17:$D$46*0.95)+SUMPRODUCT((Projects!$G$17:$G$46="Yes")*(69=Projects!$C$17:$C$46+Projects!$D$17:$D$46-1)*Projects!$B$17:$B$46*Assumptions!$B$10*0.05)+SUMPRODUCT((Projects!$G$7:$G$14="Yes")*(69>=Projects!$C$7:$C$14)*(69<Projects!$C$7:$C$14+Projects!$D$7:$D$14)*Projects!$B$7:$B$14*Assumptions!$B$12/Projects!$D$7:$D$14*0.95)+SUMPRODUCT((Projects!$G$7:$G$14="Yes")*(69=Projects!$C$7:$C$14+Projects!$D$7:$D$14-1)*Projects!$B$7:$B$14*Assumptions!$B$12*0.05)+SUMPRODUCT((Projects!$G$17:$G$46="Yes")*(69>=Projects!$C$17:$C$46)*(69<Projects!$C$17:$C$46+Projects!$D$17:$D$46)*Projects!$B$17:$B$46*Assumptions!$B$12/Projects!$D$17:$D$46*0.95)+SUMPRODUCT((Projects!$G$17:$G$46="Yes")*(69=Projects!$C$17:$C$46+Projects!$D$17:$D$46-1)*Projects!$B$17:$B$46*Assumptions!$B$12*0.05),Actuals!BV8) -> 0 | BV10: =IF(ISBLANK(Actuals!BW8),0+SUMPRODUCT((Projects!$G$7:$G$14="Yes")*(70>=Projects!$C$7:$C$14)*(70<Projects!$C$7:$C$14+Projects!$D$7:$D$14)*Projects!$B$7:$B$14*Assumptions!$B$10/Projects!$D$7:$D$14*0.95)+SUMPRODUCT((Projects!$G$7:$G$14="Yes")*(70=Projects!$C$7:$C$14+Projects!$D$7:$D$14-1)*Projects!$B$7:$B$14*Assumptions!$B$10*0.05)+SUMPRODUCT((Projects!$G$17:$G$46="Yes")*(70>=Projects!$C$17:$C$46)*(70<Projects!$C$17:$C$46+Projects!$D$17:$D$46)*Projects!$B$17:$B$46*Assumptions!$B$10/Projects!$D$17:$D$46*0.95)+SUMPRODUCT((Projects!$G$17:$G$46="Yes")*(70=Projects!$C$17:$C$46+Projects!$D$17:$D$46-1)*Projects!$B$17:$B$46*Assumptions!$B$10*0.05)+SUMPRODUCT((Projects!$G$7:$G$14="Yes")*(70>=Projects!$C$7:$C$14)*(70<Projects!$C$7:$C$14+Projects!$D$7:$D$14)*Projects!$B$7:$B$14*Assumptions!$B$12/Projects!$D$7:$D$14*0.95)+SUMPRODUCT((Projects!$G$7:$G$14="Yes")*(70=Projects!$C$7:$C$14+Projects!$D$7:$D$14-1)*Projects!$B$7:$B$14*Assumptions!$B$12*0.05)+SUMPRODUCT((Projects!$G$17:$G$46="Yes")*(70>=Projects!$C$17:$C$46)*(70<Projects!$C$17:$C$46+Projects!$D$17:$D$46)*Projects!$B$17:$B$46*Assumptions!$B$12/Projects!$D$17:$D$46*0.95)+SUMPRODUCT((Projects!$G$17:$G$46="Yes")*(70=Projects!$C$17:$C$46+Projects!$D$17:$D$46-1)*Projects!$B$17:$B$46*Assumptions!$B$12*0.05),Actuals!BW8) -> 0 | BW10: =IF(ISBLANK(Actuals!BX8),0+SUMPRODUCT((Projects!$G$7:$G$14="Yes")*(71>=Projects!$C$7:$C$14)*(71<Projects!$C$7:$C$14+Projects!$D$7:$D$14)*Projects!$B$7:$B$14*Assumptions!$B$10/Projects!$D$7:$D$14*0.95)+SUMPRODUCT((Projects!$G$7:$G$14="Yes")*(71=Projects!$C$7:$C$14+Projects!$D$7:$D$14-1)*Projects!$B$7:$B$14*Assumptions!$B$10*0.05)+SUMPRODUCT((Projects!$G$17:$G$46="Yes")*(71>=Projects!$C$17:$C$46)*(71<Projects!$C$17:$C$46+Projects!$D$17:$D$46)*Projects!$B$17:$B$46*Assumptions!$B$10/Projects!$D$17:$D$46*0.95)+SUMPRODUCT((Projects!$G$17:$G$46="Yes")*(71=Projects!$C$17:$C$46+Projects!$D$17:$D$46-1)*Projects!$B$17:$B$46*Assumptions!$B$10*0.05)+SUMPRODUCT((Projects!$G$7:$G$14="Yes")*(71>=Projects!$C$7:$C$14)*(71<Projects!$C$7:$C$14+Projects!$D$7:$D$14)*Projects!$B$7:$B$14*Assumptions!$B$12/Projects!$D$7:$D$14*0.95)+SUMPRODUCT((Projects!$G$7:$G$14="Yes")*(71=Projects!$C$7:$C$14+Projects!$D$7:$D$14-1)*Projects!$B$7:$B$14*Assumptions!$B$12*0.05)+SUMPRODUCT((Projects!$G$17:$G$46="Yes")*(71>=Projects!$C$17:$C$46)*(71<Projects!$C$17:$C$46+Projects!$D$17:$D$46)*Projects!$B$17:$B$46*Assumptions!$B$12/Projects!$D$17:$D$46*0.95)+SUMPRODUCT((Projects!$G$17:$G$46="Yes")*(71=Projects!$C$17:$C$46+Projects!$D$17:$D$46-1)*Projects!$B$17:$B$46*Assumptions!$B$12*0.05),Actuals!BX8) -> 0 | BX10: =IF(ISBLANK(Actuals!BY8),0+SUMPRODUCT((Projects!$G$7:$G$14="Yes")*(72>=Projects!$C$7:$C$14)*(72<Projects!$C$7:$C$14+Projects!$D$7:$D$14)*Projects!$B$7:$B$14*Assumptions!$B$10/Projects!$D$7:$D$14*0.95)+SUMPRODUCT((Projects!$G$7:$G$14="Yes")*(72=Projects!$C$7:$C$14+Projects!$D$7:$D$14-1)*Projects!$B$7:$B$14*Assumptions!$B$10*0.05)+SUMPRODUCT((Projects!$G$17:$G$46="Yes")*(72>=Projects!$C$17:$C$46)*(72<Projects!$C$17:$C$46+Projects!$D$17:$D$46)*Projects!$B$17:$B$46*Assumptions!$B$10/Projects!$D$17:$D$46*0.95)+SUMPRODUCT((Projects!$G$17:$G$46="Yes")*(72=Projects!$C$17:$C$46+Projects!$D$17:$D$46-1)*Projects!$B$17:$B$46*Assumptions!$B$10*0.05)+SUMPRODUCT((Projects!$G$7:$G$14="Yes")*(72>=Projects!$C$7:$C$14)*(72<Projects!$C$7:$C$14+Projects!$D$7:$D$14)*Projects!$B$7:$B$14*Assumptions!$B$12/Projects!$D$7:$D$14*0.95)+SUMPRODUCT((Projects!$G$7:$G$14="Yes")*(72=Projects!$C$7:$C$14+Projects!$D$7:$D$14-1)*Projects!$B$7:$B$14*Assumptions!$B$12*0.05)+SUMPRODUCT((Projects!$G$17:$G$46="Yes")*(72>=Projects!$C$17:$C$46)*(72<Projects!$C$17:$C$46+Projects!$D$17:$D$46)*Projects!$B$17:$B$46*Assumptions!$B$12/Projects!$D$17:$D$46*0.95)+SUMPRODUCT((Projects!$G$17:$G$46="Yes")*(72=Projects!$C$17:$C$46+Projects!$D$17:$D$46-1)*Projects!$B$17:$B$46*Assumptions!$B$12*0.05),Actuals!BY8) -> 0 | BY10: =IF(ISBLANK(Actuals!BZ8),0+SUMPRODUCT((Projects!$G$7:$G$14="Yes")*(73>=Projects!$C$7:$C$14)*(73<Projects!$C$7:$C$14+Projects!$D$7:$D$14)*Projects!$B$7:$B$14*Assumptions!$B$10/Projects!$D$7:$D$14*0.95)+SUMPRODUCT((Projects!$G$7:$G$14="Yes")*(73=Projects!$C$7:$C$14+Projects!$D$7:$D$14-1)*Projects!$B$7:$B$14*Assumptions!$B$10*0.05)+SUMPRODUCT((Projects!$G$17:$G$46="Yes")*(73>=Projects!$C$17:$C$46)*(73<Projects!$C$17:$C$46+Projects!$D$17:$D$46)*Projects!$B$17:$B$46*Assumptions!$B$10/Projects!$D$17:$D$46*0.95)+SUMPRODUCT((Projects!$G$17:$G$46="Yes")*(73=Projects!$C$17:$C$46+Projects!$D$17:$D$46-1)*Projects!$B$17:$B$46*Assumptions!$B$10*0.05)+SUMPRODUCT((Projects!$G$7:$G$14="Yes")*(73>=Projects!$C$7:$C$14)*(73<Projects!$C$7:$C$14+Projects!$D$7:$D$14)*Projects!$B$7:$B$14*Assumptions!$B$12/Projects!$D$7:$D$14*0.95)+SUMPRODUCT((Projects!$G$7:$G$14="Yes")*(73=Projects!$C$7:$C$14+Projects!$D$7:$D$14-1)*Projects!$B$7:$B$14*Assumptions!$B$12*0.05)+SUMPRODUCT((Projects!$G$17:$G$46="Yes")*(73>=Projects!$C$17:$C$46)*(73<Projects!$C$17:$C$46+Projects!$D$17:$D$46)*Projects!$B$17:$B$46*Assumptions!$B$12/Projects!$D$17:$D$46*0.95)+SUMPRODUCT((Projects!$G$17:$G$46="Yes")*(73=Projects!$C$17:$C$46+Projects!$D$17:$D$46-1)*Projects!$B$17:$B$46*Assumptions!$B$12*0.05),Actuals!BZ8) -> 0 | BZ10: =IF(ISBLANK(Actuals!CA8),0+SUMPRODUCT((Projects!$G$7:$G$14="Yes")*(74>=Projects!$C$7:$C$14)*(74<Projects!$C$7:$C$14+Projects!$D$7:$D$14)*Projects!$B$7:$B$14*Assumptions!$B$10/Projects!$D$7:$D$14*0.95)+SUMPRODUCT((Projects!$G$7:$G$14="Yes")*(74=Projects!$C$7:$C$14+Projects!$D$7:$D$14-1)*Projects!$B$7:$B$14*Assumptions!$B$10*0.05)+SUMPRODUCT((Projects!$G$17:$G$46="Yes")*(74>=Projects!$C$17:$C$46)*(74<Projects!$C$17:$C$46+Projects!$D$17:$D$46)*Projects!$B$17:$B$46*Assumptions!$B$10/Projects!$D$17:$D$46*0.95)+SUMPRODUCT((Projects!$G$17:$G$46="Yes")*(74=Projects!$C$17:$C$46+Projects!$D$17:$D$46-1)*Projects!$B$17:$B$46*Assumptions!$B$10*0.05)+SUMPRODUCT((Projects!$G$7:$G$14="Yes")*(74>=Projects!$C$7:$C$14)*(74<Projects!$C$7:$C$14+Projects!$D$7:$D$14)*Projects!$B$7:$B$14*Assumptions!$B$12/Projects!$D$7:$D$14*0.95)+SUMPRODUCT((Projects!$G$7:$G$14="Yes")*(74=Projects!$C$7:$C$14+Projects!$D$7:$D$14-1)*Projects!$B$7:$B$14*Assumptions!$B$12*0.05)+SUMPRODUCT((Projects!$G$17:$G$46="Yes")*(74>=Projects!$C$17:$C$46)*(74<Projects!$C$17:$C$46+Projects!$D$17:$D$46)*Projects!$B$17:$B$46*Assumptions!$B$12/Projects!$D$17:$D$46*0.95)+SUMPRODUCT((Projects!$G$17:$G$46="Yes")*(74=Projects!$C$17:$C$46+Projects!$D$17:$D$46-1)*Projects!$B$17:$B$46*Assumptions!$B$12*0.05),Actuals!CA8) -> 0 | CA10: =IF(ISBLANK(Actuals!CB8),0+SUMPRODUCT((Projects!$G$7:$G$14="Yes")*(75>=Projects!$C$7:$C$14)*(75<Projects!$C$7:$C$14+Projects!$D$7:$D$14)*Projects!$B$7:$B$14*Assumptions!$B$10/Projects!$D$7:$D$14*0.95)+SUMPRODUCT((Projects!$G$7:$G$14="Yes")*(75=Projects!$C$7:$C$14+Projects!$D$7:$D$14-1)*Projects!$B$7:$B$14*Assumptions!$B$10*0.05)+SUMPRODUCT((Projects!$G$17:$G$46="Yes")*(75>=Projects!$C$17:$C$46)*(75<Projects!$C$17:$C$46+Projects!$D$17:$D$46)*Projects!$B$17:$B$46*Assumptions!$B$10/Projects!$D$17:$D$46*0.95)+SUMPRODUCT((Projects!$G$17:$G$46="Yes")*(75=Projects!$C$17:$C$46+Projects!$D$17:$D$46-1)*Projects!$B$17:$B$46*Assumptions!$B$10*0.05)+SUMPRODUCT((Projects!$G$7:$G$14="Yes")*(75>=Projects!$C$7:$C$14)*(75<Projects!$C$7:$C$14+Projects!$D$7:$D$14)*Projects!$B$7:$B$14*Assumptions!$B$12/Projects!$D$7:$D$14*0.95)+SUMPRODUCT((Projects!$G$7:$G$14="Yes")*(75=Projects!$C$7:$C$14+Projects!$D$7:$D$14-1)*Projects!$B$7:$B$14*Assumptions!$B$12*0.05)+SUMPRODUCT((Projects!$G$17:$G$46="Yes")*(75>=Projects!$C$17:$C$46)*(75<Projects!$C$17:$C$46+Projects!$D$17:$D$46)*Projects!$B$17:$B$46*Assumptions!$B$12/Projects!$D$17:$D$46*0.95)+SUMPRODUCT((Projects!$G$17:$G$46="Yes")*(75=Projects!$C$17:$C$46+Projects!$D$17:$D$46-1)*Projects!$B$17:$B$46*Assumptions!$B$12*0.05),Actuals!CB8) -> 0 | CB10: =IF(ISBLANK(Actuals!CC8),0+SUMPRODUCT((Projects!$G$7:$G$14="Yes")*(76>=Projects!$C$7:$C$14)*(76<Projects!$C$7:$C$14+Projects!$D$7:$D$14)*Projects!$B$7:$B$14*Assumptions!$B$10/Projects!$D$7:$D$14*0.95)+SUMPRODUCT((Projects!$G$7:$G$14="Yes")*(76=Projects!$C$7:$C$14+Projects!$D$7:$D$14-1)*Projects!$B$7:$B$14*Assumptions!$B$10*0.05)+SUMPRODUCT((Projects!$G$17:$G$46="Yes")*(76>=Projects!$C$17:$C$46)*(76<Projects!$C$17:$C$46+Projects!$D$17:$D$46)*Projects!$B$17:$B$46*Assumptions!$B$10/Projects!$D$17:$D$46*0.95)+SUMPRODUCT((Projects!$G$17:$G$46="Yes")*(76=Projects!$C$17:$C$46+Projects!$D$17:$D$46-1)*Projects!$B$17:$B$46*Assumptions!$B$10*0.05)+SUMPRODUCT((Projects!$G$7:$G$14="Yes")*(76>=Projects!$C$7:$C$14)*(76<Projects!$C$7:$C$14+Projects!$D$7:$D$14)*Projects!$B$7:$B$14*Assumptions!$B$12/Projects!$D$7:$D$14*0.95)+SUMPRODUCT((Projects!$G$7:$G$14="Yes")*(76=Projects!$C$7:$C$14+Projects!$D$7:$D$14-1)*Projects!$B$7:$B$14*Assumptions!$B$12*0.05)+SUMPRODUCT((Projects!$G$17:$G$46="Yes")*(76>=Projects!$C$17:$C$46)*(76<Projects!$C$17:$C$46+Projects!$D$17:$D$46)*Projects!$B$17:$B$46*Assumptions!$B$12/Projects!$D$17:$D$46*0.95)+SUMPRODUCT((Projects!$G$17:$G$46="Yes")*(76=Projects!$C$17:$C$46+Projects!$D$17:$D$46-1)*Projects!$B$17:$B$46*Assumptions!$B$12*0.05),Actuals!CC8) -> 0 | CC10: =IF(ISBLANK(Actuals!CD8),0+SUMPRODUCT((Projects!$G$7:$G$14="Yes")*(77>=Projects!$C$7:$C$14)*(77<Projects!$C$7:$C$14+Projects!$D$7:$D$14)*Projects!$B$7:$B$14*Assumptions!$B$10/Projects!$D$7:$D$14*0.95)+SUMPRODUCT((Projects!$G$7:$G$14="Yes")*(77=Projects!$C$7:$C$14+Projects!$D$7:$D$14-1)*Projects!$B$7:$B$14*Assumptions!$B$10*0.05)+SUMPRODUCT((Projects!$G$17:$G$46="Yes")*(77>=Projects!$C$17:$C$46)*(77<Projects!$C$17:$C$46+Projects!$D$17:$D$46)*Projects!$B$17:$B$46*Assumptions!$B$10/Projects!$D$17:$D$46*0.95)+SUMPRODUCT((Projects!$G$17:$G$46="Yes")*(77=Projects!$C$17:$C$46+Projects!$D$17:$D$46-1)*Projects!$B$17:$B$46*Assumptions!$B$10*0.05)+SUMPRODUCT((Projects!$G$7:$G$14="Yes")*(77>=Projects!$C$7:$C$14)*(77<Projects!$C$7:$C$14+Projects!$D$7:$D$14)*Projects!$B$7:$B$14*Assumptions!$B$12/Projects!$D$7:$D$14*0.95)+SUMPRODUCT((Projects!$G$7:$G$14="Yes")*(77=Projects!$C$7:$C$14+Projects!$D$7:$D$14-1)*Projects!$B$7:$B$14*Assumptions!$B$12*0.05)+SUMPRODUCT((Projects!$G$17:$G$46="Yes")*(77>=Projects!$C$17:$C$46)*(77<Projects!$C$17:$C$46+Projects!$D$17:$D$46)*Projects!$B$17:$B$46*Assumptions!$B$12/Projects!$D$17:$D$46*0.95)+SUMPRODUCT((Projects!$G$17:$G$46="Yes")*(77=Projects!$C$17:$C$46+Projects!$D$17:$D$46-1)*Projects!$B$17:$B$46*Assumptions!$B$12*0.05),Actuals!CD8) -> 0 | CD10: =IF(ISBLANK(Actuals!CE8),0+SUMPRODUCT((Projects!$G$7:$G$14="Yes")*(78>=Projects!$C$7:$C$14)*(78<Projects!$C$7:$C$14+Projects!$D$7:$D$14)*Projects!$B$7:$B$14*Assumptions!$B$10/Projects!$D$7:$D$14*0.95)+SUMPRODUCT((Projects!$G$7:$G$14="Yes")*(78=Projects!$C$7:$C$14+Projects!$D$7:$D$14-1)*Projects!$B$7:$B$14*Assumptions!$B$10*0.05)+SUMPRODUCT((Projects!$G$17:$G$46="Yes")*(78>=Projects!$C$17:$C$46)*(78<Projects!$C$17:$C$46+Projects!$D$17:$D$46)*Projects!$B$17:$B$46*Assumptions!$B$10/Projects!$D$17:$D$46*0.95)+SUMPRODUCT((Projects!$G$17:$G$46="Yes")*(78=Projects!$C$17:$C$46+Projects!$D$17:$D$46-1)*Projects!$B$17:$B$46*Assumptions!$B$10*0.05)+SUMPRODUCT((Projects!$G$7:$G$14="Yes")*(78>=Projects!$C$7:$C$14)*(78<Projects!$C$7:$C$14+Projects!$D$7:$D$14)*Projects!$B$7:$B$14*Assumptions!$B$12/Projects!$D$7:$D$14*0.95)+SUMPRODUCT((Projects!$G$7:$G$14="Yes")*(78=Projects!$C$7:$C$14+Projects!$D$7:$D$14-1)*Projects!$B$7:$B$14*Assumptions!$B$12*0.05)+SUMPRODUCT((Projects!$G$17:$G$46="Yes")*(78>=Projects!$C$17:$C$46)*(78<Projects!$C$17:$C$46+Projects!$D$17:$D$46)*Projects!$B$17:$B$46*Assumptions!$B$12/Projects!$D$17:$D$46*0.95)+SUMPRODUCT((Projects!$G$17:$G$46="Yes")*(78=Projects!$C$17:$C$46+Projects!$D$17:$D$46-1)*Projects!$B$17:$B$46*Assumptions!$B$12*0.05),Actuals!CE8) -> 0 | CE10: =IF(ISBLANK(Actuals!CF8),0+SUMPRODUCT((Projects!$G$7:$G$14="Yes")*(79>=Projects!$C$7:$C$14)*(79<Projects!$C$7:$C$14+Projects!$D$7:$D$14)*Projects!$B$7:$B$14*Assumptions!$B$10/Projects!$D$7:$D$14*0.95)+SUMPRODUCT((Projects!$G$7:$G$14="Yes")*(79=Projects!$C$7:$C$14+Projects!$D$7:$D$14-1)*Projects!$B$7:$B$14*Assumptions!$B$10*0.05)+SUMPRODUCT((Projects!$G$17:$G$46="Yes")*(79>=Projects!$C$17:$C$46)*(79<Projects!$C$17:$C$46+Projects!$D$17:$D$46)*Projects!$B$17:$B$46*Assumptions!$B$10/Projects!$D$17:$D$46*0.95)+SUMPRODUCT((Projects!$G$17:$G$46="Yes")*(79=Projects!$C$17:$C$46+Projects!$D$17:$D$46-1)*Projects!$B$17:$B$46*Assumptions!$B$10*0.05)+SUMPRODUCT((Projects!$G$7:$G$14="Yes")*(79>=Projects!$C$7:$C$14)*(79<Projects!$C$7:$C$14+Projects!$D$7:$D$14)*Projects!$B$7:$B$14*Assumptions!$B$12/Projects!$D$7:$D$14*0.95)+SUMPRODUCT((Projects!$G$7:$G$14="Yes")*(79=Projects!$C$7:$C$14+Projects!$D$7:$D$14-1)*Projects!$B$7:$B$14*Assumptions!$B$12*0.05)+SUMPRODUCT((Projects!$G$17:$G$46="Yes")*(79>=Projects!$C$17:$C$46)*(79<Projects!$C$17:$C$46+Projects!$D$17:$D$46)*Projects!$B$17:$B$46*Assumptions!$B$12/Projects!$D$17:$D$46*0.95)+SUMPRODUCT((Projects!$G$17:$G$46="Yes")*(79=Projects!$C$17:$C$46+Projects!$D$17:$D$46-1)*Projects!$B$17:$B$46*Assumptions!$B$12*0.05),Actuals!CF8) -> 0 | CF10: =IF(ISBLANK(Actuals!CG8),0+SUMPRODUCT((Projects!$G$7:$G$14="Yes")*(80>=Projects!$C$7:$C$14)*(80<Projects!$C$7:$C$14+Projects!$D$7:$D$14)*Projects!$B$7:$B$14*Assumptions!$B$10/Projects!$D$7:$D$14*0.95)+SUMPRODUCT((Projects!$G$7:$G$14="Yes")*(80=Projects!$C$7:$C$14+Projects!$D$7:$D$14-1)*Projects!$B$7:$B$14*Assumptions!$B$10*0.05)+SUMPRODUCT((Projects!$G$17:$G$46="Yes")*(80>=Projects!$C$17:$C$46)*(80<Projects!$C$17:$C$46+Projects!$D$17:$D$46)*Projects!$B$17:$B$46*Assumptions!$B$10/Projects!$D$17:$D$46*0.95)+SUMPRODUCT((Projects!$G$17:$G$46="Yes")*(80=Projects!$C$17:$C$46+Projects!$D$17:$D$46-1)*Projects!$B$17:$B$46*Assumptions!$B$10*0.05)+SUMPRODUCT((Projects!$G$7:$G$14="Yes")*(80>=Projects!$C$7:$C$14)*(80<Projects!$C$7:$C$14+Projects!$D$7:$D$14)*Projects!$B$7:$B$14*Assumptions!$B$12/Projects!$D$7:$D$14*0.95)+SUMPRODUCT((Projects!$G$7:$G$14="Yes")*(80=Projects!$C$7:$C$14+Projects!$D$7:$D$14-1)*Projects!$B$7:$B$14*Assumptions!$B$12*0.05)+SUMPRODUCT((Projects!$G$17:$G$46="Yes")*(80>=Projects!$C$17:$C$46)*(80<Projects!$C$17:$C$46+Projects!$D$17:$D$46)*Projects!$B$17:$B$46*Assumptions!$B$12/Projects!$D$17:$D$46*0.95)+SUMPRODUCT((Projects!$G$17:$G$46="Yes")*(80=Projects!$C$17:$C$46+Projects!$D$17:$D$46-1)*Projects!$B$17:$B$46*Assumptions!$B$12*0.05),Actuals!CG8) -> 0 | CG10: =IF(ISBLANK(Actuals!CH8),0+SUMPRODUCT((Projects!$G$7:$G$14="Yes")*(81>=Projects!$C$7:$C$14)*(81<Projects!$C$7:$C$14+Projects!$D$7:$D$14)*Projects!$B$7:$B$14*Assumptions!$B$10/Projects!$D$7:$D$14*0.95)+SUMPRODUCT((Projects!$G$7:$G$14="Yes")*(81=Projects!$C$7:$C$14+Projects!$D$7:$D$14-1)*Projects!$B$7:$B$14*Assumptions!$B$10*0.05)+SUMPRODUCT((Projects!$G$17:$G$46="Yes")*(81>=Projects!$C$17:$C$46)*(81<Projects!$C$17:$C$46+Projects!$D$17:$D$46)*Projects!$B$17:$B$46*Assumptions!$B$10/Projects!$D$17:$D$46*0.95)+SUMPRODUCT((Projects!$G$17:$G$46="Yes")*(81=Projects!$C$17:$C$46+Projects!$D$17:$D$46-1)*Projects!$B$17:$B$46*Assumptions!$B$10*0.05)+SUMPRODUCT((Projects!$G$7:$G$14="Yes")*(81>=Projects!$C$7:$C$14)*(81<Projects!$C$7:$C$14+Projects!$D$7:$D$14)*Projects!$B$7:$B$14*Assumptions!$B$12/Projects!$D$7:$D$14*0.95)+SUMPRODUCT((Projects!$G$7:$G$14="Yes")*(81=Projects!$C$7:$C$14+Projects!$D$7:$D$14-1)*Projects!$B$7:$B$14*Assumptions!$B$12*0.05)+SUMPRODUCT((Projects!$G$17:$G$46="Yes")*(81>=Projects!$C$17:$C$46)*(81<Projects!$C$17:$C$46+Projects!$D$17:$D$46)*Projects!$B$17:$B$46*Assumptions!$B$12/Projects!$D$17:$D$46*0.95)+SUMPRODUCT((Projects!$G$17:$G$46="Yes")*(81=Projects!$C$17:$C$46+Projects!$D$17:$D$46-1)*Projects!$B$17:$B$46*Assumptions!$B$12*0.05),Actuals!CH8) -> 0 | CH10: =IF(ISBLANK(Actuals!CI8),0+SUMPRODUCT((Projects!$G$7:$G$14="Yes")*(82>=Projects!$C$7:$C$14)*(82<Projects!$C$7:$C$14+Projects!$D$7:$D$14)*Projects!$B$7:$B$14*Assumptions!$B$10/Projects!$D$7:$D$14*0.95)+SUMPRODUCT((Projects!$G$7:$G$14="Yes")*(82=Projects!$C$7:$C$14+Projects!$D$7:$D$14-1)*Projects!$B$7:$B$14*Assumptions!$B$10*0.05)+SUMPRODUCT((Projects!$G$17:$G$46="Yes")*(82>=Projects!$C$17:$C$46)*(82<Projects!$C$17:$C$46+Projects!$D$17:$D$46)*Projects!$B$17:$B$46*Assumptions!$B$10/Projects!$D$17:$D$46*0.95)+SUMPRODUCT((Projects!$G$17:$G$46="Yes")*(82=Projects!$C$17:$C$46+Projects!$D$17:$D$46-1)*Projects!$B$17:$B$46*Assumptions!$B$10*0.05)+SUMPRODUCT((Projects!$G$7:$G$14="Yes")*(82>=Projects!$C$7:$C$14)*(82<Projects!$C$7:$C$14+Projects!$D$7:$D$14)*Projects!$B$7:$B$14*Assumptions!$B$12/Projects!$D$7:$D$14*0.95)+SUMPRODUCT((Projects!$G$7:$G$14="Yes")*(82=Projects!$C$7:$C$14+Projects!$D$7:$D$14-1)*Projects!$B$7:$B$14*Assumptions!$B$12*0.05)+SUMPRODUCT((Projects!$G$17:$G$46="Yes")*(82>=Projects!$C$17:$C$46)*(82<Projects!$C$17:$C$46+Projects!$D$17:$D$46)*Projects!$B$17:$B$46*Assumptions!$B$12/Projects!$D$17:$D$46*0.95)+SUMPRODUCT((Projects!$G$17:$G$46="Yes")*(82=Projects!$C$17:$C$46+Projects!$D$17:$D$46-1)*Projects!$B$17:$B$46*Assumptions!$B$12*0.05),Actuals!CI8) -> 0 | CI10: =IF(ISBLANK(Actuals!CJ8),0+SUMPRODUCT((Projects!$G$7:$G$14="Yes")*(83>=Projects!$C$7:$C$14)*(83<Projects!$C$7:$C$14+Projects!$D$7:$D$14)*Projects!$B$7:$B$14*Assumptions!$B$10/Projects!$D$7:$D$14*0.95)+SUMPRODUCT((Projects!$G$7:$G$14="Yes")*(83=Projects!$C$7:$C$14+Projects!$D$7:$D$14-1)*Projects!$B$7:$B$14*Assumptions!$B$10*0.05)+SUMPRODUCT((Projects!$G$17:$G$46="Yes")*(83>=Projects!$C$17:$C$46)*(83<Projects!$C$17:$C$46+Projects!$D$17:$D$46)*Projects!$B$17:$B$46*Assumptions!$B$10/Projects!$D$17:$D$46*0.95)+SUMPRODUCT((Projects!$G$17:$G$46="Yes")*(83=Projects!$C$17:$C$46+Projects!$D$17:$D$46-1)*Projects!$B$17:$B$46*Assumptions!$B$10*0.05)+SUMPRODUCT((Projects!$G$7:$G$14="Yes")*(83>=Projects!$C$7:$C$14)*(83<Projects!$C$7:$C$14+Projects!$D$7:$D$14)*Projects!$B$7:$B$14*Assumptions!$B$12/Projects!$D$7:$D$14*0.95)+SUMPRODUCT((Projects!$G$7:$G$14="Yes")*(83=Projects!$C$7:$C$14+Projects!$D$7:$D$14-1)*Projects!$B$7:$B$14*Assumptions!$B$12*0.05)+SUMPRODUCT((Projects!$G$17:$G$46="Yes")*(83>=Projects!$C$17:$C$46)*(83<Projects!$C$17:$C$46+Projects!$D$17:$D$46)*Projects!$B$17:$B$46*Assumptions!$B$12/Projects!$D$17:$D$46*0.95)+SUMPRODUCT((Projects!$G$17:$G$46="Yes")*(83=Projects!$C$17:$C$46+Projects!$D$17:$D$46-1)*Projects!$B$17:$B$46*Assumptions!$B$12*0.05),Actuals!CJ8) -> 0 | CJ10: =IF(ISBLANK(Actuals!CK8),0+SUMPRODUCT((Projects!$G$7:$G$14="Yes")*(84>=Projects!$C$7:$C$14)*(84<Projects!$C$7:$C$14+Projects!$D$7:$D$14)*Projects!$B$7:$B$14*Assumptions!$B$10/Projects!$D$7:$D$14*0.95)+SUMPRODUCT((Projects!$G$7:$G$14="Yes")*(84=Projects!$C$7:$C$14+Projects!$D$7:$D$14-1)*Projects!$B$7:$B$14*Assumptions!$B$10*0.05)+SUMPRODUCT((Projects!$G$17:$G$46="Yes")*(84>=Projects!$C$17:$C$46)*(84<Projects!$C$17:$C$46+Projects!$D$17:$D$46)*Projects!$B$17:$B$46*Assumptions!$B$10/Projects!$D$17:$D$46*0.95)+SUMPRODUCT((Projects!$G$17:$G$46="Yes")*(84=Projects!$C$17:$C$46+Projects!$D$17:$D$46-1)*Projects!$B$17:$B$46*Assumptions!$B$10*0.05)+SUMPRODUCT((Projects!$G$7:$G$14="Yes")*(84>=Projects!$C$7:$C$14)*(84<Projects!$C$7:$C$14+Projects!$D$7:$D$14)*Projects!$B$7:$B$14*Assumptions!$B$12/Projects!$D$7:$D$14*0.95)+SUMPRODUCT((Projects!$G$7:$G$14="Yes")*(84=Projects!$C$7:$C$14+Projects!$D$7:$D$14-1)*Projects!$B$7:$B$14*Assumptions!$B$12*0.05)+SUMPRODUCT((Projects!$G$17:$G$46="Yes")*(84>=Projects!$C$17:$C$46)*(84<Projects!$C$17:$C$46+Projects!$D$17:$D$46)*Projects!$B$17:$B$46*Assumptions!$B$12/Projects!$D$17:$D$46*0.95)+SUMPRODUCT((Projects!$G$17:$G$46="Yes")*(84=Projects!$C$17:$C$46+Projects!$D$17:$D$46-1)*Projects!$B$17:$B$46*Assumptions!$B$12*0.05),Actuals!CK8) -> 0 | CK10: =IF(ISBLANK(Actuals!CL8),0+SUMPRODUCT((Projects!$G$7:$G$14="Yes")*(85>=Projects!$C$7:$C$14)*(85<Projects!$C$7:$C$14+Projects!$D$7:$D$14)*Projects!$B$7:$B$14*Assumptions!$B$10/Projects!$D$7:$D$14*0.95)+SUMPRODUCT((Projects!$G$7:$G$14="Yes")*(85=Projects!$C$7:$C$14+Projects!$D$7:$D$14-1)*Projects!$B$7:$B$14*Assumptions!$B$10*0.05)+SUMPRODUCT((Projects!$G$17:$G$46="Yes")*(85>=Projects!$C$17:$C$46)*(85<Projects!$C$17:$C$46+Projects!$D$17:$D$46)*Projects!$B$17:$B$46*Assumptions!$B$10/Projects!$D$17:$D$46*0.95)+SUMPRODUCT((Projects!$G$17:$G$46="Yes")*(85=Projects!$C$17:$C$46+Projects!$D$17:$D$46-1)*Projects!$B$17:$B$46*Assumptions!$B$10*0.05)+SUMPRODUCT((Projects!$G$7:$G$14="Yes")*(85>=Projects!$C$7:$C$14)*(85<Projects!$C$7:$C$14+Projects!$D$7:$D$14)*Projects!$B$7:$B$14*Assumptions!$B$12/Projects!$D$7:$D$14*0.95)+SUMPRODUCT((Projects!$G$7:$G$14="Yes")*(85=Projects!$C$7:$C$14+Projects!$D$7:$D$14-1)*Projects!$B$7:$B$14*Assumptions!$B$12*0.05)+SUMPRODUCT((Projects!$G$17:$G$46="Yes")*(85>=Projects!$C$17:$C$46)*(85<Projects!$C$17:$C$46+Projects!$D$17:$D$46)*Projects!$B$17:$B$46*Assumptions!$B$12/Projects!$D$17:$D$46*0.95)+SUMPRODUCT((Projects!$G$17:$G$46="Yes")*(85=Projects!$C$17:$C$46+Projects!$D$17:$D$46-1)*Projects!$B$17:$B$46*Assumptions!$B$12*0.05),Actuals!CL8) -> 0 | CL10: =IF(ISBLANK(Actuals!CM8),0+SUMPRODUCT((Projects!$G$7:$G$14="Yes")*(86>=Projects!$C$7:$C$14)*(86<Projects!$C$7:$C$14+Projects!$D$7:$D$14)*Projects!$B$7:$B$14*Assumptions!$B$10/Projects!$D$7:$D$14*0.95)+SUMPRODUCT((Projects!$G$7:$G$14="Yes")*(86=Projects!$C$7:$C$14+Projects!$D$7:$D$14-1)*Projects!$B$7:$B$14*Assumptions!$B$10*0.05)+SUMPRODUCT((Projects!$G$17:$G$46="Yes")*(86>=Projects!$C$17:$C$46)*(86<Projects!$C$17:$C$46+Projects!$D$17:$D$46)*Projects!$B$17:$B$46*Assumptions!$B$10/Projects!$D$17:$D$46*0.95)+SUMPRODUCT((Projects!$G$17:$G$46="Yes")*(86=Projects!$C$17:$C$46+Projects!$D$17:$D$46-1)*Projects!$B$17:$B$46*Assumptions!$B$10*0.05)+SUMPRODUCT((Projects!$G$7:$G$14="Yes")*(86>=Projects!$C$7:$C$14)*(86<Projects!$C$7:$C$14+Projects!$D$7:$D$14)*Projects!$B$7:$B$14*Assumptions!$B$12/Projects!$D$7:$D$14*0.95)+SUMPRODUCT((Projects!$G$7:$G$14="Yes")*(86=Projects!$C$7:$C$14+Projects!$D$7:$D$14-1)*Projects!$B$7:$B$14*Assumptions!$B$12*0.05)+SUMPRODUCT((Projects!$G$17:$G$46="Yes")*(86>=Projects!$C$17:$C$46)*(86<Projects!$C$17:$C$46+Projects!$D$17:$D$46)*Projects!$B$17:$B$46*Assumptions!$B$12/Projects!$D$17:$D$46*0.95)+SUMPRODUCT((Projects!$G$17:$G$46="Yes")*(86=Projects!$C$17:$C$46+Projects!$D$17:$D$46-1)*Projects!$B$17:$B$46*Assumptions!$B$12*0.05),Actuals!CM8) -> 0 | CM10: =IF(ISBLANK(Actuals!CN8),0+SUMPRODUCT((Projects!$G$7:$G$14="Yes")*(87>=Projects!$C$7:$C$14)*(87<Projects!$C$7:$C$14+Projects!$D$7:$D$14)*Projects!$B$7:$B$14*Assumptions!$B$10/Projects!$D$7:$D$14*0.95)+SUMPRODUCT((Projects!$G$7:$G$14="Yes")*(87=Projects!$C$7:$C$14+Projects!$D$7:$D$14-1)*Projects!$B$7:$B$14*Assumptions!$B$10*0.05)+SUMPRODUCT((Projects!$G$17:$G$46="Yes")*(87>=Projects!$C$17:$C$46)*(87<Projects!$C$17:$C$46+Projects!$D$17:$D$46)*Projects!$B$17:$B$46*Assumptions!$B$10/Projects!$D$17:$D$46*0.95)+SUMPRODUCT((Projects!$G$17:$G$46="Yes")*(87=Projects!$C$17:$C$46+Projects!$D$17:$D$46-1)*Projects!$B$17:$B$46*Assumptions!$B$10*0.05)+SUMPRODUCT((Projects!$G$7:$G$14="Yes")*(87>=Projects!$C$7:$C$14)*(87<Projects!$C$7:$C$14+Projects!$D$7:$D$14)*Projects!$B$7:$B$14*Assumptions!$B$12/Projects!$D$7:$D$14*0.95)+SUMPRODUCT((Projects!$G$7:$G$14="Yes")*(87=Projects!$C$7:$C$14+Projects!$D$7:$D$14-1)*Projects!$B$7:$B$14*Assumptions!$B$12*0.05)+SUMPRODUCT((Projects!$G$17:$G$46="Yes")*(87>=Projects!$C$17:$C$46)*(87<Projects!$C$17:$C$46+Projects!$D$17:$D$46)*Projects!$B$17:$B$46*Assumptions!$B$12/Projects!$D$17:$D$46*0.95)+SUMPRODUCT((Projects!$G$17:$G$46="Yes")*(87=Projects!$C$17:$C$46+Projects!$D$17:$D$46-1)*Projects!$B$17:$B$46*Assumptions!$B$12*0.05),Actuals!CN8) -> 0 | CN10: =IF(ISBLANK(Actuals!CO8),0+SUMPRODUCT((Projects!$G$7:$G$14="Yes")*(88>=Projects!$C$7:$C$14)*(88<Projects!$C$7:$C$14+Projects!$D$7:$D$14)*Projects!$B$7:$B$14*Assumptions!$B$10/Projects!$D$7:$D$14*0.95)+SUMPRODUCT((Projects!$G$7:$G$14="Yes")*(88=Projects!$C$7:$C$14+Projects!$D$7:$D$14-1)*Projects!$B$7:$B$14*Assumptions!$B$10*0.05)+SUMPRODUCT((Projects!$G$17:$G$46="Yes")*(88>=Projects!$C$17:$C$46)*(88<Projects!$C$17:$C$46+Projects!$D$17:$D$46)*Projects!$B$17:$B$46*Assumptions!$B$10/Projects!$D$17:$D$46*0.95)+SUMPRODUCT((Projects!$G$17:$G$46="Yes")*(88=Projects!$C$17:$C$46+Projects!$D$17:$D$46-1)*Projects!$B$17:$B$46*Assumptions!$B$10*0.05)+SUMPRODUCT((Projects!$G$7:$G$14="Yes")*(88>=Projects!$C$7:$C$14)*(88<Projects!$C$7:$C$14+Projects!$D$7:$D$14)*Projects!$B$7:$B$14*Assumptions!$B$12/Projects!$D$7:$D$14*0.95)+SUMPRODUCT((Projects!$G$7:$G$14="Yes")*(88=Projects!$C$7:$C$14+Projects!$D$7:$D$14-1)*Projects!$B$7:$B$14*Assumptions!$B$12*0.05)+SUMPRODUCT((Projects!$G$17:$G$46="Yes")*(88>=Projects!$C$17:$C$46)*(88<Projects!$C$17:$C$46+Projects!$D$17:$D$46)*Projects!$B$17:$B$46*Assumptions!$B$12/Projects!$D$17:$D$46*0.95)+SUMPRODUCT((Projects!$G$17:$G$46="Yes")*(88=Projects!$C$17:$C$46+Projects!$D$17:$D$46-1)*Projects!$B$17:$B$46*Assumptions!$B$12*0.05),Actuals!CO8) -> 0 | CO10: =IF(ISBLANK(Actuals!CP8),0+SUMPRODUCT((Projects!$G$7:$G$14="Yes")*(89>=Projects!$C$7:$C$14)*(89<Projects!$C$7:$C$14+Projects!$D$7:$D$14)*Projects!$B$7:$B$14*Assumptions!$B$10/Projects!$D$7:$D$14*0.95)+SUMPRODUCT((Projects!$G$7:$G$14="Yes")*(89=Projects!$C$7:$C$14+Projects!$D$7:$D$14-1)*Projects!$B$7:$B$14*Assumptions!$B$10*0.05)+SUMPRODUCT((Projects!$G$17:$G$46="Yes")*(89>=Projects!$C$17:$C$46)*(89<Projects!$C$17:$C$46+Projects!$D$17:$D$46)*Projects!$B$17:$B$46*Assumptions!$B$10/Projects!$D$17:$D$46*0.95)+SUMPRODUCT((Projects!$G$17:$G$46="Yes")*(89=Projects!$C$17:$C$46+Projects!$D$17:$D$46-1)*Projects!$B$17:$B$46*Assumptions!$B$10*0.05)+SUMPRODUCT((Projects!$G$7:$G$14="Yes")*(89>=Projects!$C$7:$C$14)*(89<Projects!$C$7:$C$14+Projects!$D$7:$D$14)*Projects!$B$7:$B$14*Assumptions!$B$12/Projects!$D$7:$D$14*0.95)+SUMPRODUCT((Projects!$G$7:$G$14="Yes")*(89=Projects!$C$7:$C$14+Projects!$D$7:$D$14-1)*Projects!$B$7:$B$14*Assumptions!$B$12*0.05)+SUMPRODUCT((Projects!$G$17:$G$46="Yes")*(89>=Projects!$C$17:$C$46)*(89<Projects!$C$17:$C$46+Projects!$D$17:$D$46)*Projects!$B$17:$B$46*Assumptions!$B$12/Projects!$D$17:$D$46*0.95)+SUMPRODUCT((Projects!$G$17:$G$46="Yes")*(89=Projects!$C$17:$C$46+Projects!$D$17:$D$46-1)*Projects!$B$17:$B$46*Assumptions!$B$12*0.05),Actuals!CP8) -> 0 | CP10: =IF(ISBLANK(Actuals!CQ8),0+SUMPRODUCT((Projects!$G$7:$G$14="Yes")*(90>=Projects!$C$7:$C$14)*(90<Projects!$C$7:$C$14+Projects!$D$7:$D$14)*Projects!$B$7:$B$14*Assumptions!$B$10/Projects!$D$7:$D$14*0.95)+SUMPRODUCT((Projects!$G$7:$G$14="Yes")*(90=Projects!$C$7:$C$14+Projects!$D$7:$D$14-1)*Projects!$B$7:$B$14*Assumptions!$B$10*0.05)+SUMPRODUCT((Projects!$G$17:$G$46="Yes")*(90>=Projects!$C$17:$C$46)*(90<Projects!$C$17:$C$46+Projects!$D$17:$D$46)*Projects!$B$17:$B$46*Assumptions!$B$10/Projects!$D$17:$D$46*0.95)+SUMPRODUCT((Projects!$G$17:$G$46="Yes")*(90=Projects!$C$17:$C$46+Projects!$D$17:$D$46-1)*Projects!$B$17:$B$46*Assumptions!$B$10*0.05)+SUMPRODUCT((Projects!$G$7:$G$14="Yes")*(90>=Projects!$C$7:$C$14)*(90<Projects!$C$7:$C$14+Projects!$D$7:$D$14)*Projects!$B$7:$B$14*Assumptions!$B$12/Projects!$D$7:$D$14*0.95)+SUMPRODUCT((Projects!$G$7:$G$14="Yes")*(90=Projects!$C$7:$C$14+Projects!$D$7:$D$14-1)*Projects!$B$7:$B$14*Assumptions!$B$12*0.05)+SUMPRODUCT((Projects!$G$17:$G$46="Yes")*(90>=Projects!$C$17:$C$46)*(90<Projects!$C$17:$C$46+Projects!$D$17:$D$46)*Projects!$B$17:$B$46*Assumptions!$B$12/Projects!$D$17:$D$46*0.95)+SUMPRODUCT((Projects!$G$17:$G$46="Yes")*(90=Projects!$C$17:$C$46+Projects!$D$17:$D$46-1)*Projects!$B$17:$B$46*Assumptions!$B$12*0.05),Actuals!CQ8) -> 0 | CQ10: =IF(ISBLANK(Actuals!CR8),0+SUMPRODUCT((Projects!$G$7:$G$14="Yes")*(91>=Projects!$C$7:$C$14)*(91<Projects!$C$7:$C$14+Projects!$D$7:$D$14)*Projects!$B$7:$B$14*Assumptions!$B$10/Projects!$D$7:$D$14*0.95)+SUMPRODUCT((Projects!$G$7:$G$14="Yes")*(91=Projects!$C$7:$C$14+Projects!$D$7:$D$14-1)*Projects!$B$7:$B$14*Assumptions!$B$10*0.05)+SUMPRODUCT((Projects!$G$17:$G$46="Yes")*(91>=Projects!$C$17:$C$46)*(91<Projects!$C$17:$C$46+Projects!$D$17:$D$46)*Projects!$B$17:$B$46*Assumptions!$B$10/Projects!$D$17:$D$46*0.95)+SUMPRODUCT((Projects!$G$17:$G$46="Yes")*(91=Projects!$C$17:$C$46+Projects!$D$17:$D$46-1)*Projects!$B$17:$B$46*Assumptions!$B$10*0.05)+SUMPRODUCT((Projects!$G$7:$G$14="Yes")*(91>=Projects!$C$7:$C$14)*(91<Projects!$C$7:$C$14+Projects!$D$7:$D$14)*Projects!$B$7:$B$14*Assumptions!$B$12/Projects!$D$7:$D$14*0.95)+SUMPRODUCT((Projects!$G$7:$G$14="Yes")*(91=Projects!$C$7:$C$14+Projects!$D$7:$D$14-1)*Projects!$B$7:$B$14*Assumptions!$B$12*0.05)+SUMPRODUCT((Projects!$G$17:$G$46="Yes")*(91>=Projects!$C$17:$C$46)*(91<Projects!$C$17:$C$46+Projects!$D$17:$D$46)*Projects!$B$17:$B$46*Assumptions!$B$12/Projects!$D$17:$D$46*0.95)+SUMPRODUCT((Projects!$G$17:$G$46="Yes")*(91=Projects!$C$17:$C$46+Projects!$D$17:$D$46-1)*Projects!$B$17:$B$46*Assumptions!$B$12*0.05),Actuals!CR8) -> 0 | CR10: =IF(ISBLANK(Actuals!CS8),0+SUMPRODUCT((Projects!$G$7:$G$14="Yes")*(92>=Projects!$C$7:$C$14)*(92<Projects!$C$7:$C$14+Projects!$D$7:$D$14)*Projects!$B$7:$B$14*Assumptions!$B$10/Projects!$D$7:$D$14*0.95)+SUMPRODUCT((Projects!$G$7:$G$14="Yes")*(92=Projects!$C$7:$C$14+Projects!$D$7:$D$14-1)*Projects!$B$7:$B$14*Assumptions!$B$10*0.05)+SUMPRODUCT((Projects!$G$17:$G$46="Yes")*(92>=Projects!$C$17:$C$46)*(92<Projects!$C$17:$C$46+Projects!$D$17:$D$46)*Projects!$B$17:$B$46*Assumptions!$B$10/Projects!$D$17:$D$46*0.95)+SUMPRODUCT((Projects!$G$17:$G$46="Yes")*(92=Projects!$C$17:$C$46+Projects!$D$17:$D$46-1)*Projects!$B$17:$B$46*Assumptions!$B$10*0.05)+SUMPRODUCT((Projects!$G$7:$G$14="Yes")*(92>=Projects!$C$7:$C$14)*(92<Projects!$C$7:$C$14+Projects!$D$7:$D$14)*Projects!$B$7:$B$14*Assumptions!$B$12/Projects!$D$7:$D$14*0.95)+SUMPRODUCT((Projects!$G$7:$G$14="Yes")*(92=Projects!$C$7:$C$14+Projects!$D$7:$D$14-1)*Projects!$B$7:$B$14*Assumptions!$B$12*0.05)+SUMPRODUCT((Projects!$G$17:$G$46="Yes")*(92>=Projects!$C$17:$C$46)*(92<Projects!$C$17:$C$46+Projects!$D$17:$D$46)*Projects!$B$17:$B$46*Assumptions!$B$12/Projects!$D$17:$D$46*0.95)+SUMPRODUCT((Projects!$G$17:$G$46="Yes")*(92=Projects!$C$17:$C$46+Projects!$D$17:$D$46-1)*Projects!$B$17:$B$46*Assumptions!$B$12*0.05),Actuals!CS8) -> 0 | CS10: =IF(ISBLANK(Actuals!CT8),0+SUMPRODUCT((Projects!$G$7:$G$14="Yes")*(93>=Projects!$C$7:$C$14)*(93<Projects!$C$7:$C$14+Projects!$D$7:$D$14)*Projects!$B$7:$B$14*Assumptions!$B$10/Projects!$D$7:$D$14*0.95)+SUMPRODUCT((Projects!$G$7:$G$14="Yes")*(93=Projects!$C$7:$C$14+Projects!$D$7:$D$14-1)*Projects!$B$7:$B$14*Assumptions!$B$10*0.05)+SUMPRODUCT((Projects!$G$17:$G$46="Yes")*(93>=Projects!$C$17:$C$46)*(93<Projects!$C$17:$C$46+Projects!$D$17:$D$46)*Projects!$B$17:$B$46*Assumptions!$B$10/Projects!$D$17:$D$46*0.95)+SUMPRODUCT((Projects!$G$17:$G$46="Yes")*(93=Projects!$C$17:$C$46+Projects!$D$17:$D$46-1)*Projects!$B$17:$B$46*Assumptions!$B$10*0.05)+SUMPRODUCT((Projects!$G$7:$G$14="Yes")*(93>=Projects!$C$7:$C$14)*(93<Projects!$C$7:$C$14+Projects!$D$7:$D$14)*Projects!$B$7:$B$14*Assumptions!$B$12/Projects!$D$7:$D$14*0.95)+SUMPRODUCT((Projects!$G$7:$G$14="Yes")*(93=Projects!$C$7:$C$14+Projects!$D$7:$D$14-1)*Projects!$B$7:$B$14*Assumptions!$B$12*0.05)+SUMPRODUCT((Projects!$G$17:$G$46="Yes")*(93>=Projects!$C$17:$C$46)*(93<Projects!$C$17:$C$46+Projects!$D$17:$D$46)*Projects!$B$17:$B$46*Assumptions!$B$12/Projects!$D$17:$D$46*0.95)+SUMPRODUCT((Projects!$G$17:$G$46="Yes")*(93=Projects!$C$17:$C$46+Projects!$D$17:$D$46-1)*Projects!$B$17:$B$46*Assumptions!$B$12*0.05),Actuals!CT8) -> 0 | CT10: =IF(ISBLANK(Actuals!CU8),0+SUMPRODUCT((Projects!$G$7:$G$14="Yes")*(94>=Projects!$C$7:$C$14)*(94<Projects!$C$7:$C$14+Projects!$D$7:$D$14)*Projects!$B$7:$B$14*Assumptions!$B$10/Projects!$D$7:$D$14*0.95)+SUMPRODUCT((Projects!$G$7:$G$14="Yes")*(94=Projects!$C$7:$C$14+Projects!$D$7:$D$14-1)*Projects!$B$7:$B$14*Assumptions!$B$10*0.05)+SUMPRODUCT((Projects!$G$17:$G$46="Yes")*(94>=Projects!$C$17:$C$46)*(94<Projects!$C$17:$C$46+Projects!$D$17:$D$46)*Projects!$B$17:$B$46*Assumptions!$B$10/Projects!$D$17:$D$46*0.95)+SUMPRODUCT((Projects!$G$17:$G$46="Yes")*(94=Projects!$C$17:$C$46+Projects!$D$17:$D$46-1)*Projects!$B$17:$B$46*Assumptions!$B$10*0.05)+SUMPRODUCT((Projects!$G$7:$G$14="Yes")*(94>=Projects!$C$7:$C$14)*(94<Projects!$C$7:$C$14+Projects!$D$7:$D$14)*Projects!$B$7:$B$14*Assumptions!$B$12/Projects!$D$7:$D$14*0.95)+SUMPRODUCT((Projects!$G$7:$G$14="Yes")*(94=Projects!$C$7:$C$14+Projects!$D$7:$D$14-1)*Projects!$B$7:$B$14*Assumptions!$B$12*0.05)+SUMPRODUCT((Projects!$G$17:$G$46="Yes")*(94>=Projects!$C$17:$C$46)*(94<Projects!$C$17:$C$46+Projects!$D$17:$D$46)*Projects!$B$17:$B$46*Assumptions!$B$12/Projects!$D$17:$D$46*0.95)+SUMPRODUCT((Projects!$G$17:$G$46="Yes")*(94=Projects!$C$17:$C$46+Projects!$D$17:$D$46-1)*Projects!$B$17:$B$46*Assumptions!$B$12*0.05),Actuals!CU8) -> 0 | CU10: =IF(ISBLANK(Actuals!CV8),0+SUMPRODUCT((Projects!$G$7:$G$14="Yes")*(95>=Projects!$C$7:$C$14)*(95<Projects!$C$7:$C$14+Projects!$D$7:$D$14)*Projects!$B$7:$B$14*Assumptions!$B$10/Projects!$D$7:$D$14*0.95)+SUMPRODUCT((Projects!$G$7:$G$14="Yes")*(95=Projects!$C$7:$C$14+Projects!$D$7:$D$14-1)*Projects!$B$7:$B$14*Assumptions!$B$10*0.05)+SUMPRODUCT((Projects!$G$17:$G$46="Yes")*(95>=Projects!$C$17:$C$46)*(95<Projects!$C$17:$C$46+Projects!$D$17:$D$46)*Projects!$B$17:$B$46*Assumptions!$B$10/Projects!$D$17:$D$46*0.95)+SUMPRODUCT((Projects!$G$17:$G$46="Yes")*(95=Projects!$C$17:$C$46+Projects!$D$17:$D$46-1)*Projects!$B$17:$B$46*Assumptions!$B$10*0.05)+SUMPRODUCT((Projects!$G$7:$G$14="Yes")*(95>=Projects!$C$7:$C$14)*(95<Projects!$C$7:$C$14+Projects!$D$7:$D$14)*Projects!$B$7:$B$14*Assumptions!$B$12/Projects!$D$7:$D$14*0.95)+SUMPRODUCT((Projects!$G$7:$G$14="Yes")*(95=Projects!$C$7:$C$14+Projects!$D$7:$D$14-1)*Projects!$B$7:$B$14*Assumptions!$B$12*0.05)+SUMPRODUCT((Projects!$G$17:$G$46="Yes")*(95>=Projects!$C$17:$C$46)*(95<Projects!$C$17:$C$46+Projects!$D$17:$D$46)*Projects!$B$17:$B$46*Assumptions!$B$12/Projects!$D$17:$D$46*0.95)+SUMPRODUCT((Projects!$G$17:$G$46="Yes")*(95=Projects!$C$17:$C$46+Projects!$D$17:$D$46-1)*Projects!$B$17:$B$46*Assumptions!$B$12*0.05),Actuals!CV8) -> 0 | CV10: =IF(ISBLANK(Actuals!CW8),0+SUMPRODUCT((Projects!$G$7:$G$14="Yes")*(96>=Projects!$C$7:$C$14)*(96<Projects!$C$7:$C$14+Projects!$D$7:$D$14)*Projects!$B$7:$B$14*Assumptions!$B$10/Projects!$D$7:$D$14*0.95)+SUMPRODUCT((Projects!$G$7:$G$14="Yes")*(96=Projects!$C$7:$C$14+Projects!$D$7:$D$14-1)*Projects!$B$7:$B$14*Assumptions!$B$10*0.05)+SUMPRODUCT((Projects!$G$17:$G$46="Yes")*(96>=Projects!$C$17:$C$46)*(96<Projects!$C$17:$C$46+Projects!$D$17:$D$46)*Projects!$B$17:$B$46*Assumptions!$B$10/Projects!$D$17:$D$46*0.95)+SUMPRODUCT((Projects!$G$17:$G$46="Yes")*(96=Projects!$C$17:$C$46+Projects!$D$17:$D$46-1)*Projects!$B$17:$B$46*Assumptions!$B$10*0.05)+SUMPRODUCT((Projects!$G$7:$G$14="Yes")*(96>=Projects!$C$7:$C$14)*(96<Projects!$C$7:$C$14+Projects!$D$7:$D$14)*Projects!$B$7:$B$14*Assumptions!$B$12/Projects!$D$7:$D$14*0.95)+SUMPRODUCT((Projects!$G$7:$G$14="Yes")*(96=Projects!$C$7:$C$14+Projects!$D$7:$D$14-1)*Projects!$B$7:$B$14*Assumptions!$B$12*0.05)+SUMPRODUCT((Projects!$G$17:$G$46="Yes")*(96>=Projects!$C$17:$C$46)*(96<Projects!$C$17:$C$46+Projects!$D$17:$D$46)*Projects!$B$17:$B$46*Assumptions!$B$12/Projects!$D$17:$D$46*0.95)+SUMPRODUCT((Projects!$G$17:$G$46="Yes")*(96=Projects!$C$17:$C$46+Projects!$D$17:$D$46-1)*Projects!$B$17:$B$46*Assumptions!$B$12*0.05),Actuals!CW8) -> 0 | CW10: =IF(ISBLANK(Actuals!CX8),0+SUMPRODUCT((Projects!$G$7:$G$14="Yes")*(97>=Projects!$C$7:$C$14)*(97<Projects!$C$7:$C$14+Projects!$D$7:$D$14)*Projects!$B$7:$B$14*Assumptions!$B$10/Projects!$D$7:$D$14*0.95)+SUMPRODUCT((Projects!$G$7:$G$14="Yes")*(97=Projects!$C$7:$C$14+Projects!$D$7:$D$14-1)*Projects!$B$7:$B$14*Assumptions!$B$10*0.05)+SUMPRODUCT((Projects!$G$17:$G$46="Yes")*(97>=Projects!$C$17:$C$46)*(97<Projects!$C$17:$C$46+Projects!$D$17:$D$46)*Projects!$B$17:$B$46*Assumptions!$B$10/Projects!$D$17:$D$46*0.95)+SUMPRODUCT((Projects!$G$17:$G$46="Yes")*(97=Projects!$C$17:$C$46+Projects!$D$17:$D$46-1)*Projects!$B$17:$B$46*Assumptions!$B$10*0.05)+SUMPRODUCT((Projects!$G$7:$G$14="Yes")*(97>=Projects!$C$7:$C$14)*(97<Projects!$C$7:$C$14+Projects!$D$7:$D$14)*Projects!$B$7:$B$14*Assumptions!$B$12/Projects!$D$7:$D$14*0.95)+SUMPRODUCT((Projects!$G$7:$G$14="Yes")*(97=Projects!$C$7:$C$14+Projects!$D$7:$D$14-1)*Projects!$B$7:$B$14*Assumptions!$B$12*0.05)+SUMPRODUCT((Projects!$G$17:$G$46="Yes")*(97>=Projects!$C$17:$C$46)*(97<Projects!$C$17:$C$46+Projects!$D$17:$D$46)*Projects!$B$17:$B$46*Assumptions!$B$12/Projects!$D$17:$D$46*0.95)+SUMPRODUCT((Projects!$G$17:$G$46="Yes")*(97=Projects!$C$17:$C$46+Projects!$D$17:$D$46-1)*Projects!$B$17:$B$46*Assumptions!$B$12*0.05),Actuals!CX8) -> 0 | CX10: =IF(ISBLANK(Actuals!CY8),0+SUMPRODUCT((Projects!$G$7:$G$14="Yes")*(98>=Projects!$C$7:$C$14)*(98<Projects!$C$7:$C$14+Projects!$D$7:$D$14)*Projects!$B$7:$B$14*Assumptions!$B$10/Projects!$D$7:$D$14*0.95)+SUMPRODUCT((Projects!$G$7:$G$14="Yes")*(98=Projects!$C$7:$C$14+Projects!$D$7:$D$14-1)*Projects!$B$7:$B$14*Assumptions!$B$10*0.05)+SUMPRODUCT((Projects!$G$17:$G$46="Yes")*(98>=Projects!$C$17:$C$46)*(98<Projects!$C$17:$C$46+Projects!$D$17:$D$46)*Projects!$B$17:$B$46*Assumptions!$B$10/Projects!$D$17:$D$46*0.95)+SUMPRODUCT((Projects!$G$17:$G$46="Yes")*(98=Projects!$C$17:$C$46+Projects!$D$17:$D$46-1)*Projects!$B$17:$B$46*Assumptions!$B$10*0.05)+SUMPRODUCT((Projects!$G$7:$G$14="Yes")*(98>=Projects!$C$7:$C$14)*(98<Projects!$C$7:$C$14+Projects!$D$7:$D$14)*Projects!$B$7:$B$14*Assumptions!$B$12/Projects!$D$7:$D$14*0.95)+SUMPRODUCT((Projects!$G$7:$G$14="Yes")*(98=Projects!$C$7:$C$14+Projects!$D$7:$D$14-1)*Projects!$B$7:$B$14*Assumptions!$B$12*0.05)+SUMPRODUCT((Projects!$G$17:$G$46="Yes")*(98>=Projects!$C$17:$C$46)*(98<Projects!$C$17:$C$46+Projects!$D$17:$D$46)*Projects!$B$17:$B$46*Assumptions!$B$12/Projects!$D$17:$D$46*0.95)+SUMPRODUCT((Projects!$G$17:$G$46="Yes")*(98=Projects!$C$17:$C$46+Projects!$D$17:$D$46-1)*Projects!$B$17:$B$46*Assumptions!$B$12*0.05),Actuals!CY8) -> 0 | CY10: =IF(ISBLANK(Actuals!CZ8),0+SUMPRODUCT((Projects!$G$7:$G$14="Yes")*(99>=Projects!$C$7:$C$14)*(99<Projects!$C$7:$C$14+Projects!$D$7:$D$14)*Projects!$B$7:$B$14*Assumptions!$B$10/Projects!$D$7:$D$14*0.95)+SUMPRODUCT((Projects!$G$7:$G$14="Yes")*(99=Projects!$C$7:$C$14+Projects!$D$7:$D$14-1)*Projects!$B$7:$B$14*Assumptions!$B$10*0.05)+SUMPRODUCT((Projects!$G$17:$G$46="Yes")*(99>=Projects!$C$17:$C$46)*(99<Projects!$C$17:$C$46+Projects!$D$17:$D$46)*Projects!$B$17:$B$46*Assumptions!$B$10/Projects!$D$17:$D$46*0.95)+SUMPRODUCT((Projects!$G$17:$G$46="Yes")*(99=Projects!$C$17:$C$46+Projects!$D$17:$D$46-1)*Projects!$B$17:$B$46*Assumptions!$B$10*0.05)+SUMPRODUCT((Projects!$G$7:$G$14="Yes")*(99>=Projects!$C$7:$C$14)*(99<Projects!$C$7:$C$14+Projects!$D$7:$D$14)*Projects!$B$7:$B$14*Assumptions!$B$12/Projects!$D$7:$D$14*0.95)+SUMPRODUCT((Projects!$G$7:$G$14="Yes")*(99=Projects!$C$7:$C$14+Projects!$D$7:$D$14-1)*Projects!$B$7:$B$14*Assumptions!$B$12*0.05)+SUMPRODUCT((Projects!$G$17:$G$46="Yes")*(99>=Projects!$C$17:$C$46)*(99<Projects!$C$17:$C$46+Projects!$D$17:$D$46)*Projects!$B$17:$B$46*Assumptions!$B$12/Projects!$D$17:$D$46*0.95)+SUMPRODUCT((Projects!$G$17:$G$46="Yes")*(99=Projects!$C$17:$C$46+Projects!$D$17:$D$46-1)*Projects!$B$17:$B$46*Assumptions!$B$12*0.05),Actuals!CZ8) -> 0 | CZ10: =IF(ISBLANK(Actuals!DA8),0+SUMPRODUCT((Projects!$G$7:$G$14="Yes")*(100>=Projects!$C$7:$C$14)*(100<Projects!$C$7:$C$14+Projects!$D$7:$D$14)*Projects!$B$7:$B$14*Assumptions!$B$10/Projects!$D$7:$D$14*0.95)+SUMPRODUCT((Projects!$G$7:$G$14="Yes")*(100=Projects!$C$7:$C$14+Projects!$D$7:$D$14-1)*Projects!$B$7:$B$14*Assumptions!$B$10*0.05)+SUMPRODUCT((Projects!$G$17:$G$46="Yes")*(100>=Projects!$C$17:$C$46)*(100<Projects!$C$17:$C$46+Projects!$D$17:$D$46)*Projects!$B$17:$B$46*Assumptions!$B$10/Projects!$D$17:$D$46*0.95)+SUMPRODUCT((Projects!$G$17:$G$46="Yes")*(100=Projects!$C$17:$C$46+Projects!$D$17:$D$46-1)*Projects!$B$17:$B$46*Assumptions!$B$10*0.05)+SUMPRODUCT((Projects!$G$7:$G$14="Yes")*(100>=Projects!$C$7:$C$14)*(100<Projects!$C$7:$C$14+Projects!$D$7:$D$14)*Projects!$B$7:$B$14*Assumptions!$B$12/Projects!$D$7:$D$14*0.95)+SUMPRODUCT((Projects!$G$7:$G$14="Yes")*(100=Projects!$C$7:$C$14+Projects!$D$7:$D$14-1)*Projects!$B$7:$B$14*Assumptions!$B$12*0.05)+SUMPRODUCT((Projects!$G$17:$G$46="Yes")*(100>=Projects!$C$17:$C$46)*(100<Projects!$C$17:$C$46+Projects!$D$17:$D$46)*Projects!$B$17:$B$46*Assumptions!$B$12/Projects!$D$17:$D$46*0.95)+SUMPRODUCT((Projects!$G$17:$G$46="Yes")*(100=Projects!$C$17:$C$46+Projects!$D$17:$D$46-1)*Projects!$B$17:$B$46*Assumptions!$B$12*0.05),Actuals!DA8) -> 0 | DA10: =IF(ISBLANK(Actuals!DB8),0+SUMPRODUCT((Projects!$G$7:$G$14="Yes")*(101>=Projects!$C$7:$C$14)*(101<Projects!$C$7:$C$14+Projects!$D$7:$D$14)*Projects!$B$7:$B$14*Assumptions!$B$10/Projects!$D$7:$D$14*0.95)+SUMPRODUCT((Projects!$G$7:$G$14="Yes")*(101=Projects!$C$7:$C$14+Projects!$D$7:$D$14-1)*Projects!$B$7:$B$14*Assumptions!$B$10*0.05)+SUMPRODUCT((Projects!$G$17:$G$46="Yes")*(101>=Projects!$C$17:$C$46)*(101<Projects!$C$17:$C$46+Projects!$D$17:$D$46)*Projects!$B$17:$B$46*Assumptions!$B$10/Projects!$D$17:$D$46*0.95)+SUMPRODUCT((Projects!$G$17:$G$46="Yes")*(101=Projects!$C$17:$C$46+Projects!$D$17:$D$46-1)*Projects!$B$17:$B$46*Assumptions!$B$10*0.05)+SUMPRODUCT((Projects!$G$7:$G$14="Yes")*(101>=Projects!$C$7:$C$14)*(101<Projects!$C$7:$C$14+Projects!$D$7:$D$14)*Projects!$B$7:$B$14*Assumptions!$B$12/Projects!$D$7:$D$14*0.95)+SUMPRODUCT((Projects!$G$7:$G$14="Yes")*(101=Projects!$C$7:$C$14+Projects!$D$7:$D$14-1)*Projects!$B$7:$B$14*Assumptions!$B$12*0.05)+SUMPRODUCT((Projects!$G$17:$G$46="Yes")*(101>=Projects!$C$17:$C$46)*(101<Projects!$C$17:$C$46+Projects!$D$17:$D$46)*Projects!$B$17:$B$46*Assumptions!$B$12/Projects!$D$17:$D$46*0.95)+SUMPRODUCT((Projects!$G$17:$G$46="Yes")*(101=Projects!$C$17:$C$46+Projects!$D$17:$D$46-1)*Projects!$B$17:$B$46*Assumptions!$B$12*0.05),Actuals!DB8) -> 0 | DB10: =IF(ISBLANK(Actuals!DC8),0+SUMPRODUCT((Projects!$G$7:$G$14="Yes")*(102>=Projects!$C$7:$C$14)*(102<Projects!$C$7:$C$14+Projects!$D$7:$D$14)*Projects!$B$7:$B$14*Assumptions!$B$10/Projects!$D$7:$D$14*0.95)+SUMPRODUCT((Projects!$G$7:$G$14="Yes")*(102=Projects!$C$7:$C$14+Projects!$D$7:$D$14-1)*Projects!$B$7:$B$14*Assumptions!$B$10*0.05)+SUMPRODUCT((Projects!$G$17:$G$46="Yes")*(102>=Projects!$C$17:$C$46)*(102<Projects!$C$17:$C$46+Projects!$D$17:$D$46)*Projects!$B$17:$B$46*Assumptions!$B$10/Projects!$D$17:$D$46*0.95)+SUMPRODUCT((Projects!$G$17:$G$46="Yes")*(102=Projects!$C$17:$C$46+Projects!$D$17:$D$46-1)*Projects!$B$17:$B$46*Assumptions!$B$10*0.05)+SUMPRODUCT((Projects!$G$7:$G$14="Yes")*(102>=Projects!$C$7:$C$14)*(102<Projects!$C$7:$C$14+Projects!$D$7:$D$14)*Projects!$B$7:$B$14*Assumptions!$B$12/Projects!$D$7:$D$14*0.95)+SUMPRODUCT((Projects!$G$7:$G$14="Yes")*(102=Projects!$C$7:$C$14+Projects!$D$7:$D$14-1)*Projects!$B$7:$B$14*Assumptions!$B$12*0.05)+SUMPRODUCT((Projects!$G$17:$G$46="Yes")*(102>=Projects!$C$17:$C$46)*(102<Projects!$C$17:$C$46+Projects!$D$17:$D$46)*Projects!$B$17:$B$46*Assumptions!$B$12/Projects!$D$17:$D$46*0.95)+SUMPRODUCT((Projects!$G$17:$G$46="Yes")*(102=Projects!$C$17:$C$46+Projects!$D$17:$D$46-1)*Projects!$B$17:$B$46*Assumptions!$B$12*0.05),Actuals!DC8) -> 0 | DC10: =IF(ISBLANK(Actuals!DD8),0+SUMPRODUCT((Projects!$G$7:$G$14="Yes")*(103>=Projects!$C$7:$C$14)*(103<Projects!$C$7:$C$14+Projects!$D$7:$D$14)*Projects!$B$7:$B$14*Assumptions!$B$10/Projects!$D$7:$D$14*0.95)+SUMPRODUCT((Projects!$G$7:$G$14="Yes")*(103=Projects!$C$7:$C$14+Projects!$D$7:$D$14-1)*Projects!$B$7:$B$14*Assumptions!$B$10*0.05)+SUMPRODUCT((Projects!$G$17:$G$46="Yes")*(103>=Projects!$C$17:$C$46)*(103<Projects!$C$17:$C$46+Projects!$D$17:$D$46)*Projects!$B$17:$B$46*Assumptions!$B$10/Projects!$D$17:$D$46*0.95)+SUMPRODUCT((Projects!$G$17:$G$46="Yes")*(103=Projects!$C$17:$C$46+Projects!$D$17:$D$46-1)*Projects!$B$17:$B$46*Assumptions!$B$10*0.05)+SUMPRODUCT((Projects!$G$7:$G$14="Yes")*(103>=Projects!$C$7:$C$14)*(103<Projects!$C$7:$C$14+Projects!$D$7:$D$14)*Projects!$B$7:$B$14*Assumptions!$B$12/Projects!$D$7:$D$14*0.95)+SUMPRODUCT((Projects!$G$7:$G$14="Yes")*(103=Projects!$C$7:$C$14+Projects!$D$7:$D$14-1)*Projects!$B$7:$B$14*Assumptions!$B$12*0.05)+SUMPRODUCT((Projects!$G$17:$G$46="Yes")*(103>=Projects!$C$17:$C$46)*(103<Projects!$C$17:$C$46+Projects!$D$17:$D$46)*Projects!$B$17:$B$46*Assumptions!$B$12/Projects!$D$17:$D$46*0.95)+SUMPRODUCT((Projects!$G$17:$G$46="Yes")*(103=Projects!$C$17:$C$46+Projects!$D$17:$D$46-1)*Projects!$B$17:$B$46*Assumptions!$B$12*0.05),Actuals!DD8) -> 0 | DD10: =IF(ISBLANK(Actuals!DE8),0+SUMPRODUCT((Projects!$G$7:$G$14="Yes")*(104>=Projects!$C$7:$C$14)*(104<Projects!$C$7:$C$14+Projects!$D$7:$D$14)*Projects!$B$7:$B$14*Assumptions!$B$10/Projects!$D$7:$D$14*0.95)+SUMPRODUCT((Projects!$G$7:$G$14="Yes")*(104=Projects!$C$7:$C$14+Projects!$D$7:$D$14-1)*Projects!$B$7:$B$14*Assumptions!$B$10*0.05)+SUMPRODUCT((Projects!$G$17:$G$46="Yes")*(104>=Projects!$C$17:$C$46)*(104<Projects!$C$17:$C$46+Projects!$D$17:$D$46)*Projects!$B$17:$B$46*Assumptions!$B$10/Projects!$D$17:$D$46*0.95)+SUMPRODUCT((Projects!$G$17:$G$46="Yes")*(104=Projects!$C$17:$C$46+Projects!$D$17:$D$46-1)*Projects!$B$17:$B$46*Assumptions!$B$10*0.05)+SUMPRODUCT((Projects!$G$7:$G$14="Yes")*(104>=Projects!$C$7:$C$14)*(104<Projects!$C$7:$C$14+Projects!$D$7:$D$14)*Projects!$B$7:$B$14*Assumptions!$B$12/Projects!$D$7:$D$14*0.95)+SUMPRODUCT((Projects!$G$7:$G$14="Yes")*(104=Projects!$C$7:$C$14+Projects!$D$7:$D$14-1)*Projects!$B$7:$B$14*Assumptions!$B$12*0.05)+SUMPRODUCT((Projects!$G$17:$G$46="Yes")*(104>=Projects!$C$17:$C$46)*(104<Projects!$C$17:$C$46+Projects!$D$17:$D$46)*Projects!$B$17:$B$46*Assumptions!$B$12/Projects!$D$17:$D$46*0.95)+SUMPRODUCT((Projects!$G$17:$G$46="Yes")*(104=Projects!$C$17:$C$46+Projects!$D$17:$D$46-1)*Projects!$B$17:$B$46*Assumptions!$B$12*0.05),Actuals!DE8) -> 0 | DE10: =IF(ISBLANK(Actuals!DF8),0+SUMPRODUCT((Projects!$G$7:$G$14="Yes")*(105>=Projects!$C$7:$C$14)*(105<Projects!$C$7:$C$14+Projects!$D$7:$D$14)*Projects!$B$7:$B$14*Assumptions!$B$10/Projects!$D$7:$D$14*0.95)+SUMPRODUCT((Projects!$G$7:$G$14="Yes")*(105=Projects!$C$7:$C$14+Projects!$D$7:$D$14-1)*Projects!$B$7:$B$14*Assumptions!$B$10*0.05)+SUMPRODUCT((Projects!$G$17:$G$46="Yes")*(105>=Projects!$C$17:$C$46)*(105<Projects!$C$17:$C$46+Projects!$D$17:$D$46)*Projects!$B$17:$B$46*Assumptions!$B$10/Projects!$D$17:$D$46*0.95)+SUMPRODUCT((Projects!$G$17:$G$46="Yes")*(105=Projects!$C$17:$C$46+Projects!$D$17:$D$46-1)*Projects!$B$17:$B$46*Assumptions!$B$10*0.05)+SUMPRODUCT((Projects!$G$7:$G$14="Yes")*(105>=Projects!$C$7:$C$14)*(105<Projects!$C$7:$C$14+Projects!$D$7:$D$14)*Projects!$B$7:$B$14*Assumptions!$B$12/Projects!$D$7:$D$14*0.95)+SUMPRODUCT((Projects!$G$7:$G$14="Yes")*(105=Projects!$C$7:$C$14+Projects!$D$7:$D$14-1)*Projects!$B$7:$B$14*Assumptions!$B$12*0.05)+SUMPRODUCT((Projects!$G$17:$G$46="Yes")*(105>=Projects!$C$17:$C$46)*(105<Projects!$C$17:$C$46+Projects!$D$17:$D$46)*Projects!$B$17:$B$46*Assumptions!$B$12/Projects!$D$17:$D$46*0.95)+SUMPRODUCT((Projects!$G$17:$G$46="Yes")*(105=Projects!$C$17:$C$46+Projects!$D$17:$D$46-1)*Projects!$B$17:$B$46*Assumptions!$B$12*0.05),Actuals!DF8) -> 0
