Workbook

Sheet Full Year
A1: FY2026 Full Year: Budget vs Forecast
A2: Budget = 2026 approved budget. Forecast = Jan to Sep actuals + Oct to Dec Base Case (28 Oct 2026: Acama bond actuals booked in October; 12th & Fir developer fee at $8,800 a month). Positive variance = better than budget. The budget charged $704,200 of Six Peak salaries to LV; that charge is shown on the Six Peak side here, so LV and Six Peak budget net income differ from the budget file by that amount (consolidated is unchanged). Board portal copy: prepared by Chris Andresen (29 Oct 2026), restated to the 28 Oct models.
A4: Line item | B4: Budget FY2026 | C4: Forecast FY2026 | D4: Variance | E4: Main reason for the variance
A5: LV CONSTRUCTION
A6: LV gross profit (excl. bonding) | B6: =Summary!H6 -> 5822292 | C6: =Summary!I6 -> 6437321.8 | D6: =C6-B6 -> 615029.84 | E6: Francis started in Aug instead of May (-$672K for the year). More than offset by higher margins on Crenshaw, Ramsgate, Califa and Whipple (+$670K) and by Riverton and Lexington, which were not in the budget (+$542K).
A7: Bonding program, net | B7: =Summary!H7 -> 0 | C7: =Summary!I7 -> -353763.79 | D7: =C7-B7 -> -353763.79 | E7: Not in the budget. Break-even through Sep; the Acama bond cost (-$391K) was booked in Oct, when the bond was issued.
A8: LV payroll and staff cost | B8: =Summary!H8 -> -2765983.4 | C8: =Summary!I8 -> -3052561.1 | D8: =C8-B8 -> -286577.62 | E8: LV roster is 26 people ($3.54M a year) vs 15 ($2.12M) in the budget, plus the $75K Dec bonus. Partly offset by lower payroll taxes and benefits and the Apr to May payroll reclass to job cost.
A9: LV other overhead | B9: =Summary!H9 -> -393698.1 | C9: =Summary!I9 -> -1039076.2 | D9: =C9-B9 -> -645378.06 | E9: Budget allowed about $33K a month; actual spending runs $70K to $90K a month (job-site supplies, warranty, consulting and placement fees, accounting, software, rent).
A10: LV net income | B10: =SUM(B6:B9) -> 2662610.4 | C10: =SUM(C6:C9) -> 1991920.8 | D10: =SUM(D6:D9) -> -670689.63
A12: SIX PEAK CAPITAL
A13: Six Peak fee revenue | B13: =Summary!H10 -> 647381.91 | C13: =Summary!I10 -> 484658.31 | D13: =C13-B13 -> -162723.6 | E13: Ramsgate construction dev fee $23.9K a month vs $36.5K budgeted; 12th & Fir at $8,800 a month; Crenshaw fee ends Oct.
A14: Six Peak one-time revenue | B14: =Summary!H11 -> 0 | C14: =Summary!I11 -> 426514 | D14: =C14-B14 -> 426514 | E14: Not budgeted: June $299K Aimwell LOC write-off (non-cash) and Aug Francis LIHTC $127.5K.
A15: Six Peak people cost | B15: =Summary!H12 -> -1990457.8 | C15: =Summary!I12 -> -2053724.9 | D15: =C15-B15 -> -63267.12 | E15: Close to budget. Partners paid as consultants and outside consultants replace budgeted payroll (budget shown gross of the $704K SP salary charge to LV).
A16: Six Peak other expenses | B16: =Summary!H13 -> -371578.98 | C16: =Summary!I13 -> -378002.77 | D16: =C16-B16 -> -6423.79 | E16: Close to budget.
A17: Six Peak net income | B17: =SUM(B13:B16) -> -1714654.8 | C17: =SUM(C13:C16) -> -1520555.3 | D17: =SUM(D13:D16) -> 194099.49
A19: SUBSIDIARIES
A20: APA Inc. (Six Peak share) | B20: =Summary!H14 -> 0 | C20: =Summary!I14 -> 3324.19 | D20: =C20-B20 -> 3324.19 | E20: Not budgeted; small.
A22: Consolidated net income | B22: =B10+B17+B20 -> 947955.58 | C22: =C10+C17+C20 -> 474689.63 | D22: =D10+D17+D20 -> -473265.95 | E22: Ahead by $655K through Sep, then -$1.13M in Q4: Francis and slower billing on the in-place jobs, the Acama bonding cost, the full LV roster plus bonus, and overhead. See the Drivers tab.
A23: Check vs Summary (should be 0) | B23: =ROUND(B22-Summary!H15,0) -> 0 | C23: =ROUND(C22-Summary!I15,0) -> 0 | D23: =ROUND(D22-Summary!J15,0) -> 0

Sheet Drivers
A1: Why FY2026 Misses Budget: Main Drivers
A2: Bridge from budget to forecast consolidated net income. Positive = better than budget. All amounts link to the Summary and LV GP by Job tabs.
A4: Driver | B4: Jan to Sep | C4: Q4 (Oct to Dec) | D4: Full year | E4: What happened
A5: Budget net income | B5: =Summary!B15 -> 501975.99 | C5: =Summary!E15 -> 445979.59 | D5: =B5+C5 -> 947955.58 | E5: Budget: ahead in Jan to Sep ($502K), $446K in Q4.
A6: Francis started three months late | B6: ='LV GP by Job'!D6 -> -443886 | C6: ='LV GP by Job'!G6 -> -228141 | D6: =B6+C6 -> -672027 | E6: Budget assumed a May 2026 start; the job started in August. Through Sep it billed $1.7M vs about $4.6M budgeted, and Q4 bills $2.6M vs $4.7M. The single largest gross profit shortfall.
A7: Other in-place jobs (Crenshaw, Ramsgate, Califa, Whipple, Nelrose) | B7: ='LV GP by Job'!D7+'LV GP by Job'!D8+'LV GP by Job'!D9+'LV GP by Job'!D10+'LV GP by Job'!D11 -> 1104703 | C7: ='LV GP by Job'!G7+'LV GP by Job'!G8+'LV GP by Job'!G9+'LV GP by Job'!G10+'LV GP by Job'!G11 -> -435158 | D7: =B7+C7 -> 669545 | E7: Well ahead through Sep on buyout savings and trade margin the budget did not include. Behind in Q4 because these jobs now bill on their schedules, more slowly than the budget curves, and Crenshaw has no margin left.
A8: Riverton and Lexington (not in budget) | B8: ='LV GP by Job'!D12+'LV GP by Job'!D13 -> 145922 | C8: ='LV GP by Job'!G12+'LV GP by Job'!G13 -> 396269 | D8: =B8+C8 -> 542191 | E8: New jobs that started Aug and Sep; they replace part of the Francis gap.
A9: Other job gross profit / rounding | B9: ='LV GP by Job'!D14 -> -131.46 | C9: ='LV GP by Job'!G14 -> 75452.3 | D9: =B9+C9 -> 75320.84 | E9: Plug to the model total (see LV GP by Job).
A10: Bonding program (not budgeted) | B10: =Summary!D7 -> 37404 | C10: =Summary!G7 -> -391167.79 | D10: =B10+C10 -> -353763.79 | E10: Roughly break-even through Sep; the Acama bond cost (-$391K) was booked in October, when the bond was issued.
A11: LV hiring and staff cost | B11: =Summary!D8 -> 106111.93 | C11: =Summary!G8 -> -392689.55 | D11: =B11+C11 -> -286577.62 | E11: LV has grown to 26 people ($3.54M a year) vs 15 ($2.12M) in the budget. Through Sep this was hidden by lower payroll taxes and benefits and the self-performed trades reclass; Q4 carries the full roster, the $75K Dec bonus and two new hires.
A12: LV other overhead | B12: =Summary!D9 -> -532379.58 | C12: =Summary!G9 -> -112998.48 | D12: =B12+C12 -> -645378.06 | E12: Budget allowed about $33K a month for non-payroll overhead; actual spending runs $70K to $90K a month (job-site supplies, warranty, consulting and placement fees, accounting, software, rent). A full-year issue, not a Q4 one.
A13: Six Peak fee revenue below budget | B13: =Summary!D10 -> -122476.98 | C13: =Summary!G10 -> -40246.62 | D13: =B13+C13 -> -162723.6 | E13: Ramsgate dev fee lower than budgeted; 12th & Fir at $8,800 a month; Crenshaw fee ends in Oct.
A14: Six Peak one-time revenue | B14: =Summary!D11 -> 426514 | C14: =Summary!G11 -> 0 | D14: =B14+C14 -> 426514 | E14: June $299K Aimwell LOC write-off (non-cash) and Aug Francis LIHTC $127.5K. These carried the Jan to Sep result and do not repeat in Q4.
A15: Six Peak people and other costs | B15: =Summary!D12+Summary!D13 -> -66784.45 | C15: =Summary!G12+Summary!G13 -> -2906.46 | D15: =B15+C15 -> -69690.91 | E15: Close to budget once the intercompany salary charge is put back on the Six Peak side.
A16: APA Inc. | B16: =Summary!D14 -> 0 | C16: =Summary!G14 -> 3324.19 | D16: =B16+C16 -> 3324.19 | E16: Small.
A17: Forecast net income | B17: =SUM(B5:B16) -> 1156972.4 | C17: =SUM(C5:C16) -> -682282.82 | D17: =SUM(D5:D16) -> 474689.63
A18: Variance to budget | B18: =B17-B5 -> 654996.46 | C18: =C17-C5 -> -1128262.4 | D18: =D17-D5 -> -473265.95
A19: Check vs Summary (should be 0) | B19: =ROUND(B17-Summary!C15,0) -> 0 | C19: =ROUND(C17-Summary!F15,0) -> 0 | D19: =ROUND(D17-Summary!I15,0) -> 0
A21: Key takeaways
A22: 1. Ahead through September (+$655K) because the existing jobs earned more margin than budgeted (+$1.29M) and Six Peak had $427K of one-time revenue. Those more than covered Francis running late (-$444K) and overhead above budget.
A23: 2. Q4 swings to -$1.13M vs budget: Francis and the slower burn on the in-place jobs (-$192K of gross profit after Riverton and Lexington), the Acama bonding cost (-$391K), the full LV roster plus the bonus (-$393K) and overhead (-$113K).
A24: 3. Full year -$473K. The biggest negatives are Francis (-$672K), LV non-payroll overhead (-$645K), bonding (-$354K) and LV staff cost (-$287K). Better margins on the other jobs (+$670K), Riverton and Lexington (+$542K) and one-time Six Peak revenue (+$427K) offset most of it.
A25: 4. So the read is: yes, Francis starting late and more hiring, but non-payroll overhead running about twice budget all year is just as large, and the October Acama bonding charge is not in the budget at all.
A26: 5. Why Q4 turns negative: Jan to Sep was carried by items the budget did not have and that do not repeat. Bonding was break-even while Krueger's fee on Califa, Whipple and Riverton was paid in equity, and Six Peak booked the $299K Aimwell line-of-credit write-off and the $127.5K Francis LIHTC fee. Q4 has none of those, and it carries the Acama bonding cost, the full LV roster and the December bonus.

Sheet Summary
A1: FY2026 Budget vs Forecast: Consolidated Net Income
A2: Budget = 2026 approved budget (Base Case Budget tab). Forecast = Jan to Sep actuals + Oct to Dec Base Case (28 Oct 2026: Acama bond actuals booked in October; 12th & Fir developer fee at $8,800 a month). Bonding shown on its own line. Blue = values from source files; black = formulas.
B4: Jan to Sep | E4: Q4 (Oct to Dec) | H4: Full Year 2026
A5: Line item | B5: Budget | C5: Actual | D5: Variance | E5: Budget | F5: Forecast | G5: Variance | H5: Budget | I5: Forecast | J5: Variance | K5: Why the difference exists
A6: LV gross profit (excl. bonding) | B6: 4143426.9 | C6: 4950034.5 | D6: =C6-B6 -> 806607.54 | E6: 1678865 | F6: 1487287.3 | G6: =F6-E6 -> -191577.7 | H6: =B6+E6 -> 5822292 | I6: =C6+F6 -> 6437321.8 | J6: =I6-H6 -> 615029.84 | K6: Jan to Sep ahead: actual job margins include buyout savings and trade margin the budget did not assume (the budget billed trades at cost and earned only fee, supervision and admin). Q4 behind: Francis started in Aug, not May as budgeted, and Ramsgate, Whipple and Califa bill more slowly on their schedules than the budget curves; Riverton and Lexington (not budgeted) offset part. See 'LV GP by Job'.
A7: Bonding program, net | B7: 0 | C7: 37404 | D7: =C7-B7 -> 37404 | E7: 0 | F7: -391167.79 | G7: =F7-E7 -> -391167.79 | H7: =B7+E7 -> 0 | I7: =C7+F7 -> -353763.79 | J7: =I7-H7 -> -353763.79 | K7: Not budgeted. Jan to Sep: Francis, Riverton and Lexington bond lines billed $1,243,016, less CBI premiums $512,735, less Krueger cash $692,877 (booked Sep). Q4: Acama Krueger cash and premium, net of its bond line, booked in Oct (bond issued 12 Oct).
A8: LV payroll and staff cost | B8: -2074487.6 | C8: -1968375.6 | D8: =C8-B8 -> 106111.93 | E8: -691495.86 | F8: -1084185.4 | G8: =F8-E8 -> -392689.55 | H8: =B8+E8 -> -2765983.4 | I8: =C8+F8 -> -3052561.1 | J8: =I8-H8 -> -286577.62 | K8: Salaries, consultant split, taxes, benefits, net of the Apr to May self-performed trades reclass (+$332,814 moved to job cost). Jan to Sep looks favorable only because taxes and benefits ran about $279K under budget and the reclass. Q4: the LV roster is now 26 people at $3.54M a year vs 15 people at $2.12M in the budget, plus the $75K Dec bonus, the Oct coordinator and the Dec superintendent.
A9: LV other overhead | B9: -294299.1 | C9: -826678.68 | D9: =C9-B9 -> -532379.58 | E9: -99399 | F9: -212397.48 | G9: =F9-E9 -> -112998.48 | H9: =B9+E9 -> -393698.1 | I9: =C9+F9 -> -1039076.2 | J9: =I9-H9 -> -645378.06 | K9: The budget allowed about $33K a month; actuals ran about $92K a month Jan to Sep and the forecast about $71K a month. Largest lines: job-site supplies, warranty, consulting and placement fees, accounting, outside consultants, software and rent. See 'Overhead by Account'.
A10: Six Peak fee revenue | B10: 499641.54 | C10: 377164.56 | D10: =C10-B10 -> -122476.98 | E10: 147740.37 | F10: 107493.75 | G10: =F10-E10 -> -40246.62 | H10: =B10+E10 -> 647381.91 | I10: =C10+F10 -> 484658.31 | J10: =I10-H10 -> -162723.6 | K10: Ramsgate construction dev fee is $23.9K a month vs $36.5K budgeted; 12th & Fir ($8,800 a month) and Edgemont below budget; Crenshaw dev fee ends Oct.
A11: Six Peak one-time revenue | B11: 0 | C11: 426514 | D11: =C11-B11 -> 426514 | E11: 0 | F11: 0 | G11: =F11-E11 -> 0 | H11: =B11+E11 -> 0 | I11: =C11+F11 -> 426514 | J11: =I11-H11 -> 426514 | K11: Not budgeted: June $299,000 Aimwell line-of-credit write-off (non-cash) and Aug Francis LIHTC revenue $127,514.
A12: Six Peak people cost | B12: -1494541.3 | C12: -1555123.4 | D12: =C12-B12 -> -60582.06 | E12: -495916.44 | F12: -498601.5 | G12: =F12-E12 -> -2685.06 | H12: =B12+E12 -> -1990457.8 | I12: =C12+F12 -> -2053724.9 | J12: =I12-H12 -> -63267.12 | K12: Budget shown gross: it charged $58.7K a month of Six Peak salaries to LV, added back here so LV and Six Peak compare like for like. Partners paid as consultants ($800K a year) and outside consultants replace budgeted payroll; net close to budget.
A13: Six Peak other expenses | B13: -277764.48 | C13: -283966.87 | D13: =C13-B13 -> -6202.39 | E13: -93814.5 | F13: -94035.9 | G13: =F13-E13 -> -221.4 | H13: =B13+E13 -> -371578.98 | I13: =C13+F13 -> -378002.77 | J13: =I13-H13 -> -6423.79 | K13: Close to budget.
A14: APA Inc. (Six Peak share) | B14: 0 | C14: 0 | D14: =C14-B14 -> 0 | E14: 0 | F14: 3324.19 | G14: =F14-E14 -> 3324.19 | H14: =B14+E14 -> 0 | I14: =C14+F14 -> 3324.19 | J14: =I14-H14 -> 3324.19 | K14: Not budgeted; small.
A15: Consolidated net income | B15: =SUM(B6:B14) -> 501975.99 | C15: =SUM(C6:C14) -> 1156972.4 | D15: =SUM(D6:D14) -> 654996.46 | E15: =SUM(E6:E14) -> 445979.59 | F15: =SUM(F6:F14) -> -682282.82 | G15: =SUM(G6:G14) -> -1128262.4 | H15: =SUM(H6:H14) -> 947955.58 | I15: =SUM(I6:I14) -> 474689.63 | J15: =SUM(J6:J14) -> -473265.95
A16: Check: model / budget net income | B16: 501975.99 | C16: 1156972.4 | E16: 445979.59 | F16: -682282.82 | H16: =B16+E16 -> 947955.58 | I16: =C16+F16 -> 474689.63 | K16: Budget: Base Case Budget tab rows 57 + 114. Model: Base Case Model row 308.
A17: Difference (should be 0) | B17: =ROUND(B15-B16,0) -> 0 | C17: =ROUND(C15-C16,0) -> 0 | E17: =ROUND(E15-E16,0) -> 0 | F17: =ROUND(F15-F16,0) -> 0 | H17: =ROUND(H15-H16,0) -> 0 | I17: =ROUND(I15-I16,0) -> 0

Sheet LV GP by Job
A1: LV Gross Profit by Job (excl. bonding)
A2: Budget: Nov 2025 budget model, LV Detail Projection (fee rows 84-89 + supervision 114-119 + admin 144-149; trades billed at cost). Actual Jan to Sep: LV Board Portal September, Job Results YTD GP less 2026 bonding. Q4: 9/30 backlog x remaining cost from the portal job tabs, applied to Model rows 60-67 Q4 cost.
B4: Jan to Sep | E4: Q4 (Oct to Dec) | H4: Full Year 2026
A5: Job | B5: Budget | C5: Actual | D5: Variance | E5: Budget | F5: Forecast | G5: Variance | H5: Budget | I5: Forecast | J5: Variance | K5: Note
A6: Francis | B6: 764527 | C6: 320641 | D6: =C6-B6 -> -443886 | E6: 534528 | F6: 306387 | G6: =F6-E6 -> -228141 | H6: =B6+E6 -> 1299055 | I6: =C6+F6 -> 627028 | J6: =I6-H6 -> -672027 | K6: Budget assumed a May 2026 start (30 months); job started Aug 2026. Billed $1.7M through Sep vs about $4.6M of budgeted trade billing. Q4 revenue $2.6M vs $4.7M budgeted.
A7: Crenshaw | B7: 570931 | C7: 849821 | D7: =C7-B7 -> 278890 | E7: 96383 | F7: -1288 | G7: =F7-E7 -> -97671 | H7: =B7+E7 -> 667314 | I7: =C7+F7 -> 848533 | J7: =I7-H7 -> 181219 | K7: Ahead through Sep on buyout savings; Q4 has no margin left (remaining fee, supervision and admin billings absorbed by trade cost and contingency).
A8: Ramsgate | B8: 967731 | C8: 1388965 | D8: =C8-B8 -> 421234 | E8: 339026 | F8: 185788 | G8: =F8-E8 -> -153238 | H8: =B8+E8 -> 1306757 | I8: =C8+F8 -> 1574753 | J8: =I8-H8 -> 267996 | K8: Ahead through Sep; Q4 billing $2.6M vs $4.6M budgeted (schedule slower than the budget curve) and remaining margin 7.7% after contingency overrun.
A9: Califa | B9: 734724 | C9: 943558 | D9: =C9-B9 -> 208834 | E9: 284423 | F9: 201669 | G9: =F9-E9 -> -82754 | H9: =B9+E9 -> 1019147 | I9: =C9+F9 -> 1145227 | J9: =I9-H9 -> 126080 | K9: Ahead through Sep; Q4 billing $1.8M vs $3.0M budgeted.
A10: Whipple | B10: 820840 | C10: 1052962 | D10: =C10-B10 -> 232122 | E10: 317759 | F10: 188277 | G10: =F10-E10 -> -129482 | H10: =B10+E10 -> 1138599 | I10: =C10+F10 -> 1241239 | J10: =I10-H10 -> 102640 | K10: Ahead through Sep; Q4 billing $1.7M vs $3.4M budgeted.
A11: Nelrose | B11: 284673 | C11: 248296 | D11: =C11-B11 -> -36377 | E11: 106746 | F11: 134733 | G11: =F11-E11 -> 27987 | H11: =B11+E11 -> 391419 | I11: =C11+F11 -> 383029 | J11: =I11-H11 -> -8390 | K11: About on budget.
A12: Riverton | B12: 0 | C12: 66270 | D12: =C12-B12 -> 66270 | E12: 0 | F12: 221423 | G12: =F12-E12 -> 221423 | H12: =B12+E12 -> 0 | I12: =C12+F12 -> 287693 | J12: =I12-H12 -> 287693 | K12: Not in the 2026 budget.
A13: Lexington | B13: 0 | C13: 79652 | D13: =C13-B13 -> 79652 | E13: 0 | F13: 174846 | G13: =F13-E13 -> 174846 | H13: =B13+E13 -> 0 | I13: =C13+F13 -> 254498 | J13: =I13-H13 -> 254498 | K13: Not in the 2026 budget. Actual YTD excludes bonding.
A14: Other / unallocated | B14: =Summary!B6-SUM(B6:B13) -> 0.93 | C14: =Summary!C6-SUM(C6:C13) -> -130.53 | D14: =C14-B14 -> -131.46 | E14: =Summary!E6-SUM(E6:E13) -> 0.02 | F14: =Summary!F6-SUM(F6:F13) -> 75452.32 | G14: =F14-E14 -> 75452.3 | H14: =B14+E14 -> 0.95 | I14: =C14+F14 -> 75321.79 | J14: =I14-H14 -> 75320.84 | K14: Plugs the job rows to the model total: Acama, Scott, Klump, rounding to the P&L, and the per-job Q4 estimate (the model holds in-place fee income as one combined figure in rows 10 and 11). Q4 trade cost true-up included.
A15: Total LV gross profit | B15: =SUM(B6:B14) -> 4143426.9 | C15: =SUM(C6:C14) -> 4950034.5 | D15: =SUM(D6:D14) -> 806607.54 | E15: =SUM(E6:E14) -> 1678865 | F15: =SUM(F6:F14) -> 1487287.3 | G15: =SUM(G6:G14) -> -191577.7 | H15: =SUM(H6:H14) -> 5822292 | I15: =SUM(I6:I14) -> 6437321.8 | J15: =SUM(J6:J14) -> 615029.84

Sheet Overhead by Account
A1: Overhead by Account: Budget vs Forecast
A2: Budget: Base Case Budget tab. Forecast: Actuals Jan to Sep + Model Q4. Budget SP salaries charged to LV are shown in the Six Peak section (intercompany), not in LV. The Other P&L items rows tie the account lines to the P&L totals (small lines the model does not show by account).
A4: Account | B4: Budget Jan-Sep | C4: Actual Jan-Sep | D4: Budget Q4 | E4: Forecast Q4 | F4: Budget FY | G4: Forecast FY | H4: Variance FY | I4: Variance Q4
A5: LV CONSTRUCTION
A6: 5000-1000 Payroll (incl. LV Dec bonus) | B6: -1586250 | C6: -1813500 | D6: -528750 | E6: -892226 | F6: =B6+D6 -> -2115000 | G6: =C6+E6 -> -2705726 | H6: =G6-F6 -> -590726 | I6: =E6-D6 -> -363476
A7: 5000-1001 Payroll Taxes | B7: -237938 | C7: -138159 | D7: -79312 | E7: -68581 | F7: =B7+D7 -> -317250 | G7: =C7+E7 -> -206740 | H7: =G7-F7 -> 110510 | I7: =E7-D7 -> 10731
A8: 5000-1002 Employee Benefits | B8: -225645 | C8: -63206 | D8: -75215 | E8: -34290 | F8: =B8+D8 -> -300860 | G8: =C8+E8 -> -97496 | H8: =G8-F8 -> 203364 | I8: =E8-D8 -> 40925
A9: 5000-1003 Workers Comp | B9: -15583 | C9: -7095 | D9: -5194 | E9: -2939 | F9: =B9+D9 -> -20777 | G9: =C9+E9 -> -10034 | H9: =G9-F9 -> 10743 | I9: =E9-D9 -> 2255
A10: 5000-1005 Payroll Servicing Fees | B10: -9072 | C10: -395 | D10: -3024 | E10: -4899 | F10: =B10+D10 -> -12096 | G10: =C10+E10 -> -5294 | H10: =G10-F10 -> 6802 | I10: =E10-D10 -> -1875
A11: 5000-1007 Payroll - Consultants | B11: 0 | C11: -278836 | D11: 0 | E11: -81250 | F11: =B11+D11 -> 0 | G11: =C11+E11 -> -360086 | H11: =G11-F11 -> -360086 | I11: =E11-D11 -> -81250
A12: 5000-1018 Payroll - Self Performed Trades | B12: 0 | C12: 332814 | D12: 0 | E12: 0 | F12: =B12+D12 -> 0 | G12: =C12+E12 -> 332814 | H12: =G12-F12 -> 332814 | I12: =E12-D12 -> 0
A13: 5100-1000 Rent Expense | B13: -90600 | C13: -133215 | D13: -30600 | E13: -45000 | F13: =B13+D13 -> -121200 | G13: =C13+E13 -> -178215 | H13: =G13-F13 -> -57015 | I13: =E13-D13 -> -14400
A14: 5200-1000 Office Supplies and Expenses | B14: -25368 | C14: -44106 | D14: -8568 | E14: -12074 | F14: =B14+D14 -> -33936 | G14: =C14+E14 -> -56180 | H14: =G14-F14 -> -22244 | I14: =E14-D14 -> -3506
A15: 5200-1002 Printing and Reproduction | B15: 0 | C15: -6842 | D15: 0 | E15: -1077 | F15: =B15+D15 -> 0 | G15: =C15+E15 -> -7919 | H15: =G15-F15 -> -7919 | I15: =E15-D15 -> -1077
A16: 5200-1050 Computer and IT Expenses | B16: -29898 | C16: -168 | D16: -10098 | E16: -79 | F16: =B16+D16 -> -39996 | G16: =C16+E16 -> -247 | H16: =G16-F16 -> 39749 | I16: =E16-D16 -> 10019
A17: 5200-1053 IT Software and Subscriptions | B17: 0 | C17: -54278 | D17: 0 | E17: -15902 | F17: =B17+D17 -> 0 | G17: =C17+E17 -> -70180 | H17: =G17-F17 -> -70180 | I17: =E17-D17 -> -15902
... A36: 8200-2000 State Tax and Fees | B36: -3775 | C36: -11105 | D36: -1275 | E36: -3750 | F36: =B36+D36 -> -5050 | G36: =C36+E36 -> -14855 | H36: =G36-F36 -> -9805 | I36: =E36-D36 -> -2475
A37: Other P&L items not on an account line above | B37: =ROUND((Summary!B8+Summary!B9)-SUM(B6:B36),0) -> 0 | C37: =ROUND((Summary!C8+Summary!C9)-SUM(C6:C36),0) -> -5442 | D37: =ROUND((Summary!E8+Summary!E9)-SUM(D6:D36),0) -> -1 | E37: =ROUND((Summary!F8+Summary!F9)-SUM(E6:E36),0) -> -2 | F37: =B37+D37 -> -1 | G37: =C37+E37 -> -5444 | H37: =G37-F37 -> -5443 | I37: =E37-D37 -> -1
A38: Total LV Construction | B38: =SUM(B6:B37) -> -2368787 | C38: =SUM(C6:C37) -> -2795054 | D38: =SUM(D6:D37) -> -790895 | E38: =SUM(E6:E37) -> -1296583 | F38: =SUM(F6:F37) -> -3159682 | G38: =SUM(G6:G37) -> -4091637 | H38: =SUM(H6:H37) -> -931955 | I38: =SUM(I6:I37) -> -505688
A39: Check vs Summary (should be 0) | B39: =ROUND(B38-(Summary!B8+Summary!B9),0) -> 0 | C39: =ROUND(C38-(Summary!C8+Summary!C9),0) -> 0 | D39: =ROUND(D38-(Summary!E8+Summary!E9),0) -> 0 | E39: =ROUND(E38-(Summary!F8+Summary!F9),0) -> 0
A41: SIX PEAK CAPITAL
A42: 5000-1000 Payroll | B42: -808579 | C42: -487754 | D42: -267179 | E42: -162500 | F42: =B42+D42 -> -1075758 | G42: =C42+E42 -> -650254 | H42: =G42-F42 -> 425504 | I42: =E42-D42 -> 104679
A43: 5000-1001 Payroll Taxes | B43: -73125 | C43: -38245 | D43: -24375 | E43: -11375 | F43: =B43+D43 -> -97500 | G43: =C43+E43 -> -49620 | H43: =G43-F43 -> 47880 | I43: =E43-D43 -> 13000
A44: 5000-1002 Employee Benefits | B44: -58988 | C44: -109240 | D44: -19663 | E44: -36414 | F44: =B44+D44 -> -78651 | G44: =C44+E44 -> -145654 | H44: =G44-F44 -> -67003 | I44: =E44-D44 -> -16751
A45: 5000-1003 Workers Comp | B45: -4388 | C45: -4282 | D45: -1462 | E45: -3250 | F45: =B45+D45 -> -5850 | G45: =C45+E45 -> -7532 | H45: =G45-F45 -> -1682 | I45: =E45-D45 -> -1788
A46: 5000-1005 Payroll Servicing Fees | B46: -2437 | C46: -19801 | D46: -812 | E46: -812 | F46: =B46+D46 -> -3249 | G46: =C46+E46 -> -20613 | H46: =G46-F46 -> -17364 | I46: =E46-D46 -> 0
A47: 5100-1000 Rent Expense | B47: -72480 | C47: -74297 | D47: -24480 | E47: -25500 | F47: =B47+D47 -> -96960 | G47: =C47+E47 -> -99797 | H47: =G47-F47 -> -2837 | I47: =E47-D47 -> -1020
A48: 5200-1000 Office Supplies and Expenses | B48: -1661 | C48: -3710 | D48: -561 | E48: -1751 | F48: =B48+D48 -> -2222 | G48: =C48+E48 -> -5461 | H48: =G48-F48 -> -3239 | I48: =E48-D48 -> -1190
A49: 5200-1053 IT Software and Subscriptions | B49: -27180 | C49: -22779 | D49: -9180 | E49: -4494 | F49: =B49+D49 -> -36360 | G49: =C49+E49 -> -27273 | H49: =G49-F49 -> 9087 | I49: =E49-D49 -> 4686
A50: 5200-1060 Website Design | B50: 0 | C50: -870 | D50: 0 | E50: -870 | F50: =B50+D50 -> 0 | G50: =C50+E50 -> -1740 | H50: =G50-F50 -> -1740 | I50: =E50-D50 -> -870
A51: 5200-1061 Website Hosting | B51: 0 | C51: -1960 | D51: 0 | E51: -735 | F51: =B51+D51 -> 0 | G51: =C51+E51 -> -2695 | H51: =G51-F51 -> -2695 | I51: =E51-D51 -> -735
A52: 5300-1000 Travel and Lodging | B52: -27180 | C52: -15003 | D52: -9180 | E52: -3538 | F52: =B52+D52 -> -36360 | G52: =C52+E52 -> -18541 | H52: =G52-F52 -> 17819 | I52: =E52-D52 -> 5642
A53: 5300-1001 Public Transportation | B53: -7550 | C53: -3130 | D53: -2550 | E53: -1099 | F53: =B53+D53 -> -10100 | G53: =C53+E53 -> -4229 | H53: =G53-F53 -> 5871 | I53: =E53-D53 -> 1451
... A66: Budget: SP salaries charged to LV (intercompany) | B66: -528150 | C66: 0 | D66: -176050 | E66: 0 | F66: =B66+D66 -> -704200 | G66: =C66+E66 -> 0 | H66: =G66-F66 -> 704200 | I66: =E66-D66 -> 176050
A67: Other P&L items not on an account line above | B67: =ROUND((Summary!B12+Summary!B13)-SUM(B42:B66),0) -> 1 | C67: =ROUND((Summary!C12+Summary!C13)-SUM(C42:C66),0) -> 50838 | D67: =ROUND((Summary!E12+Summary!E13)-SUM(D42:D66),0) -> 0 | E67: =ROUND((Summary!F12+Summary!F13)-SUM(E42:E66),0) -> 0 | F67: =B67+D67 -> 1 | G67: =C67+E67 -> 50838 | H67: =G67-F67 -> 50837 | I67: =E67-D67 -> 0
A68: Total Six Peak Capital | B68: =SUM(B42:B67) -> -1772306 | C68: =SUM(C42:C67) -> -1839090 | D68: =SUM(D42:D67) -> -589731 | E68: =SUM(E42:E67) -> -592637 | F68: =SUM(F42:F67) -> -2362037 | G68: =SUM(G42:G67) -> -2431727 | H68: =SUM(H42:H67) -> -69690 | I68: =SUM(I42:I67) -> -2906
A69: Check vs Summary (should be 0) | B69: =ROUND(B68-(Summary!B12+Summary!B13),0) -> 0 | C69: =ROUND(C68-(Summary!C12+Summary!C13),0) -> 0 | D69: =ROUND(D68-(Summary!E12+Summary!E13),0) -> 0 | E69: =ROUND(E68-(Summary!F12+Summary!F13),0) -> 0
