Workbook

Sheet Annual Summary
A1: Six Peak Capital - Annual Summary
B2: FY 2026 | C2: FY 2027 | D2: FY 2028 | E2: FY 2029 | F2: FY 2030 | G2: FY 2031 | H2: FY 2032 | I2: FY 2033
A3: Construction Billing | B3: =Model!C7+Model!D7+Model!E7+Model!F7+Model!G7+Model!H7+Model!I7+Model!J7+Model!K7 -> 49799775 | C3: =Model!L7+Model!M7+Model!N7+Model!O7+Model!P7+Model!Q7+Model!R7+Model!S7+Model!T7+Model!U7+Model!V7+Model!W7 -> 87218737 | D3: =Model!X7+Model!Y7+Model!Z7+Model!AA7+Model!AB7+Model!AC7+Model!AD7+Model!AE7+Model!AF7+Model!AG7+Model!AH7+Model!AI7 -> 51675801 | E3: =Model!AJ7+Model!AK7+Model!AL7+Model!AM7+Model!AN7+Model!AO7+Model!AP7+Model!AQ7+Model!AR7+Model!AS7+Model!AT7+Model!AU7 -> 32893827 | F3: =Model!AV7+Model!AW7+Model!AX7+Model!AY7+Model!AZ7+Model!BA7+Model!BB7+Model!BC7+Model!BD7+Model!BE7+Model!BF7+Model!BG7 -> 13258750 | G3: =Model!BH7+Model!BI7+Model!BJ7+Model!BK7+Model!BL7+Model!BM7+Model!BN7+Model!BO7+Model!BP7+Model!BQ7+Model!BR7+Model!BS7 -> 0 | H3: =Model!BT7+Model!BU7+Model!BV7+Model!BW7+Model!BX7+Model!BY7+Model!BZ7+Model!CA7+Model!CB7+Model!CC7+Model!CD7+Model!CE7 -> 0 | I3: =Model!CF7+Model!CG7+Model!CH7 -> 0
A4: GC Revenue
A5: Project Supervision | B5: =Model!C8+Model!D8+Model!E8+Model!F8+Model!G8+Model!H8+Model!I8+Model!J8+Model!K8 -> 2232648.8 | C5: =Model!L8+Model!M8+Model!N8+Model!O8+Model!P8+Model!Q8+Model!R8+Model!S8+Model!T8+Model!U8+Model!V8+Model!W8 -> 3751686.3 | D5: =Model!X8+Model!Y8+Model!Z8+Model!AA8+Model!AB8+Model!AC8+Model!AD8+Model!AE8+Model!AF8+Model!AG8+Model!AH8+Model!AI8 -> 3068658.6 | E5: =Model!AJ8+Model!AK8+Model!AL8+Model!AM8+Model!AN8+Model!AO8+Model!AP8+Model!AQ8+Model!AR8+Model!AS8+Model!AT8+Model!AU8 -> 1544141.5 | F5: =Model!AV8+Model!AW8+Model!AX8+Model!AY8+Model!AZ8+Model!BA8+Model!BB8+Model!BC8+Model!BD8+Model!BE8+Model!BF8+Model!BG8 -> 738475.57 | G5: =Model!BH8+Model!BI8+Model!BJ8+Model!BK8+Model!BL8+Model!BM8+Model!BN8+Model!BO8+Model!BP8+Model!BQ8+Model!BR8+Model!BS8 -> 0 | H5: =Model!BT8+Model!BU8+Model!BV8+Model!BW8+Model!BX8+Model!BY8+Model!BZ8+Model!CA8+Model!CB8+Model!CC8+Model!CD8+Model!CE8 -> 0 | I5: =Model!CF8+Model!CG8+Model!CH8 -> 0
A6: GC-CM Fee | B6: =Model!C9+Model!D9+Model!E9+Model!F9+Model!G9+Model!H9+Model!I9+Model!J9+Model!K9 -> 2357173 | C6: =Model!L9+Model!M9+Model!N9+Model!O9+Model!P9+Model!Q9+Model!R9+Model!S9+Model!T9+Model!U9+Model!V9+Model!W9 -> 3824039.1 | D6: =Model!X9+Model!Y9+Model!Z9+Model!AA9+Model!AB9+Model!AC9+Model!AD9+Model!AE9+Model!AF9+Model!AG9+Model!AH9+Model!AI9 -> 3068658.6 | E6: =Model!AJ9+Model!AK9+Model!AL9+Model!AM9+Model!AN9+Model!AO9+Model!AP9+Model!AQ9+Model!AR9+Model!AS9+Model!AT9+Model!AU9 -> 1544141.5 | F6: =Model!AV9+Model!AW9+Model!AX9+Model!AY9+Model!AZ9+Model!BA9+Model!BB9+Model!BC9+Model!BD9+Model!BE9+Model!BF9+Model!BG9 -> 738475.57 | G6: =Model!BH9+Model!BI9+Model!BJ9+Model!BK9+Model!BL9+Model!BM9+Model!BN9+Model!BO9+Model!BP9+Model!BQ9+Model!BR9+Model!BS9 -> 0 | H6: =Model!BT9+Model!BU9+Model!BV9+Model!BW9+Model!BX9+Model!BY9+Model!BZ9+Model!CA9+Model!CB9+Model!CC9+Model!CD9+Model!CE9 -> 0 | I6: =Model!CF9+Model!CG9+Model!CH9 -> 0
A7: Project Administration | B7: =Model!C10+Model!D10+Model!E10+Model!F10+Model!G10+Model!H10+Model!I10+Model!J10+Model!K10 -> 619717.29 | C7: =Model!L10+Model!M10+Model!N10+Model!O10+Model!P10+Model!Q10+Model!R10+Model!S10+Model!T10+Model!U10+Model!V10+Model!W10 -> 1155343.7 | D7: =Model!X10+Model!Y10+Model!Z10+Model!AA10+Model!AB10+Model!AC10+Model!AD10+Model!AE10+Model!AF10+Model!AG10+Model!AH10+Model!AI10 -> 1022886.2 | E7: =Model!AJ10+Model!AK10+Model!AL10+Model!AM10+Model!AN10+Model!AO10+Model!AP10+Model!AQ10+Model!AR10+Model!AS10+Model!AT10+Model!AU10 -> 514713.83 | F7: =Model!AV10+Model!AW10+Model!AX10+Model!AY10+Model!AZ10+Model!BA10+Model!BB10+Model!BC10+Model!BD10+Model!BE10+Model!BF10+Model!BG10 -> 246158.52 | G7: =Model!BH10+Model!BI10+Model!BJ10+Model!BK10+Model!BL10+Model!BM10+Model!BN10+Model!BO10+Model!BP10+Model!BQ10+Model!BR10+Model!BS10 -> 0 | H7: =Model!BT10+Model!BU10+Model!BV10+Model!BW10+Model!BX10+Model!BY10+Model!BZ10+Model!CA10+Model!CB10+Model!CC10+Model!CD10+Model!CE10 -> 0 | I7: =Model!CF10+Model!CG10+Model!CH10 -> 0
A8: Bonding Revenue | B8: =Model!C11+Model!D11+Model!E11+Model!F11+Model!G11+Model!H11+Model!I11+Model!J11+Model!K11 -> 1405537.6 | C8: =Model!L11+Model!M11+Model!N11+Model!O11+Model!P11+Model!Q11+Model!R11+Model!S11+Model!T11+Model!U11+Model!V11+Model!W11 -> 679001.55 | D8: =Model!X11+Model!Y11+Model!Z11+Model!AA11+Model!AB11+Model!AC11+Model!AD11+Model!AE11+Model!AF11+Model!AG11+Model!AH11+Model!AI11 -> 620319.48 | E8: =Model!AJ11+Model!AK11+Model!AL11+Model!AM11+Model!AN11+Model!AO11+Model!AP11+Model!AQ11+Model!AR11+Model!AS11+Model!AT11+Model!AU11 -> 0 | F8: =Model!AV11+Model!AW11+Model!AX11+Model!AY11+Model!AZ11+Model!BA11+Model!BB11+Model!BC11+Model!BD11+Model!BE11+Model!BF11+Model!BG11 -> 0 | G8: =Model!BH11+Model!BI11+Model!BJ11+Model!BK11+Model!BL11+Model!BM11+Model!BN11+Model!BO11+Model!BP11+Model!BQ11+Model!BR11+Model!BS11 -> 0 | H8: =Model!BT11+Model!BU11+Model!BV11+Model!BW11+Model!BX11+Model!BY11+Model!BZ11+Model!CA11+Model!CB11+Model!CC11+Model!CD11+Model!CE11 -> 0 | I8: =Model!CF11+Model!CG11+Model!CH11 -> 0
A9: Total GC Revenue | B9: =Model!C12+Model!D12+Model!E12+Model!F12+Model!G12+Model!H12+Model!I12+Model!J12+Model!K12 -> 6615076.7 | C9: =Model!L12+Model!M12+Model!N12+Model!O12+Model!P12+Model!Q12+Model!R12+Model!S12+Model!T12+Model!U12+Model!V12+Model!W12 -> 9410070.7 | D9: =Model!X12+Model!Y12+Model!Z12+Model!AA12+Model!AB12+Model!AC12+Model!AD12+Model!AE12+Model!AF12+Model!AG12+Model!AH12+Model!AI12 -> 7780522.9 | E9: =Model!AJ12+Model!AK12+Model!AL12+Model!AM12+Model!AN12+Model!AO12+Model!AP12+Model!AQ12+Model!AR12+Model!AS12+Model!AT12+Model!AU12 -> 3602996.8 | F9: =Model!AV12+Model!AW12+Model!AX12+Model!AY12+Model!AZ12+Model!BA12+Model!BB12+Model!BC12+Model!BD12+Model!BE12+Model!BF12+Model!BG12 -> 1723109.7 | G9: =Model!BH12+Model!BI12+Model!BJ12+Model!BK12+Model!BL12+Model!BM12+Model!BN12+Model!BO12+Model!BP12+Model!BQ12+Model!BR12+Model!BS12 -> 0 | H9: =Model!BT12+Model!BU12+Model!BV12+Model!BW12+Model!BX12+Model!BY12+Model!BZ12+Model!CA12+Model!CB12+Model!CC12+Model!CD12+Model!CE12 -> 0 | I9: =Model!CF12+Model!CG12+Model!CH12 -> 0
A11: GC Costs
A12: Bonding Costs | B12: =Model!C15+Model!D15+Model!E15+Model!F15+Model!G15+Model!H15+Model!I15+Model!J15+Model!K15 -> -693398.56 | C12: =Model!L15+Model!M15+Model!N15+Model!O15+Model!P15+Model!Q15+Model!R15+Model!S15+Model!T15+Model!U15+Model!V15+Model!W15 -> -1471170 | D12: =Model!X15+Model!Y15+Model!Z15+Model!AA15+Model!AB15+Model!AC15+Model!AD15+Model!AE15+Model!AF15+Model!AG15+Model!AH15+Model!AI15 -> -1344025.5 | E12: =Model!AJ15+Model!AK15+Model!AL15+Model!AM15+Model!AN15+Model!AO15+Model!AP15+Model!AQ15+Model!AR15+Model!AS15+Model!AT15+Model!AU15 -> 0 | F12: =Model!AV15+Model!AW15+Model!AX15+Model!AY15+Model!AZ15+Model!BA15+Model!BB15+Model!BC15+Model!BD15+Model!BE15+Model!BF15+Model!BG15 -> 0 | G12: =Model!BH15+Model!BI15+Model!BJ15+Model!BK15+Model!BL15+Model!BM15+Model!BN15+Model!BO15+Model!BP15+Model!BQ15+Model!BR15+Model!BS15 -> 0 | H12: =Model!BT15+Model!BU15+Model!BV15+Model!BW15+Model!BX15+Model!BY15+Model!BZ15+Model!CA15+Model!CB15+Model!CC15+Model!CD15+Model!CE15 -> 0 | I12: =Model!CF15+Model!CG15+Model!CH15 -> 0
A13: GC Personnel | B13: =Model!C16+Model!D16+Model!E16+Model!F16+Model!G16+Model!H16+Model!I16+Model!J16+Model!K16 -> -2218919 | C13: =Model!L16+Model!M16+Model!N16+Model!O16+Model!P16+Model!Q16+Model!R16+Model!S16+Model!T16+Model!U16+Model!V16+Model!W16 -> -3133195.4 | D13: =Model!X16+Model!Y16+Model!Z16+Model!AA16+Model!AB16+Model!AC16+Model!AD16+Model!AE16+Model!AF16+Model!AG16+Model!AH16+Model!AI16 -> -3195859.3 | E13: =Model!AJ16+Model!AK16+Model!AL16+Model!AM16+Model!AN16+Model!AO16+Model!AP16+Model!AQ16+Model!AR16+Model!AS16+Model!AT16+Model!AU16 -> -3259776.5 | F13: =Model!AV16+Model!AW16+Model!AX16+Model!AY16+Model!AZ16+Model!BA16+Model!BB16+Model!BC16+Model!BD16+Model!BE16+Model!BF16+Model!BG16 -> -3324972 | G13: =Model!BH16+Model!BI16+Model!BJ16+Model!BK16+Model!BL16+Model!BM16+Model!BN16+Model!BO16+Model!BP16+Model!BQ16+Model!BR16+Model!BS16 -> -3391471.4 | H13: =Model!BT16+Model!BU16+Model!BV16+Model!BW16+Model!BX16+Model!BY16+Model!BZ16+Model!CA16+Model!CB16+Model!CC16+Model!CD16+Model!CE16 -> -3459300.9 | I13: =Model!CF16+Model!CG16+Model!CH16 -> -869085.44
A14: SP Allocated to LV | B14: =Model!C17+Model!D17+Model!E17+Model!F17+Model!G17+Model!H17+Model!I17+Model!J17+Model!K17 -> -491250 | C14: =Model!L17+Model!M17+Model!N17+Model!O17+Model!P17+Model!Q17+Model!R17+Model!S17+Model!T17+Model!U17+Model!V17+Model!W17 -> -664825 | D14: =Model!X17+Model!Y17+Model!Z17+Model!AA17+Model!AB17+Model!AC17+Model!AD17+Model!AE17+Model!AF17+Model!AG17+Model!AH17+Model!AI17 -> -678121.5 | E14: =Model!AJ17+Model!AK17+Model!AL17+Model!AM17+Model!AN17+Model!AO17+Model!AP17+Model!AQ17+Model!AR17+Model!AS17+Model!AT17+Model!AU17 -> -691683.93 | F14: =Model!AV17+Model!AW17+Model!AX17+Model!AY17+Model!AZ17+Model!BA17+Model!BB17+Model!BC17+Model!BD17+Model!BE17+Model!BF17+Model!BG17 -> -705517.61 | G14: =Model!BH17+Model!BI17+Model!BJ17+Model!BK17+Model!BL17+Model!BM17+Model!BN17+Model!BO17+Model!BP17+Model!BQ17+Model!BR17+Model!BS17 -> -719627.96 | H14: =Model!BT17+Model!BU17+Model!BV17+Model!BW17+Model!BX17+Model!BY17+Model!BZ17+Model!CA17+Model!CB17+Model!CC17+Model!CD17+Model!CE17 -> -734020.52 | I14: =Model!CF17+Model!CG17+Model!CH17 -> -184409.1
A15: Total GC Costs | B15: =Model!C38+Model!D38+Model!E38+Model!F38+Model!G38+Model!H38+Model!I38+Model!J38+Model!K38 -> -4338997.1 | C15: =Model!L38+Model!M38+Model!N38+Model!O38+Model!P38+Model!Q38+Model!R38+Model!S38+Model!T38+Model!U38+Model!V38+Model!W38 -> -6572262 | D15: =Model!X38+Model!Y38+Model!Z38+Model!AA38+Model!AB38+Model!AC38+Model!AD38+Model!AE38+Model!AF38+Model!AG38+Model!AH38+Model!AI38 -> -6547139.4 | E15: =Model!AJ38+Model!AK38+Model!AL38+Model!AM38+Model!AN38+Model!AO38+Model!AP38+Model!AQ38+Model!AR38+Model!AS38+Model!AT38+Model!AU38 -> -5307176.1 | F15: =Model!AV38+Model!AW38+Model!AX38+Model!AY38+Model!AZ38+Model!BA38+Model!BB38+Model!BC38+Model!BD38+Model!BE38+Model!BF38+Model!BG38 -> -5413319.7 | G15: =Model!BH38+Model!BI38+Model!BJ38+Model!BK38+Model!BL38+Model!BM38+Model!BN38+Model!BO38+Model!BP38+Model!BQ38+Model!BR38+Model!BS38 -> -5521586 | H15: =Model!BT38+Model!BU38+Model!BV38+Model!BW38+Model!BX38+Model!BY38+Model!BZ38+Model!CA38+Model!CB38+Model!CC38+Model!CD38+Model!CE38 -> -5632017.8 | I15: =Model!CF38+Model!CG38+Model!CH38 -> -1414940.4
A16: GC Net Income | B16: =Model!C40+Model!D40+Model!E40+Model!F40+Model!G40+Model!H40+Model!I40+Model!J40+Model!K40 -> 2276079.6 | C16: =Model!L40+Model!M40+Model!N40+Model!O40+Model!P40+Model!Q40+Model!R40+Model!S40+Model!T40+Model!U40+Model!V40+Model!W40 -> 2837808.7 | D16: =Model!X40+Model!Y40+Model!Z40+Model!AA40+Model!AB40+Model!AC40+Model!AD40+Model!AE40+Model!AF40+Model!AG40+Model!AH40+Model!AI40 -> 1233383.5 | E16: =Model!AJ40+Model!AK40+Model!AL40+Model!AM40+Model!AN40+Model!AO40+Model!AP40+Model!AQ40+Model!AR40+Model!AS40+Model!AT40+Model!AU40 -> -1704179.3 | F16: =Model!AV40+Model!AW40+Model!AX40+Model!AY40+Model!AZ40+Model!BA40+Model!BB40+Model!BC40+Model!BD40+Model!BE40+Model!BF40+Model!BG40 -> -3690210 | G16: =Model!BH40+Model!BI40+Model!BJ40+Model!BK40+Model!BL40+Model!BM40+Model!BN40+Model!BO40+Model!BP40+Model!BQ40+Model!BR40+Model!BS40 -> -5521586 | H16: =Model!BT40+Model!BU40+Model!BV40+Model!BW40+Model!BX40+Model!BY40+Model!BZ40+Model!CA40+Model!CB40+Model!CC40+Model!CD40+Model!CE40 -> -5632017.8 | I16: =Model!CF40+Model!CG40+Model!CH40 -> -1414940.4
A17: GC Profit Margin % | B17: =IF((Model!C12+Model!D12+Model!E12+Model!F12+Model!G12+Model!H12+Model!I12+Model!J12+Model!K12)<>0,(Model!C40+Model!D40+Model!E40+Model!F40+Model!G40+Model!H40+Model!I40+Model!J40+Model!K40)/(Model!C12+Model!D12+Model!E12+Model!F12+Model!G12+Model!H12+Model!I12+Model!J12+Model!K12),0) -> 0.34407456 | C17: =IF((Model!L12+Model!M12+Model!N12+Model!O12+Model!P12+Model!Q12+Model!R12+Model!S12+Model!T12+Model!U12+Model!V12+Model!W12)<>0,(Model!L40+Model!M40+Model!N40+Model!O40+Model!P40+Model!Q40+Model!R40+Model!S40+Model!T40+Model!U40+Model!V40+Model!W40)/(Model!L12+Model!M12+Model!N12+Model!O12+Model!P12+Model!Q12+Model!R12+Model!S12+Model!T12+Model!U12+Model!V12+Model!W12),0) -> 0.30157145 | D17: =IF((Model!X12+Model!Y12+Model!Z12+Model!AA12+Model!AB12+Model!AC12+Model!AD12+Model!AE12+Model!AF12+Model!AG12+Model!AH12+Model!AI12)<>0,(Model!X40+Model!Y40+Model!Z40+Model!AA40+Model!AB40+Model!AC40+Model!AD40+Model!AE40+Model!AF40+Model!AG40+Model!AH40+Model!AI40)/(Model!X12+Model!Y12+Model!Z12+Model!AA12+Model!AB12+Model!AC12+Model!AD12+Model!AE12+Model!AF12+Model!AG12+Model!AH12+Model!AI12),0) -> 0.15852193 | E17: =IF((Model!AJ12+Model!AK12+Model!AL12+Model!AM12+Model!AN12+Model!AO12+Model!AP12+Model!AQ12+Model!AR12+Model!AS12+Model!AT12+Model!AU12)<>0,(Model!AJ40+Model!AK40+Model!AL40+Model!AM40+Model!AN40+Model!AO40+Model!AP40+Model!AQ40+Model!AR40+Model!AS40+Model!AT40+Model!AU40)/(Model!AJ12+Model!AK12+Model!AL12+Model!AM12+Model!AN12+Model!AO12+Model!AP12+Model!AQ12+Model!AR12+Model!AS12+Model!AT12+Model!AU12),0) -> -0.4729894 | F17: =IF((Model!AV12+Model!AW12+Model!AX12+Model!AY12+Model!AZ12+Model!BA12+Model!BB12+Model!BC12+Model!BD12+Model!BE12+Model!BF12+Model!BG12)<>0,(Model!AV40+Model!AW40+Model!AX40+Model!AY40+Model!AZ40+Model!BA40+Model!BB40+Model!BC40+Model!BD40+Model!BE40+Model!BF40+Model!BG40)/(Model!AV12+Model!AW12+Model!AX12+Model!AY12+Model!AZ12+Model!BA12+Model!BB12+Model!BC12+Model!BD12+Model!BE12+Model!BF12+Model!BG12),0) -> -2.141599 | G17: =IF((Model!BH12+Model!BI12+Model!BJ12+Model!BK12+Model!BL12+Model!BM12+Model!BN12+Model!BO12+Model!BP12+Model!BQ12+Model!BR12+Model!BS12)<>0,(Model!BH40+Model!BI40+Model!BJ40+Model!BK40+Model!BL40+Model!BM40+Model!BN40+Model!BO40+Model!BP40+Model!BQ40+Model!BR40+Model!BS40)/(Model!BH12+Model!BI12+Model!BJ12+Model!BK12+Model!BL12+Model!BM12+Model!BN12+Model!BO12+Model!BP12+Model!BQ12+Model!BR12+Model!BS12),0) -> 0 | H17: =IF((Model!BT12+Model!BU12+Model!BV12+Model!BW12+Model!BX12+Model!BY12+Model!BZ12+Model!CA12+Model!CB12+Model!CC12+Model!CD12+Model!CE12)<>0,(Model!BT40+Model!BU40+Model!BV40+Model!BW40+Model!BX40+Model!BY40+Model!BZ40+Model!CA40+Model!CB40+Model!CC40+Model!CD40+Model!CE40)/(Model!BT12+Model!BU12+Model!BV12+Model!BW12+Model!BX12+Model!BY12+Model!BZ12+Model!CA12+Model!CB12+Model!CC12+Model!CD12+Model!CE12),0) -> 0 | I17: =IF((Model!CF12+Model!CG12+Model!CH12)<>0,(Model!CF40+Model!CG40+Model!CH40)/(Model!CF12+Model!CG12+Model!CH12),0) -> 0
A19: Six Peak Revenue | B19: =Model!C63+Model!D63+Model!E63+Model!F63+Model!G63+Model!H63+Model!I63+Model!J63+Model!K63 -> 370447.9 | C19: =Model!L63+Model!M63+Model!N63+Model!O63+Model!P63+Model!Q63+Model!R63+Model!S63+Model!T63+Model!U63+Model!V63+Model!W63 -> 733409.56 | D19: =Model!X63+Model!Y63+Model!Z63+Model!AA63+Model!AB63+Model!AC63+Model!AD63+Model!AE63+Model!AF63+Model!AG63+Model!AH63+Model!AI63 -> 2216571.5 | E19: =Model!AJ63+Model!AK63+Model!AL63+Model!AM63+Model!AN63+Model!AO63+Model!AP63+Model!AQ63+Model!AR63+Model!AS63+Model!AT63+Model!AU63 -> 1366426.8 | F19: =Model!AV63+Model!AW63+Model!AX63+Model!AY63+Model!AZ63+Model!BA63+Model!BB63+Model!BC63+Model!BD63+Model!BE63+Model!BF63+Model!BG63 -> 1802920.1 | G19: =Model!BH63+Model!BI63+Model!BJ63+Model!BK63+Model!BL63+Model!BM63+Model!BN63+Model!BO63+Model!BP63+Model!BQ63+Model!BR63+Model!BS63 -> 822166.09 | H19: =Model!BT63+Model!BU63+Model!BV63+Model!BW63+Model!BX63+Model!BY63+Model!BZ63+Model!CA63+Model!CB63+Model!CC63+Model!CD63+Model!CE63 -> 819993 | I19: =Model!CF63+Model!CG63+Model!CH63 -> 231016
A20: Six Peak Expenses | B20: =Model!C84+Model!D84+Model!E84+Model!F84+Model!G84+Model!H84+Model!I84+Model!J84+Model!K84 -> -1120081.2 | C20: =Model!L84+Model!M84+Model!N84+Model!O84+Model!P84+Model!Q84+Model!R84+Model!S84+Model!T84+Model!U84+Model!V84+Model!W84 -> -1501176.6 | D20: =Model!X84+Model!Y84+Model!Z84+Model!AA84+Model!AB84+Model!AC84+Model!AD84+Model!AE84+Model!AF84+Model!AG84+Model!AH84+Model!AI84 -> -1531200.2 | E20: =Model!AJ84+Model!AK84+Model!AL84+Model!AM84+Model!AN84+Model!AO84+Model!AP84+Model!AQ84+Model!AR84+Model!AS84+Model!AT84+Model!AU84 -> -1725189.2 | F20: =Model!AV84+Model!AW84+Model!AX84+Model!AY84+Model!AZ84+Model!BA84+Model!BB84+Model!BC84+Model!BD84+Model!BE84+Model!BF84+Model!BG84 -> -2870017.6 | G20: =Model!BH84+Model!BI84+Model!BJ84+Model!BK84+Model!BL84+Model!BM84+Model!BN84+Model!BO84+Model!BP84+Model!BQ84+Model!BR84+Model!BS84 -> -2052206.3 | H20: =Model!BT84+Model!BU84+Model!BV84+Model!BW84+Model!BX84+Model!BY84+Model!BZ84+Model!CA84+Model!CB84+Model!CC84+Model!CD84+Model!CE84 -> -2188891.3 | I20: =Model!CF84+Model!CG84+Model!CH84 -> -551856.39
A21: Six Peak Net Income | B21: =Model!C86+Model!D86+Model!E86+Model!F86+Model!G86+Model!H86+Model!I86+Model!J86+Model!K86 -> -749633.35 | C21: =Model!L86+Model!M86+Model!N86+Model!O86+Model!P86+Model!Q86+Model!R86+Model!S86+Model!T86+Model!U86+Model!V86+Model!W86 -> -767767.06 | D21: =Model!X86+Model!Y86+Model!Z86+Model!AA86+Model!AB86+Model!AC86+Model!AD86+Model!AE86+Model!AF86+Model!AG86+Model!AH86+Model!AI86 -> 685371.37 | E21: =Model!AJ86+Model!AK86+Model!AL86+Model!AM86+Model!AN86+Model!AO86+Model!AP86+Model!AQ86+Model!AR86+Model!AS86+Model!AT86+Model!AU86 -> -358762.39 | F21: =Model!AV86+Model!AW86+Model!AX86+Model!AY86+Model!AZ86+Model!BA86+Model!BB86+Model!BC86+Model!BD86+Model!BE86+Model!BF86+Model!BG86 -> -1067097.5 | G21: =Model!BH86+Model!BI86+Model!BJ86+Model!BK86+Model!BL86+Model!BM86+Model!BN86+Model!BO86+Model!BP86+Model!BQ86+Model!BR86+Model!BS86 -> -1230040.2 | H21: =Model!BT86+Model!BU86+Model!BV86+Model!BW86+Model!BX86+Model!BY86+Model!BZ86+Model!CA86+Model!CB86+Model!CC86+Model!CD86+Model!CE86 -> -1368898.3 | I21: =Model!CF86+Model!CG86+Model!CH86 -> -320840.39
A23: Consolidated Net Income | B23: =Model!C95+Model!D95+Model!E95+Model!F95+Model!G95+Model!H95+Model!I95+Model!J95+Model!K95 -> 1526446.2 | C23: =Model!L95+Model!M95+Model!N95+Model!O95+Model!P95+Model!Q95+Model!R95+Model!S95+Model!T95+Model!U95+Model!V95+Model!W95 -> 2070041.6 | D23: =Model!X95+Model!Y95+Model!Z95+Model!AA95+Model!AB95+Model!AC95+Model!AD95+Model!AE95+Model!AF95+Model!AG95+Model!AH95+Model!AI95 -> 1918754.9 | E23: =Model!AJ95+Model!AK95+Model!AL95+Model!AM95+Model!AN95+Model!AO95+Model!AP95+Model!AQ95+Model!AR95+Model!AS95+Model!AT95+Model!AU95 -> -2062941.7 | F23: =Model!AV95+Model!AW95+Model!AX95+Model!AY95+Model!AZ95+Model!BA95+Model!BB95+Model!BC95+Model!BD95+Model!BE95+Model!BF95+Model!BG95 -> -4757307.5 | G23: =Model!BH95+Model!BI95+Model!BJ95+Model!BK95+Model!BL95+Model!BM95+Model!BN95+Model!BO95+Model!BP95+Model!BQ95+Model!BR95+Model!BS95 -> -6751626.3 | H23: =Model!BT95+Model!BU95+Model!BV95+Model!BW95+Model!BX95+Model!BY95+Model!BZ95+Model!CA95+Model!CB95+Model!CC95+Model!CD95+Model!CE95 -> -7000916.1 | I23: =Model!CF95+Model!CG95+Model!CH95 -> -1735780.8
A25: Steyn Group Fees
A26: Completion Guaranty Fee | B26: =Model!C79+Model!D79+Model!E79+Model!F79+Model!G79+Model!H79+Model!I79+Model!J79+Model!K79 -> 0 | C26: =Model!L79+Model!M79+Model!N79+Model!O79+Model!P79+Model!Q79+Model!R79+Model!S79+Model!T79+Model!U79+Model!V79+Model!W79 -> 0 | D26: =Model!X79+Model!Y79+Model!Z79+Model!AA79+Model!AB79+Model!AC79+Model!AD79+Model!AE79+Model!AF79+Model!AG79+Model!AH79+Model!AI79 -> 0 | E26: =Model!AJ79+Model!AK79+Model!AL79+Model!AM79+Model!AN79+Model!AO79+Model!AP79+Model!AQ79+Model!AR79+Model!AS79+Model!AT79+Model!AU79 -> 0 | F26: =Model!AV79+Model!AW79+Model!AX79+Model!AY79+Model!AZ79+Model!BA79+Model!BB79+Model!BC79+Model!BD79+Model!BE79+Model!BF79+Model!BG79 -> 0 | G26: =Model!BH79+Model!BI79+Model!BJ79+Model!BK79+Model!BL79+Model!BM79+Model!BN79+Model!BO79+Model!BP79+Model!BQ79+Model!BR79+Model!BS79 -> 0 | H26: =Model!BT79+Model!BU79+Model!BV79+Model!BW79+Model!BX79+Model!BY79+Model!BZ79+Model!CA79+Model!CB79+Model!CC79+Model!CD79+Model!CE79 -> 0 | I26: =Model!CF79+Model!CG79+Model!CH79 -> 0
A27: Liquidity Guarantee Fee | B27: =Model!C80+Model!D80+Model!E80+Model!F80+Model!G80+Model!H80+Model!I80+Model!J80+Model!K80 -> 0 | C27: =Model!L80+Model!M80+Model!N80+Model!O80+Model!P80+Model!Q80+Model!R80+Model!S80+Model!T80+Model!U80+Model!V80+Model!W80 -> 0 | D27: =Model!X80+Model!Y80+Model!Z80+Model!AA80+Model!AB80+Model!AC80+Model!AD80+Model!AE80+Model!AF80+Model!AG80+Model!AH80+Model!AI80 -> 0 | E27: =Model!AJ80+Model!AK80+Model!AL80+Model!AM80+Model!AN80+Model!AO80+Model!AP80+Model!AQ80+Model!AR80+Model!AS80+Model!AT80+Model!AU80 -> 0 | F27: =Model!AV80+Model!AW80+Model!AX80+Model!AY80+Model!AZ80+Model!BA80+Model!BB80+Model!BC80+Model!BD80+Model!BE80+Model!BF80+Model!BG80 -> 0 | G27: =Model!BH80+Model!BI80+Model!BJ80+Model!BK80+Model!BL80+Model!BM80+Model!BN80+Model!BO80+Model!BP80+Model!BQ80+Model!BR80+Model!BS80 -> 0 | H27: =Model!BT80+Model!BU80+Model!BV80+Model!BW80+Model!BX80+Model!BY80+Model!BZ80+Model!CA80+Model!CB80+Model!CC80+Model!CD80+Model!CE80 -> 0 | I27: =Model!CF80+Model!CG80+Model!CH80 -> 0
A28: Francis Steyn Fee + PIK (LIHTC) | B28: =Model!C81+Model!D81+Model!E81+Model!F81+Model!G81+Model!H81+Model!I81+Model!J81+Model!K81 -> 0 | C28: =Model!L81+Model!M81+Model!N81+Model!O81+Model!P81+Model!Q81+Model!R81+Model!S81+Model!T81+Model!U81+Model!V81+Model!W81 -> 0 | D28: =Model!X81+Model!Y81+Model!Z81+Model!AA81+Model!AB81+Model!AC81+Model!AD81+Model!AE81+Model!AF81+Model!AG81+Model!AH81+Model!AI81 -> 0 | E28: =Model!AJ81+Model!AK81+Model!AL81+Model!AM81+Model!AN81+Model!AO81+Model!AP81+Model!AQ81+Model!AR81+Model!AS81+Model!AT81+Model!AU81 -> -163365 | F28: =Model!AV81+Model!AW81+Model!AX81+Model!AY81+Model!AZ81+Model!BA81+Model!BB81+Model!BC81+Model!BD81+Model!BE81+Model!BF81+Model!BG81 -> -281718 | G28: =Model!BH81+Model!BI81+Model!BJ81+Model!BK81+Model!BL81+Model!BM81+Model!BN81+Model!BO81+Model!BP81+Model!BQ81+Model!BR81+Model!BS81 -> -134601.48 | H28: =Model!BT81+Model!BU81+Model!BV81+Model!BW81+Model!BX81+Model!BY81+Model!BZ81+Model!CA81+Model!CB81+Model!CC81+Model!CD81+Model!CE81 -> 0 | I28: =Model!CF81+Model!CG81+Model!CH81 -> 0
A29: Reseda Steyn Fee + PIK (LIHTC) | B29: =Model!C82+Model!D82+Model!E82+Model!F82+Model!G82+Model!H82+Model!I82+Model!J82+Model!K82 -> 0 | C29: =Model!L82+Model!M82+Model!N82+Model!O82+Model!P82+Model!Q82+Model!R82+Model!S82+Model!T82+Model!U82+Model!V82+Model!W82 -> 0 | D29: =Model!X82+Model!Y82+Model!Z82+Model!AA82+Model!AB82+Model!AC82+Model!AD82+Model!AE82+Model!AF82+Model!AG82+Model!AH82+Model!AI82 -> 0 | E29: =Model!AJ82+Model!AK82+Model!AL82+Model!AM82+Model!AN82+Model!AO82+Model!AP82+Model!AQ82+Model!AR82+Model!AS82+Model!AT82+Model!AU82 -> 0 | F29: =Model!AV82+Model!AW82+Model!AX82+Model!AY82+Model!AZ82+Model!BA82+Model!BB82+Model!BC82+Model!BD82+Model!BE82+Model!BF82+Model!BG82 -> -995239 | G29: =Model!BH82+Model!BI82+Model!BJ82+Model!BK82+Model!BL82+Model!BM82+Model!BN82+Model!BO82+Model!BP82+Model!BQ82+Model!BR82+Model!BS82 -> -292683 | H29: =Model!BT82+Model!BU82+Model!BV82+Model!BW82+Model!BX82+Model!BY82+Model!BZ82+Model!CA82+Model!CB82+Model!CC82+Model!CD82+Model!CE82 -> -312005 | I29: =Model!CF82+Model!CG82+Model!CH82 -> -74753.973
A30: 3rd St Steyn Fee + PIK (LIHTC) | B30: =Model!C83+Model!D83+Model!E83+Model!F83+Model!G83+Model!H83+Model!I83+Model!J83+Model!K83 -> 0 | C30: =Model!L83+Model!M83+Model!N83+Model!O83+Model!P83+Model!Q83+Model!R83+Model!S83+Model!T83+Model!U83+Model!V83+Model!W83 -> 0 | D30: =Model!X83+Model!Y83+Model!Z83+Model!AA83+Model!AB83+Model!AC83+Model!AD83+Model!AE83+Model!AF83+Model!AG83+Model!AH83+Model!AI83 -> 0 | E30: =Model!AJ83+Model!AK83+Model!AL83+Model!AM83+Model!AN83+Model!AO83+Model!AP83+Model!AQ83+Model!AR83+Model!AS83+Model!AT83+Model!AU83 -> 0 | F30: =Model!AV83+Model!AW83+Model!AX83+Model!AY83+Model!AZ83+Model!BA83+Model!BB83+Model!BC83+Model!BD83+Model!BE83+Model!BF83+Model!BG83 -> 0 | G30: =Model!BH83+Model!BI83+Model!BJ83+Model!BK83+Model!BL83+Model!BM83+Model!BN83+Model!BO83+Model!BP83+Model!BQ83+Model!BR83+Model!BS83 -> 0 | H30: =Model!BT83+Model!BU83+Model!BV83+Model!BW83+Model!BX83+Model!BY83+Model!BZ83+Model!CA83+Model!CB83+Model!CC83+Model!CD83+Model!CE83 -> -219466 | I30: =Model!CF83+Model!CG83+Model!CH83 -> -73155
A32: Debt Facilities
A33: Debt Facility Payment | B33: =Model!C100+Model!D100+Model!E100+Model!F100+Model!G100+Model!H100+Model!I100+Model!J100+Model!K100 -> -390000 | C33: =Model!L100+Model!M100+Model!N100+Model!O100+Model!P100+Model!Q100+Model!R100+Model!S100+Model!T100+Model!U100+Model!V100+Model!W100 -> -1495969.2 | D33: =Model!X100+Model!Y100+Model!Z100+Model!AA100+Model!AB100+Model!AC100+Model!AD100+Model!AE100+Model!AF100+Model!AG100+Model!AH100+Model!AI100 -> 0 | E33: =Model!AJ100+Model!AK100+Model!AL100+Model!AM100+Model!AN100+Model!AO100+Model!AP100+Model!AQ100+Model!AR100+Model!AS100+Model!AT100+Model!AU100 -> 0 | F33: =Model!AV100+Model!AW100+Model!AX100+Model!AY100+Model!AZ100+Model!BA100+Model!BB100+Model!BC100+Model!BD100+Model!BE100+Model!BF100+Model!BG100 -> 0 | G33: =Model!BH100+Model!BI100+Model!BJ100+Model!BK100+Model!BL100+Model!BM100+Model!BN100+Model!BO100+Model!BP100+Model!BQ100+Model!BR100+Model!BS100 -> 0 | H33: =Model!BT100+Model!BU100+Model!BV100+Model!BW100+Model!BX100+Model!BY100+Model!BZ100+Model!CA100+Model!CB100+Model!CC100+Model!CD100+Model!CE100 -> 0 | I33: =Model!CF100+Model!CG100+Model!CH100 -> 0
A34: Debt Facility Balance | B34: =Model!K101 -> 1404377.6 | C34: =Model!W101 -> 0 | D34: =Model!AI101 -> 0 | E34: =Model!AU101 -> 0 | F34: =Model!BG101 -> 0 | G34: =Model!BS101 -> 0 | H34: =Model!CE101 -> 0 | I34: =Model!CH101 -> 0
A35: Row Run Capital Payment | B35: =Model!C106+Model!D106+Model!E106+Model!F106+Model!G106+Model!H106+Model!I106+Model!J106+Model!K106 -> 0 | C35: =Model!L106+Model!M106+Model!N106+Model!O106+Model!P106+Model!Q106+Model!R106+Model!S106+Model!T106+Model!U106+Model!V106+Model!W106 -> -250000 | D35: =Model!X106+Model!Y106+Model!Z106+Model!AA106+Model!AB106+Model!AC106+Model!AD106+Model!AE106+Model!AF106+Model!AG106+Model!AH106+Model!AI106 -> -250000 | E35: =Model!AJ106+Model!AK106+Model!AL106+Model!AM106+Model!AN106+Model!AO106+Model!AP106+Model!AQ106+Model!AR106+Model!AS106+Model!AT106+Model!AU106 -> -250000 | F35: =Model!AV106+Model!AW106+Model!AX106+Model!AY106+Model!AZ106+Model!BA106+Model!BB106+Model!BC106+Model!BD106+Model!BE106+Model!BF106+Model!BG106 -> 0 | G35: =Model!BH106+Model!BI106+Model!BJ106+Model!BK106+Model!BL106+Model!BM106+Model!BN106+Model!BO106+Model!BP106+Model!BQ106+Model!BR106+Model!BS106 -> 0 | H35: =Model!BT106+Model!BU106+Model!BV106+Model!BW106+Model!BX106+Model!BY106+Model!BZ106+Model!CA106+Model!CB106+Model!CC106+Model!CD106+Model!CE106 -> 0 | I35: =Model!CF106+Model!CG106+Model!CH106 -> 0
A36: Row Run Capital Balance | B36: =Model!K107 -> 1000000 | C36: =Model!W107 -> 750000 | D36: =Model!AI107 -> 500000 | E36: =Model!AU107 -> 250000 | F36: =Model!BG107 -> 250000 | G36: =Model!BS107 -> 250000 | H36: =Model!CE107 -> 250000 | I36: =Model!CH107 -> 250000
A37: PIK Repayment (in Steyn + PIK above) | B37: =Model!C154+Model!D154+Model!E154+Model!F154+Model!G154+Model!H154+Model!I154+Model!J154+Model!K154 -> 0 | C37: =Model!L154+Model!M154+Model!N154+Model!O154+Model!P154+Model!Q154+Model!R154+Model!S154+Model!T154+Model!U154+Model!V154+Model!W154 -> 0 | D37: =Model!X154+Model!Y154+Model!Z154+Model!AA154+Model!AB154+Model!AC154+Model!AD154+Model!AE154+Model!AF154+Model!AG154+Model!AH154+Model!AI154 -> 0 | E37: =Model!AJ154+Model!AK154+Model!AL154+Model!AM154+Model!AN154+Model!AO154+Model!AP154+Model!AQ154+Model!AR154+Model!AS154+Model!AT154+Model!AU154 -> 0 | F37: =Model!AV154+Model!AW154+Model!AX154+Model!AY154+Model!AZ154+Model!BA154+Model!BB154+Model!BC154+Model!BD154+Model!BE154+Model!BF154+Model!BG154 -> 0 | G37: =Model!BH154+Model!BI154+Model!BJ154+Model!BK154+Model!BL154+Model!BM154+Model!BN154+Model!BO154+Model!BP154+Model!BQ154+Model!BR154+Model!BS154 -> 0 | H37: =Model!BT154+Model!BU154+Model!BV154+Model!BW154+Model!BX154+Model!BY154+Model!BZ154+Model!CA154+Model!CB154+Model!CC154+Model!CD154+Model!CE154 -> 0 | I37: =Model!CF154+Model!CG154+Model!CH154 -> 0
A38: Investment Capital Outstanding | B38: =Model!K114+Model!K119+Model!K124+Model!K129 -> 2378399.9 | C38: =Model!W114+Model!W119+Model!W124+Model!W129 -> 1714451.1 | D38: =Model!AI114+Model!AI119+Model!AI124+Model!AI129 -> 1035128.5 | E38: =Model!AU114+Model!AU119+Model!AU124+Model!AU129 -> 1199352.1 | F38: =Model!BG114+Model!BG119+Model!BG124+Model!BG129 -> 975331.5 | G38: =Model!BS114+Model!BS119+Model!BS124+Model!BS129 -> 820735.29 | H38: =Model!CE114+Model!CE119+Model!CE124+Model!CE129 -> 621470.38 | I38: =Model!CH114+Model!CH119+Model!CH124+Model!CH129 -> 570021.55
A40: Bonding Outstanding | B40: =Model!K140 -> 89880219 | C40: =Model!W140 -> 56473336 | D40: =Model!AI140 -> 46152167 | E40: =Model!AU140 -> 13258585 | F40: =Model!BG140 -> 0 | G40: =Model!BS140 -> 0 | H40: =Model!CE140 -> 0 | I40: =Model!CH140 -> 0
A42: LV Ending Cash | B42: =Model!K147 -> 3927995.3 | C42: =Model!W147 -> 6765804 | D42: =Model!AI147 -> 7999187.5 | E42: =Model!AU147 -> 6295008.2 | F42: =Model!BG147 -> 2604798.2 | G42: =Model!BS147 -> -2916787.9 | H42: =Model!CE147 -> -8548805.6 | I42: =Model!CH147 -> -9963746.1
A43: SP Ending Cash | B43: =Model!K155 -> -688002.19 | C43: =Model!W155 -> -3201738.5 | D43: =Model!AI155 -> -2766367.1 | E43: =Model!AU155 -> -3375129.5 | F43: =Model!BG155 -> -4442227 | G43: =Model!BS155 -> -5672267.3 | H43: =Model!CE155 -> -7041165.6 | I43: =Model!CH155 -> -7362005.9
A44: Tax Distribution (30% Consol NI) | B44: =Model!C159+Model!D159+Model!E159+Model!F159+Model!G159+Model!H159+Model!I159+Model!J159+Model!K159 -> 0 | C44: =Model!L159+Model!M159+Model!N159+Model!O159+Model!P159+Model!Q159+Model!R159+Model!S159+Model!T159+Model!U159+Model!V159+Model!W159 -> -457933.87 | D44: =Model!X159+Model!Y159+Model!Z159+Model!AA159+Model!AB159+Model!AC159+Model!AD159+Model!AE159+Model!AF159+Model!AG159+Model!AH159+Model!AI159 -> -621012.49 | E44: =Model!AJ159+Model!AK159+Model!AL159+Model!AM159+Model!AN159+Model!AO159+Model!AP159+Model!AQ159+Model!AR159+Model!AS159+Model!AT159+Model!AU159 -> -575626.47 | F44: =Model!AV159+Model!AW159+Model!AX159+Model!AY159+Model!AZ159+Model!BA159+Model!BB159+Model!BC159+Model!BD159+Model!BE159+Model!BF159+Model!BG159 -> 0 | G44: =Model!BH159+Model!BI159+Model!BJ159+Model!BK159+Model!BL159+Model!BM159+Model!BN159+Model!BO159+Model!BP159+Model!BQ159+Model!BR159+Model!BS159 -> 0 | H44: =Model!BT159+Model!BU159+Model!BV159+Model!BW159+Model!BX159+Model!BY159+Model!BZ159+Model!CA159+Model!CB159+Model!CC159+Model!CD159+Model!CE159 -> 0 | I44: =Model!CF159+Model!CG159+Model!CH159 -> 0
A45: Total Ending Cash | B45: =Model!K160 -> 3239993.1 | C45: =Model!W160 -> 3564065.5 | D45: =Model!AI160 -> 5232820.4 | E45: =Model!AU160 -> 2919878.7 | F45: =Model!BG160 -> -1837428.8 | G45: =Model!BS160 -> -8589055.1 | H45: =Model!CE160 -> -15589971 | I45: =Model!CH160 -> -17325752

Sheet Model
A1: Six Peak Capital - Financial Projections
C2: 46113 | D2: 46143 | E2: 46174 | F2: 46204 | G2: 46235 | H2: 46266 | I2: 46296 | J2: 46327 | K2: 46357 | L2: 46388 | M2: 46419 | N2: 46447 | O2: 46478 | P2: 46508 | Q2: 46539 | R2: 46569 | S2: 46600 | T2: 46631 | U2: 46661 | V2: 46692 | W2: 46722 | X2: 46753 | Y2: 46784 | Z2: 46813 | AA2: 46844 | AB2: 46874 | AC2: 46905 | AD2: 46935 | AE2: 46966 | AF2: 46997 | AG2: 47027 | AH2: 47058 | AI2: 47088 | AJ2: 47119 | AK2: 47150 | AL2: 47178 | AM2: 47209 | AN2: 47239 | AO2: 47270 | AP2: 47300 | AQ2: 47331 | AR2: 47362 | AS2: 47392 | AT2: 47423 | AU2: 47453 | AV2: 47484 | AW2: 47515 | AX2: 47543 | AY2: 47574 | AZ2: 47604 | BA2: 47635 | BB2: 47665 | BC2: 47696 | BD2: 47727 | BE2: 47757 | BF2: 47788 | BG2: 47818 | BH2: 47849 | BI2: 47880 | BJ2: 47908 | BK2: 47939 | BL2: 47969 | BM2: 48000 | BN2: 48030 | BO2: 48061 | BP2: 48092 | BQ2: 48122 | BR2: 48153 | BS2: 48183 | BT2: 48214 | BU2: 48245 | BV2: 48274 | BW2: 48305 | BX2: 48335 | BY2: 48366 | BZ2: 48396 | CA2: 48427 | CB2: 48458 | CC2: 48488 | CD2: 48519 | CE2: 48549 | CF2: 48580 | CG2: 48611 | CH2: 48639
A3: Month # | C3: 1 | D3: 2 | E3: 3 | F3: 4 | G3: 5 | H3: 6 | I3: 7 | J3: 8 | K3: 9 | L3: 10 | M3: 11 | N3: 12 | O3: 13 | P3: 14 | Q3: 15 | R3: 16 | S3: 17 | T3: 18 | U3: 19 | V3: 20 | W3: 21 | X3: 22 | Y3: 23 | Z3: 24 | AA3: 25 | AB3: 26 | AC3: 27 | AD3: 28 | AE3: 29 | AF3: 30 | AG3: 31 | AH3: 32 | AI3: 33 | AJ3: 34 | AK3: 35 | AL3: 36 | AM3: 37 | AN3: 38 | AO3: 39 | AP3: 40 | AQ3: 41 | AR3: 42 | AS3: 43 | AT3: 44 | AU3: 45 | AV3: 46 | AW3: 47 | AX3: 48 | AY3: 49 | AZ3: 50 | BA3: 51 | BB3: 52 | BC3: 53 | BD3: 54 | BE3: 55 | BF3: 56 | BG3: 57 | BH3: 58 | BI3: 59 | BJ3: 60 | BK3: 61 | BL3: 62 | BM3: 63 | BN3: 64 | BO3: 65 | BP3: 66 | BQ3: 67 | BR3: 68 | BS3: 69 | BT3: 70 | BU3: 71 | BV3: 72 | BW3: 73 | BX3: 74 | BY3: 75 | BZ3: 76 | CA3: 77 | CB3: 78 | CC3: 79 | CD3: 80 | CE3: 81 | CF3: 82 | CG3: 83 | CH3: 84
A5: GC CONSTRUCTION P&L | C5: Crenshaw, Ramsgate, Califa, Whipple, Nelrose | F5: Francis | G5: Klump | H5: Scott | I5: Lexington, Denny | J5: Acama | O5: Reseda | R5: HVN Pipeline 1 | U5: HVN Pipeline 2 | AC5: 3rd St
A6: GC Revenue
